Workbook
Name DiasCategorias: #REF!
Name DiasCategorias: #REF!
Name FechaInicio: #REF!
Name FechaInicio: #REF!
Name x_customMessage: Procesos!$AG$1129

Sheet Procesos
C1: SEGUIMIENTO A TÉRMINOS PROCESALES - PROCESOS | J1: =IF(G1085="","",(IF(N1085="","Pendiente primera actuación",IF(N1085="N.A.","N.A.",IF(NETWORKDAYS((G1085+1),N1085,'Días No Laborales'!$A$2:$U$145)<=20,"SI","NO"))))) -> SI
B4: Juzgado: | C4: JUZGADO 004 CIVIL MUNICIPAL DE ENVIDAGO
A6: N° | B6: Radicado | C6: Clase de proceso | D6: Sub clase de proceso | E6: Cuantía | F6: Concepto de Ingreso | G6: Fecha de ingreso | H6: Demandante(s) | I6: M | J6: F | K6: Demandado(s) | L6: M | M6: F | N6: FECHA DEL AUTO PRIMERA ACTUACIÓN dd-mm-aaaa | O6: ¿CUMPLIÓ PRIMERA ACTUACIÓN DENTRO DEL TÉRMINO? (SI/NO) | P6: OBSERVACIONES (EN CASO DE NO CUMPLIR LOS TÉRMINOS) | Q6: PERSPECTIVA DE GÉNERO (SI/NO) | R6: Fecha de notificación al último de los ddos | S6: ALERTA | T6: Pérdida de competencia en 1a. Instancia | U6: Pérdida de competencia en 2a instancia | V6: No. DE DÍAS | W6: FECHA DE SENTENCIA O DECISIÓN DEFINITIVA PRIMERA INSTANCIA (dd-mm-aaaa) | X6: FINALIZADO / DESCARGA EN ESTADÍSTICA | Y6: FECHA DE SENTENCIA O DECISIÓN DEFINITIVA SEGUNDA INSTANCIA (dd-mm-aaaa) | Z6: No. DE DÍAS FIN DEL PROCESO PRIMERA INSTANCIA | AA6: No. DE DÍAS FIN DEL PROCESO SEGUNDA INSTANCIA | AB6: CAUSAL DE TERMINACIÓN DEFINITIVA (ACORDE CON LA ESTADÍSTICA) | AC6: TRIMESTRE DE SALIDA | AD6: ULTIMA ACTUACIÓN | AE6: FECHA ÚLTIMA ACTUACIÓN | AF6: TRAMITADOR | AG6: ORIGEN | AH6: UBICACIÓN | AI6: FECHA ARCHIVO DEFINITIVO | AJ6: INICIO TP | AK6: FIN TP | AL6: FECHA TERMINACIÓN TRÁMITE POSTERIOR | AM6: OBSERVACIONES
C7: RESTITUCION BIEN INMUEBLE | D7: VERBAL SUMARIO | E7: MINIMA | F7: REMITIDA POR OTRO DESPACHO | G7: 45565 | H7: VISTA INMOBILIARIA SAS | I7: 1 | J7: 0 | K7: SEBASTIAN COLORADO SALZAR | L7: 1 | M7: 0 | N7: 45565 | O7: =IF(G7="","",(IF(N7="","Pendiente primera actuación",IF(N7="N.A.","N.A.",IF(NETWORKDAYS((G7+1),N7,'Días No Laborales'!$A$2:$U$145)<=20,"SI","NO"))))) -> SI | Q7: NO | Y7: N/A | Z7: =IF(B7="","",IF(W7="","Pendiente de sentencia",IF(W7="N.A.","N.A.",DAYS360(G7,W7)))) -> Pendiente de sentencia | AA7: N/A | AD7: FIJA CAUCION | AE7: 45708 | AF7: CAROLINA | AG7: 01 CIVIL MCPAL | AH7: ELECTRONICO
A8: 1 | B8: Así mismo se deberá cumplir la ritualidad contemplada en el artículo 375 del CGP, sumando a la fijación de la valla que cumpla con (i) las dimensiones legales; (ii) la información que debe contener y (iii) el lugar de ubicación y el tiempo que debe permanecer alii, conforme al numeral 7° del multicitado canon 375 de la ley 1564 de 2012, y la inclusión mediática alii contemplada en el registro de procesos de pertenencia. | C8: PERTENENCIA | D8: VERBAL | E8: MINIMA | F8: REMITIDA POR OTRO DESPACHO | G8: 45568 | H8: IMPORTADORA GIRATORIA SAS | I8: 1 | J8: 0 | K8: HECTOR EMILIO LOPERA QUICENO | L8: 1 | M8: 0 | N8: 45568 | O8: =IF(G8="","",(IF(N8="","Pendiente primera actuación",IF(N8="N.A.","N.A.",IF(NETWORKDAYS((G8+1),N8,'Días No Laborales'!$A$2:$U$145)<=20,"SI","NO"))))) -> SI | Q8: NO | Y8: N/A | Z8: =IF(B8="","",IF(W8="","Pendiente de sentencia",IF(W8="N.A.","N.A.",DAYS360(G8,W8)))) -> Pendiente de sentencia | AA8: N/A | AD8: REQUIERE | AE8: 45842 | AF8: CAMILA | AG8: 01 CIVIL MCPAL | AH8: ELECTRONICO | AM8: P. OFICIOS - EMPLAZAMIENTO
A9: 2 | C9: PRESCRIPCIÓN EXTINTIVA OBLIGACION HIPOTECARIA | D9: DECLARATIVO VERBAL SUMARIO OTROS PROCESO | E9: MINIMA | F9: REMITIDA POR OTRO DESPACHO | G9: 45566 | H9: HERNANDO DE JESUS GONZALEZ CORTES | I9: 1 | J9: 0 | K9: MARIA JUDITH GONZALES DE GUTIERREZ | L9: 0 | M9: 1 | N9: 45568 | O9: =IF(G9="","",(IF(N9="","Pendiente primera actuación",IF(N9="N.A.","N.A.",IF(NETWORKDAYS((G9+1),N9,'Días No Laborales'!$A$2:$U$145)<=20,"SI","NO"))))) -> SI | Q9: NO | W9: 45670 | Y9: N/A | Z9: =IF(B9="","",IF(W9="","Pendiente de sentencia",IF(W9="N.A.","N.A.",DAYS360(G9,W9)))) -> 102 | AA9: N/A | AB9: DESISTIMIENTO TACITO | AC9: 2025-1 | AD9: TERMINA PROCESO POR DESISTIMIENTO | AE9: 45670 | AF9: LACIDES | AG9: 01 CIVIL MCPAL | AH9: ELECTRONICO | AI9: 45715 | AM9: Vence Req. 05/12/2024
A10: 3 | B10: Se le informa a la parte actora que una vez se encuentre instalada la valla o el aviso, deberá aportar fotografías del inmueble en las que se observe el contenido de ellos y la certificación expedida por la empresa responsable de elaborar la valla con las dimensiones requeridas. La valla o el aviso deberán permanecer instalados hasta la audiencia de instrucción y juzgamiento. | C10: NULIDAD ABSOLUTA CONTRATO | D10: DECLARATIVO VERBAL OTROS PROCESO | E10: MENOR | F10: REMITIDA POR OTRO DESPACHO | G10: 45568 | H10: NATHALIA CORDOBA CASTAÑO | I10: 0 | J10: 1 | K10: JULIANA URIBE MEJIA | L10: 0 | M10: 1 | N10: 45568 | O10: =IF(G10="","",(IF(N10="","Pendiente primera actuación",IF(N10="N.A.","N.A.",IF(NETWORKDAYS((G10+1),N10,'Días No Laborales'!$A$2:$U$145)<=20,"SI","NO"))))) -> SI | Q10: NO | Y10: N/A | Z10: =IF(B10="","",IF(W10="","Pendiente de sentencia",IF(W10="N.A.","N.A.",DAYS360(G10,W10)))) -> Pendiente de sentencia | AA10: N/A | AD10: INCORPORA Y PONE EN CONOCIMIENTO | AE10: 45797 | AF10: CAMILA | AG10: 01 CIVIL MCPAL | AH10: ELECTRONICO
A11: 4 | B11: 001-2023-00453 | C11: RESPONSABILIDAD CIVIL EXTRACONTRACTUAL | D11: DECLARATIVO VERBAL SUMARIO OTROS PROCESO | E11: MINIMA | F11: REMITIDA POR OTRO DESPACHO | G11: 45566 | H11: CESAR AUGUSTO CALLE OQUENDO | I11: 1 | J11: 0 | K11: SANTIAGO DUQUE ALVAREZ Y OTROS | L11: 0 | M11: 1 | N11: 45566 | O11: =IF(G11="","",(IF(N11="","Pendiente primera actuación",IF(N11="N.A.","N.A.",IF(NETWORKDAYS((G11+1),N11,'Días No Laborales'!$A$2:$U$145)<=20,"SI","NO"))))) -> SI | Q11: NO | W11: 45721 | Y11: N/A | Z11: =IF(B11="","",IF(W11="","Pendiente de sentencia",IF(W11="N.A.","N.A.",DAYS360(G11,W11)))) -> 154 | AA11: N/A | AB11: DESISTIMIENTO TACITO | AC11: 2025-1 | AD11: DECRETA DESISTIMIENTO TACITO ART. 317 | AE11: 45721 | AF11: LACIDES | AG11: 01 CIVIL MCPAL | AH11: ELECTRONICO | AI11: 45729 | AM11: Vence Req. 05/12/2024
A12: 5 | B12: 001-2023-00619 | C12: RESTITUCION BIEN INMUEBLE | D12: VERBAL SUMARIO | E12: MINIMA | F12: REMITIDA POR OTRO DESPACHO | G12: 45565 | H12: GERENCIAR Y SERVIR SAS | I12: 1 | J12: 0 | K12: HEYMAR LOPEZ VILLAMIZAR | L12: 1 | M12: 0 | N12: 45565 | O12: =IF(G12="","",(IF(N12="","Pendiente primera actuación",IF(N12="N.A.","N.A.",IF(NETWORKDAYS((G12+1),N12,'Días No Laborales'!$A$2:$U$145)<=20,"SI","NO"))))) -> SI | Q12: NO | W12: 45580 | Y12: N/A | Z12: =IF(B12="","",IF(W12="","Pendiente de sentencia",IF(W12="N.A.","N.A.",DAYS360(G12,W12)))) -> 15 | AA12: N/A | AB12: SENTENCIA ANTICIPADA | AC12: 2024-4 | AD12: SENTENCIA ANTICIPADA | AE12: 45580 | AF12: CAROLINA | AG12: 01 CIVIL MCPAL | AH12: ELECTRONICO
A13: 6 | B13: 001-2023-00960 | C13: PAGO POR CONSIGNACIÓN | D13: DECLARATIVO VERBAL SUMARIO OTROS PROCESO | E13: MINIMA | F13: REMITIDA POR OTRO DESPACHO | G13: 45567 | H13: MARIA DEL CARMEN RESTREPO VELEZ | I13: 0 | J13: 1 | K13: BLANCA LIGIA PEREZ MONA | L13: 0 | M13: 1 | N13: 45567 | O13: =IF(G13="","",(IF(N13="","Pendiente primera actuación",IF(N13="N.A.","N.A.",IF(NETWORKDAYS((G13+1),N13,'Días No Laborales'!$A$2:$U$145)<=20,"SI","NO"))))) -> SI | Q13: NO | Y13: N/A | Z13: =IF(B13="","",IF(W13="","Pendiente de sentencia",IF(W13="N.A.","N.A.",DAYS360(G13,W13)))) -> Pendiente de sentencia | AA13: N/A | AD13: ORDENA REAJUSTAR CONSIGNACION | AE13: 45840 | AF13: LACIDES | AG13: 01 CIVIL MCPAL | AH13: ELECTRONICO
A14: 7 | B14: 001-2023-01227 | C14: RESTITUCION BIEN INMUEBLE | D14: VERBAL SUMARIO | E14: MINIMA | F14: REMITIDA POR OTRO DESPACHO | G14: 45567 | H14: HERNAN ALBERTO GARCES BEDOYA | I14: 1 | J14: 0 | K14: LINA MARCELA MEJIA LONDOÑO | L14: 0 | M14: 1 | N14: 45567 | O14: =IF(G14="","",(IF(N14="","Pendiente primera actuación",IF(N14="N.A.","N.A.",IF(NETWORKDAYS((G14+1),N14,'Días No Laborales'!$A$2:$U$145)<=20,"SI","NO"))))) -> SI | Q14: NO | W14: 45811 | Y14: N/A | Z14: =IF(B14="","",IF(W14="","Pendiente de sentencia",IF(W14="N.A.","N.A.",DAYS360(G14,W14)))) -> 241 | AA14: N/A | AB14: DESISTIMIENTO TACITO | AC14: 2025-2 | AD14: DESISTIMIENTO TACITO PROCESO | AE14: 45811 | AF14: CAROLINA | AG14: 01 CIVIL MCPAL | AH14: ELECTRONICO
A15: 8 | B15: 001-2023-01613 | C15: EJECUTIVO | D15: POR SUMAS DE DINERO | E15: MINIMA | F15: REMITIDA POR OTRO DESPACHO | G15: 45568 | H15: DAISY JANETH PASCUAL MONSALVE | I15: 0 | J15: 1 | K15: JUAN ESTEBAN VANEGAS ECHAVARRIA | L15: 1 | M15: 0 | N15: 45568 | O15: =IF(G15="","",(IF(N15="","Pendiente primera actuación",IF(N15="N.A.","N.A.",IF(NETWORKDAYS((G15+1),N15,'Días No Laborales'!$A$2:$U$145)<=20,"SI","NO"))))) -> SI | Q15: NO | Y15: N/A | Z15: =IF(B15="","",IF(W15="","Pendiente de sentencia",IF(W15="N.A.","N.A.",DAYS360(G15,W15)))) -> Pendiente de sentencia | AA15: N/A | AD15: REQUIERE 30 DÌAS | AE15: 45713 | AF15: CAROLINA | AG15: 01 CIVIL MCPAL | AH15: ELECTRONICO
A16: 9 | B16: 001-2023-01614 | C16: EJECUTIVO | D16: POR SUMAS DE DINERO | E16: MINIMA | F16: REMITIDA POR OTRO DESPACHO | G16: 45568 | H16: URBANIZACIÓN RESERVA DE LA MARIA | I16: 1 | J16: 0 | K16: BANCOLOMBIA Y OTROS | L16: 1 | M16: 0 | N16: 45568 | O16: =IF(G16="","",(IF(N16="","Pendiente primera actuación",IF(N16="N.A.","N.A.",IF(NETWORKDAYS((G16+1),N16,'Días No Laborales'!$A$2:$U$145)<=20,"SI","NO"))))) -> SI | Q16: NO | W16: 45686 | Y16: N/A | Z16: =IF(B16="","",IF(W16="","Pendiente de sentencia",IF(W16="N.A.","N.A.",DAYS360(G16,W16)))) -> 116 | AA16: N/A | AB16: TERMINA POR PAGO TOTAL | AC16: 2025-1 | AD16: INCORPORA Y RESUELVE | AE16: 45859 | AF16: CAMILA | AG16: 01 CIVIL MCPAL | AH16: ELECTRONICO | AI16: 46004
A17: 10 | B17: 001-2024-00018 | C17: EJECUTIVO | D17: POR SUMAS DE DINERO | E17: MENOR | F17: REMITIDA POR OTRO DESPACHO | G17: 45568 | H17: BANCO DAVIVIENDA | I17: 1 | J17: 0 | K17: WILLIAM GALLEGO HURTADO | L17: 1 | M17: 0 | N17: 45568 | O17: =IF(G17="","",(IF(N17="","Pendiente primera actuación",IF(N17="N.A.","N.A.",IF(NETWORKDAYS((G17+1),N17,'Días No Laborales'!$A$2:$U$145)<=20,"SI","NO"))))) -> SI | Q17: NO | Y17: N/A | Z17: =IF(B17="","",IF(W17="","Pendiente de sentencia",IF(W17="N.A.","N.A.",DAYS360(G17,W17)))) -> Pendiente de sentencia | AA17: N/A | AD17: REQUIERE 5 DIAS | AE17: 45841 | AF17: LACIDES | AG17: 01 CIVIL MCPAL | AH17: ELECTRONICO
A18: 11 | B18: 001-2024-00031 | C18: EJECUTIVO | D18: POR SUMAS DE DINERO | E18: MINIMA | F18: REMITIDA POR OTRO DESPACHO | G18: 45568 | H18: SEGUROS COMERCIALES BOLIVAR | I18: 1 | J18: 0 | K18: LOURDES GARCIA Y OTROS | L18: 0 | M18: 1 | N18: 45568 | O18: =IF(G18="","",(IF(N18="","Pendiente primera actuación",IF(N18="N.A.","N.A.",IF(NETWORKDAYS((G18+1),N18,'Días No Laborales'!$A$2:$U$145)<=20,"SI","NO"))))) -> SI | Q18: NO | W18: 45670 | Y18: N/A | Z18: =IF(B18="","",IF(W18="","Pendiente de sentencia",IF(W18="N.A.","N.A.",DAYS360(G18,W18)))) -> 100 | AA18: N/A | AB18: ORDENA SEGUIR ADELANTE CON LA EJECUCIÓN | AC18: 2025-1 | AD18: REQUIERE 5 DIAS | AE18: 45841 | AF18: LACIDES | AG18: 01 CIVIL MCPAL | AH18: ELECTRONICO | AJ18: X
A19: 12 | B19: 001-2024-00032 | C19: EJECUTIVO | D19: POR SUMAS DE DINERO | E19: MINIMA | F19: REMITIDA POR OTRO DESPACHO | G19: 45568 | H19: RENTA INVERSIONES INMOBILIARIA | I19: 1 | J19: 0 | K19: DOUGLAS ENRIQUE VALBUENA RINCON | L19: 1 | M19: 0 | N19: 45568 | O19: =IF(G19="","",(IF(N19="","Pendiente primera actuación",IF(N19="N.A.","N.A.",IF(NETWORKDAYS((G19+1),N19,'Días No Laborales'!$A$2:$U$145)<=20,"SI","NO"))))) -> SI | Q19: NO | Y19: N/A | Z19: =IF(B19="","",IF(W19="","Pendiente de sentencia",IF(W19="N.A.","N.A.",DAYS360(G19,W19)))) -> Pendiente de sentencia | AA19: N/A | AD19: TERMINA DESISTIMIENTO TACITO MEDIDA | AE19: 45807 | AF19: CAROLINA | AG19: 01 CIVIL MCPAL | AH19: ELECTRONICO
A20: 13 | B20: 001-2024-00035 | C20: EJECUTIVO | D20: POR SUMAS DE DINERO | E20: MENOR | F20: REMITIDA POR OTRO DESPACHO | G20: 45568 | H20: BANCO SCOTIBANK COLPATRIA S.A | I20: 1 | J20: 0 | K20: PAULA ANDREA GALEANO MARULANDA | L20: 0 | M20: 1 | N20: 45568 | O20: =IF(G20="","",(IF(N20="","Pendiente primera actuación",IF(N20="N.A.","N.A.",IF(NETWORKDAYS((G20+1),N20,'Días No Laborales'!$A$2:$U$145)<=20,"SI","NO"))))) -> SI | Q20: NO | W20: 45572 | Y20: N/A | Z20: =IF(B20="","",IF(W20="","Pendiente de sentencia",IF(W20="N.A.","N.A.",DAYS360(G20,W20)))) -> 4 | AA20: N/A | AB20: ORDENA SEGUIR ADELANTE CON LA EJECUCIÓN | AC20: 2024-4 | AD20: TERMINA X PAGO CON OSAE | AE20: 45862 | AF20: CAMILA | AG20: 01 CIVIL MCPAL | AH20: ELECTRONICO | AJ20: X
A21: 14 | B21: 001-2024-00053 | C21: EJECUTIVO | D21: POR SUMAS DE DINERO | E21: MENOR | F21: REMITIDA POR OTRO DESPACHO | G21: 45568 | H21: BANCO DE OCCIDENTE S.A | I21: 1 | J21: 0 | K21: DIANA CAROLINA LOPERA FLOREZ | L21: 0 | M21: 1 | N21: 45568 | O21: =IF(G21="","",(IF(N21="","Pendiente primera actuación",IF(N21="N.A.","N.A.",IF(NETWORKDAYS((G21+1),N21,'Días No Laborales'!$A$2:$U$145)<=20,"SI","NO"))))) -> SI | Q21: NO | W21: 45569 | Y21: N/A | Z21: =IF(B21="","",IF(W21="","Pendiente de sentencia",IF(W21="N.A.","N.A.",DAYS360(G21,W21)))) -> 1 | AA21: N/A | AB21: ORDENA SEGUIR ADELANTE CON LA EJECUCIÓN | AC21: 2024-4 | AD21: ORDENA TRASLADO | AE21: 45841 | AF21: LACIDES | AG21: 01 CIVIL MCPAL | AH21: ELECTRONICO | AJ21: X
A22: 15 | B22: 001-2024-00074 | C22: EJECUTIVO | D22: POR SUMAS DE DINERO | E22: MINIMA | F22: REMITIDA POR OTRO DESPACHO | G22: 45568 | H22: COTRAFA COOPERATIVA FINANCIERA | I22: 1 | J22: 0 | K22: DIANA MARCELA MAZO CASTRO | L22: 0 | M22: 1 | N22: 45568 | O22: =IF(G22="","",(IF(N22="","Pendiente primera actuación",IF(N22="N.A.","N.A.",IF(NETWORKDAYS((G22+1),N22,'Días No Laborales'!$A$2:$U$145)<=20,"SI","NO"))))) -> SI | Q22: NO | W22: 45572 | Y22: N/A | Z22: =IF(B22="","",IF(W22="","Pendiente de sentencia",IF(W22="N.A.","N.A.",DAYS360(G22,W22)))) -> 4 | AA22: N/A | AB22: ORDENA SEGUIR ADELANTE CON LA EJECUCIÓN | AC22: 2024-4 | AD22: APRUEBA LIQUIDACION CREDITO | AE22: 45750 | AF22: CAROLINA | AG22: 01 CIVIL MCPAL | AH22: ELECTRONICO | AJ22: X
A23: 16 | B23: 001-2024-00078 | C23: EJECUTIVO | D23: POR SUMAS DE DINERO | E23: MINIMA | F23: REMITIDA POR OTRO DESPACHO | G23: 45568 | H23: ALAMACENES EXITOS S.A | I23: 1 | J23: 0 | K23: GIOVANNY ALEXANDER HERNANDEZ | L23: 1 | M23: 0 | N23: 45568 | O23: =IF(G23="","",(IF(N23="","Pendiente primera actuación",IF(N23="N.A.","N.A.",IF(NETWORKDAYS((G23+1),N23,'Días No Laborales'!$A$2:$U$145)<=20,"SI","NO"))))) -> SI | Q23: NO | W23: 45574 | Y23: N/A | Z23: =IF(B23="","",IF(W23="","Pendiente de sentencia",IF(W23="N.A.","N.A.",DAYS360(G23,W23)))) -> 6 | AA23: N/A | AB23: ORDENA SEGUIR ADELANTE CON LA EJECUCIÓN | AC23: 2024-4 | AD23: APRUEBA LIQUIDACION CREDITO | AE23: 45714 | AF23: CAMILA | AG23: 01 CIVIL MCPAL | AH23: ELECTRONICO | AJ23: X | AM23: P. COSTAS
A24: 17 | B24: 001-2024-00083 | C24: EJECUTIVO | D24: POR SUMAS DE DINERO | E24: MINIMA | F24: REMITIDA POR OTRO DESPACHO | G24: 45568 | H24: BANCO FINANDINA S.A | I24: 1 | J24: 0 | K24: CARLOS ANDRES MORALES ECHAVARRIA | L24: 1 | M24: 0 | N24: 45568 | O24: =IF(G24="","",(IF(N24="","Pendiente primera actuación",IF(N24="N.A.","N.A.",IF(NETWORKDAYS((G24+1),N24,'Días No Laborales'!$A$2:$U$145)<=20,"SI","NO"))))) -> SI | Q24: NO | W24: 45617 | Y24: N/A | Z24: =IF(B24="","",IF(W24="","Pendiente de sentencia",IF(W24="N.A.","N.A.",DAYS360(G24,W24)))) -> 48 | AA24: N/A | AB24: ORDENA SEGUIR ADELANTE CON LA EJECUCIÓN | AC24: 2024-4 | AD24: ORDENA TRASLADO Y REQUIERE 5 DIAS | AE24: 45841 | AF24: LACIDES | AG24: 01 CIVIL MCPAL | AH24: ELECTRONICO | AJ24: X
A25: 18 | B25: 001-2024-00097 | C25: EJECUTIVO | D25: POR SUMAS DE DINERO | E25: MINIMA | F25: REMITIDA POR OTRO DESPACHO | G25: 45568 | H25: NUEVO SUR INMOBILIARIA S.A.S | I25: 1 | J25: 0 | K25: OSCAR LEONARDO RODRIGUEZ HERNANDEZ | L25: 1 | M25: 0 | N25: 45568 | O25: =IF(G25="","",(IF(N25="","Pendiente primera actuación",IF(N25="N.A.","N.A.",IF(NETWORKDAYS((G25+1),N25,'Días No Laborales'!$A$2:$U$145)<=20,"SI","NO"))))) -> SI | Q25: NO | Y25: N/A | Z25: =IF(B25="","",IF(W25="","Pendiente de sentencia",IF(W25="N.A.","N.A.",DAYS360(G25,W25)))) -> Pendiente de sentencia | AA25: N/A | AD25: REQUIERE | AE25: 45799 | AF25: CAROLINA | AG25: 01 CIVIL MCPAL | AH25: ELECTRONICO
A26: 19 | B26: 001-2024-00100 | C26: RESPONSABILIDAD CIVIL CONTRACTUAL | D26: DECLARATIVO VERBAL OTROS PROCESO | E26: MINIMA | F26: REMITIDA POR OTRO DESPACHO | G26: 45568 | H26: LISETH ALEJANDRA GUTIERREZ MARIN | I26: 0 | J26: 1 | K26: MARTHA ELENA LONDOÑO Y OTROS | L26: 0 | M26: 1 | N26: 45568 | O26: =IF(G26="","",(IF(N26="","Pendiente primera actuación",IF(N26="N.A.","N.A.",IF(NETWORKDAYS((G26+1),N26,'Días No Laborales'!$A$2:$U$145)<=20,"SI","NO"))))) -> SI | Q26: NO | Y26: N/A | Z26: =IF(B26="","",IF(W26="","Pendiente de sentencia",IF(W26="N.A.","N.A.",DAYS360(G26,W26)))) -> Pendiente de sentencia | AA26: N/A | AD26: NOTIFICACION PERSONAL ALGUNOS DEMDOS | AE26: 45744 | AF26: LINA | AG26: 01 CIVIL MCPAL | AH26: ELECTRONICO
A27: 20 | B27: 001-2024-00103 | C27: EJECUTIVO | D27: POR SUMAS DE DINERO | E27: MINIMA | F27: REMITIDA POR OTRO DESPACHO | G27: 45568 | H27: UNIDAD RESIDENCIAL AIRE DEL BOSQUE | I27: 1 | J27: 0 | K27: MARIA DORA MURIEL ECHEVERRI | L27: 1 | M27: 0 | N27: 45568 | O27: =IF(G27="","",(IF(N27="","Pendiente primera actuación",IF(N27="N.A.","N.A.",IF(NETWORKDAYS((G27+1),N27,'Días No Laborales'!$A$2:$U$145)<=20,"SI","NO"))))) -> SI | Q27: NO | Y27: N/A | Z27: =IF(B27="","",IF(W27="","Pendiente de sentencia",IF(W27="N.A.","N.A.",DAYS360(G27,W27)))) -> Pendiente de sentencia | AA27: N/A | AD27: REQUIERE ART. 317 | AE27: 45814 | AF27: LUISA | AG27: 01 CIVIL MCPAL | AH27: ELECTRONICO
A28: 21 | B28: 001-2024-00105 | C28: EJECUTIVO | D28: POR SUMAS DE DINERO | E28: MINIMA | F28: REMITIDA POR OTRO DESPACHO | G28: 45568 | H28: ALCATOP SAS | I28: 1 | J28: 0 | K28: CONSTRUCCIONES TORRE LA VEGA DEL SUR | L28: 1 | M28: 0 | N28: 45568 | O28: =IF(G28="","",(IF(N28="","Pendiente primera actuación",IF(N28="N.A.","N.A.",IF(NETWORKDAYS((G28+1),N28,'Días No Laborales'!$A$2:$U$145)<=20,"SI","NO"))))) -> SI | Q28: NO | Y28: N/A | Z28: =IF(B28="","",IF(W28="","Pendiente de sentencia",IF(W28="N.A.","N.A.",DAYS360(G28,W28)))) -> Pendiente de sentencia | AA28: N/A | AD28: DECRETA TEMRINACION MEDIDA CAUTELAR Y REQUIERE ART. 317 | AE28: 45797 | AF28: CAROLINA | AG28: 01 CIVIL MCPAL | AH28: ELECTRONICO | AM28: VENCEN LO 30 DÍAS EL 22/JULIO/2025
A29: 22 | B29: 001-2024-00107 | C29: EJECUTIVO | D29: POR SUMAS DE DINERO | E29: MENOR | F29: REMITIDA POR OTRO DESPACHO | G29: 45568 | H29: JUAN DAVID JARAMILLO CORREA | I29: 1 | J29: 0 | K29: ALVARO FERNANDO SALAZAR GUERRERO Y OTRO | L29: 1 | M29: 0 | N29: 45568 | O29: =IF(G29="","",(IF(N29="","Pendiente primera actuación",IF(N29="N.A.","N.A.",IF(NETWORKDAYS((G29+1),N29,'Días No Laborales'!$A$2:$U$145)<=20,"SI","NO"))))) -> SI | Q29: NO | W29: 45687 | Y29: N/A | Z29: =IF(B29="","",IF(W29="","Pendiente de sentencia",IF(W29="N.A.","N.A.",DAYS360(G29,W29)))) -> 117 | AA29: N/A | AB29: TERMINA POR PAGO TOTAL | AC29: 2025-1 | AD29: TERMINA POR PAGO | AE29: 45687 | AF29: CAMILA | AG29: 01 CIVIL MCPAL | AH29: ELECTRONICO | AI29: 45693
A30: 23 | B30: 001-2024-00126 | C30: EJECUTIVO | D30: POR SUMAS DE DINERO | E30: MENOR | F30: REMITIDA POR OTRO DESPACHO | G30: 45568 | H30: BANCO DE BOGOTA | I30: 1 | J30: 0 | K30: NAFER JOSE PEÑA BERTEL | L30: 1 | M30: 0 | N30: 45568 | O30: =IF(G30="","",(IF(N30="","Pendiente primera actuación",IF(N30="N.A.","N.A.",IF(NETWORKDAYS((G30+1),N30,'Días No Laborales'!$A$2:$U$145)<=20,"SI","NO"))))) -> SI | Q30: NO | W30: 45617 | Y30: N/A | Z30: =IF(B30="","",IF(W30="","Pendiente de sentencia",IF(W30="N.A.","N.A.",DAYS360(G30,W30)))) -> 48 | AA30: N/A | AB30: ORDENA SEGUIR ADELANTE CON LA EJECUCIÓN | AC30: 2024-4 | AD30: REQUIERE 10 DIAS | AE30: 45842 | AF30: LACIDES | AG30: 01 CIVIL MCPAL | AH30: ELECTRONICO | AJ30: x
A31: 24 | B31: 001-2024-00141 | C31: DIVISORIO | D31: DIVISORIO | E31: MENOR | F31: REMITIDA POR OTRO DESPACHO | G31: 45568 | H31: OLGA ISABEL OROZCO PATIÑO | I31: 0 | J31: 1 | K31: LEOPOLDO DE JESUS JIMENEZ GOMEZ Y OTRO | L31: 1 | M31: 0 | N31: 45568 | O31: =IF(G31="","",(IF(N31="","Pendiente primera actuación",IF(N31="N.A.","N.A.",IF(NETWORKDAYS((G31+1),N31,'Días No Laborales'!$A$2:$U$145)<=20,"SI","NO"))))) -> SI | Q31: NO | W31: 45621 | Y31: N/A | Z31: =IF(B31="","",IF(W31="","Pendiente de sentencia",IF(W31="N.A.","N.A.",DAYS360(G31,W31)))) -> 52 | AA31: N/A | AB31: TERMINA PROCESO POR DESISTIMIENTO | AC31: 2024-4 | AD31: TERMINA PROCESO POR DESISTIMIENTO | AE31: 45621 | AF31: LACIDES | AG31: 01 CIVIL MCPAL | AH31: ELECTRONICO | AM31: TEMRINADO POR DESISTIMIENTO
A32: 25 | B32: 001-2024-00174 | C32: EJECUTIVO | D32: POR SUMAS DE DINERO | E32: MINIMA | F32: REMITIDA POR OTRO DESPACHO | G32: 45568 | H32: COBELEN | I32: 0 | J32: 1 | K32: JUAN FELIPE CARVAJAL NOREÑA Y OTRO | L32: 1 | M32: 2 | N32: 45568 | O32: =IF(G32="","",(IF(N32="","Pendiente primera actuación",IF(N32="N.A.","N.A.",IF(NETWORKDAYS((G32+1),N32,'Días No Laborales'!$A$2:$U$145)<=20,"SI","NO"))))) -> SI | Q32: NO | W32: 45574 | Y32: N/A | Z32: =IF(B32="","",IF(W32="","Pendiente de sentencia",IF(W32="N.A.","N.A.",DAYS360(G32,W32)))) -> 6 | AA32: N/A | AB32: ORDENA SEGUIR ADELANTE CON LA EJECUCIÓN | AC32: 2024-4 | AD32: SUSPENDE PROCESO | AE32: 45680 | AF32: CAROLINA | AG32: 01 CIVIL MCPAL | AH32: ELECTRONICO
A33: 26 | B33: 001-2024-00175 | C33: EJECUTIVO | D33: POR SUMAS DE DINERO | E33: MINIMA | F33: REMITIDA POR OTRO DESPACHO | G33: 45568 | H33: AECSA S.A | I33: 1 | J33: 0 | K33: NURY DEL SOCORRO CHAVERRA BENITEZ | L33: 0 | M33: 0 | N33: 45568 | O33: =IF(G33="","",(IF(N33="","Pendiente primera actuación",IF(N33="N.A.","N.A.",IF(NETWORKDAYS((G33+1),N33,'Días No Laborales'!$A$2:$U$145)<=20,"SI","NO"))))) -> SI | Q33: NO | Z33: =IF(B33="","",IF(W33="","Pendiente de sentencia",IF(W33="N.A.","N.A.",DAYS360(G33,W33)))) -> Pendiente de sentencia | AB33: ORDENA SEGUIR ADELANTE CON LA EJECUCIÓN | AC33: 2024-4 | AD33: REQUIERE ART. 317 | AE33: 45846 | AF33: CAMILA | AG33: 01 CIVIL MCPAL | AH33: ELECTRONICO | AJ33: X
A34: 27 | B34: 001-2024-00213 | C34: EJECUTIVO | D34: POR SUMAS DE DINERO | E34: MINIMA | F34: REMITIDA POR OTRO DESPACHO | G34: 45568 | H34: BANCOLOMBIA S.A | I34: 0 | J34: 1 | K34: JHON EDISON MADRIGAL LONDOÑO | L34: 0 | M34: 1 | N34: 45568 | O34: =IF(G34="","",(IF(N34="","Pendiente primera actuación",IF(N34="N.A.","N.A.",IF(NETWORKDAYS((G34+1),N34,'Días No Laborales'!$A$2:$U$145)<=20,"SI","NO"))))) -> SI | Q34: NO | W34: 45828 | Y34: N/A | Z34: =IF(B34="","",IF(W34="","Pendiente de sentencia",IF(W34="N.A.","N.A.",DAYS360(G34,W34)))) -> 257 | AA34: N/A | AB34: ORDENA SEGUIR ADELANTE CON LA EJECUCION | AC34: 2025-2 | AD34: ORDENA TRASLADO LIQUIDACION CRDITO | AE34: 45866 | AF34: CAROLINA | AG34: 01 CIVIL MCPAL | AH34: ELECTRONICO
A35: 28 | B35: 001-2024-00240 | C35: EJECUTIVO | D35: POR SUMAS DE DINERO | E35: MENOR | F35: REMITIDA POR OTRO DESPACHO | G35: 45568 | H35: BANCO DE BOGOTA | K35: ALVARO FERNANDO TORO RENDON | L35: 1 | M35: 0 | N35: 45575 | O35: =IF(G35="","",(IF(N35="","Pendiente primera actuación",IF(N35="N.A.","N.A.",IF(NETWORKDAYS((G35+1),N35,'Días No Laborales'!$A$2:$U$145)<=20,"SI","NO"))))) -> SI | Q35: NO | W35: 45575 | Y35: N/A | Z35: =IF(B35="","",IF(W35="","Pendiente de sentencia",IF(W35="N.A.","N.A.",DAYS360(G35,W35)))) -> 7 | AA35: N/A | AB35: ORDENA SEGUIR ADELANTE CON LA EJECUCIÓN | AC35: 2024-4 | AD35: OSAE - COSTAS | AE35: 45575 | AF35: LUISA | AG35: 01 CIVIL MCPAL | AH35: ELECTRONICO
A36: 29 | B36: 001-2024-00263 | C36: EJECUTIVO | D36: POR SUMAS DE DINERO | E36: MINIMA | F36: REMITIDA POR OTRO DESPACHO | G36: 45568 | H36: GUILLERMO LEON BENITEZ GARCIA | I36: 1 | J36: 0 | K36: YESSICA YULIANA HERNANDEZ FRANCO | L36: 1 | M36: 0 | N36: 45568 | O36: =IF(G36="","",(IF(N36="","Pendiente primera actuación",IF(N36="N.A.","N.A.",IF(NETWORKDAYS((G36+1),N36,'Días No Laborales'!$A$2:$U$145)<=20,"SI","NO"))))) -> SI | Q36: NO | W36: 45734 | Y36: N/A | Z36: =IF(B36="","",IF(W36="","Pendiente de sentencia",IF(W36="N.A.","N.A.",DAYS360(G36,W36)))) -> 165 | AA36: N/A | AB36: ORDENA SEGUIR ADELANTE CON LA EJECUCIÓN | AC36: 2025-1 | AD36: REQUIERE | AE36: 45842 | AF36: LACIDES | AG36: 01 CIVIL MCPAL | AH36: ELECTRONICO
A37: 30 | B37: 001-2024-00277 | C37: EJECUTIVO | D37: POR SUMAS DE DINERO | E37: MINIMA | F37: REMITIDA POR OTRO DESPACHO | G37: 45568 | H37: SEGUROS COMERCIALES BOLIVAR | I37: 1 | J37: 1 | K37: ROGER ALEXANDER FLOREZ GIRLDO | L37: 1 | M37: 0 | N37: 45569 | O37: =IF(G37="","",(IF(N37="","Pendiente primera actuación",IF(N37="N.A.","N.A.",IF(NETWORKDAYS((G37+1),N37,'Días No Laborales'!$A$2:$U$145)<=20,"SI","NO"))))) -> SI | Q37: NO | W37: 45574 | Y37: N/A | Z37: =IF(B37="","",IF(W37="","Pendiente de sentencia",IF(W37="N.A.","N.A.",DAYS360(G37,W37)))) -> 6 | AA37: N/A | AB37: ORDENA SEGUIR ADELANTE CON LA EJECUCIÓN | AC37: 2024-4 | AD37: OSAE - COSTAS | AE37: 45581 | AF37: CAROLINA | AG37: 01 CIVIL MCPAL | AH37: ELECTRONICO
A38: 31 | B38: 001-2024-00279 | C38: EJECUTIVO | D38: POR SUMAS DE DINERO | E38: MINIMA | F38: REMITIDA POR OTRO DESPACHO | G38: 45568 | H38: DORIS ELENA ZAPATA | I38: 1 | J38: 0 | K38: JORGE ALBERTO GIRALDO RESTREPO | L38: 1 | M38: 0 | N38: 45568 | O38: =IF(G38="","",(IF(N38="","Pendiente primera actuación",IF(N38="N.A.","N.A.",IF(NETWORKDAYS((G38+1),N38,'Días No Laborales'!$A$2:$U$145)<=20,"SI","NO"))))) -> SI | Q38: NO | Y38: N/A | Z38: =IF(B38="","",IF(W38="","Pendiente de sentencia",IF(W38="N.A.","N.A.",DAYS360(G38,W38)))) -> Pendiente de sentencia | AA38: N/A | AD38: AUTORIZA NUEVA DIRECCION | AE38: 45799 | AF38: LUISA | AG38: 01 CIVIL MCPAL | AH38: ELECTRONICO
A39: 32 | B39: 001-2024-00282 | C39: EJECUTIVO | D39: POR SUMAS DE DINERO | E39: MINIMA | F39: REMITIDA POR OTRO DESPACHO | G39: 45568 | H39: ANIBAL ARISTIZABAL HOYOS | I39: 1 | J39: 0 | K39: MANUEL RAMIREZ SIERRA | L39: 1 | M39: 0 | N39: 45568 | O39: =IF(G39="","",(IF(N39="","Pendiente primera actuación",IF(N39="N.A.","N.A.",IF(NETWORKDAYS((G39+1),N39,'Días No Laborales'!$A$2:$U$145)<=20,"SI","NO"))))) -> SI | Q39: NO | Y39: N/A | Z39: =IF(B39="","",IF(W39="","Pendiente de sentencia",IF(W39="N.A.","N.A.",DAYS360(G39,W39)))) -> Pendiente de sentencia | AA39: N/A | AD39: REQ. ART. 317 | AE39: 45679 | AF39: LUISA | AG39: 01 CIVIL MCPAL | AH39: ELECTRONICO
A40: 33 | B40: 001-2024-00289 | C40: RESTITUCION BIEN INMUEBLE | D40: VERBAL SUMARIO | E40: MINIMA | F40: REMITIDA POR OTRO DESPACHO | G40: 45568 | H40: BANCOLOMBIA S.A | I40: 1 | J40: 0 | K40: JOSE FERNANDO ROMERO GUARDAMINO | L40: 0 | M40: 0 | N40: 45568 | O40: =IF(G40="","",(IF(N40="","Pendiente primera actuación",IF(N40="N.A.","N.A.",IF(NETWORKDAYS((G40+1),N40,'Días No Laborales'!$A$2:$U$145)<=20,"SI","NO"))))) -> SI | Q40: NO | W40: 45709 | Y40: N/A | Z40: =IF(B40="","",IF(W40="","Pendiente de sentencia",IF(W40="N.A.","N.A.",DAYS360(G40,W40)))) -> 138 | AA40: N/A | AB40: SENTENCIA ANTICIPADA | AC40: 2025-1 | AD40: ORDENA EXPEDIR COMISION | AE40: 45804 | AF40: CAROLINA | AG40: 01 CIVIL MCPAL | AH40: ELECTRONICO | AI40: 45662
A41: 34 | B41: 001-2024-00297 | C41: EJECUTIVO | D41: POR SUMAS DE DINERO | E41: MENOR | F41: REMITIDA POR OTRO DESPACHO | G41: 45568 | H41: BANCO DE OCCIDENTE | I41: 0 | J41: 1 | K41: MARIA ALEJANDRA PATIÑO RUIZ | L41: 0 | M41: 1 | N41: 45568 | O41: =IF(G41="","",(IF(N41="","Pendiente primera actuación",IF(N41="N.A.","N.A.",IF(NETWORKDAYS((G41+1),N41,'Días No Laborales'!$A$2:$U$145)<=20,"SI","NO"))))) -> SI | Q41: NO | Z41: =IF(B41="","",IF(W41="","Pendiente de sentencia",IF(W41="N.A.","N.A.",DAYS360(G41,W41)))) -> Pendiente de sentencia | AB41: REMITIDOS A OTROS DESPACHOS | AC41: 2024-4 | AD41: INCORPORA/RESPONDE | AE41: 45723 | AF41: LACIDES | AG41: 01 CIVIL MCPAL | AH41: ELECTRONICO | AM41: REMITIDO 09/12/2024
A42: 35 | B42: 001-2024-00312 | C42: EJECUTIVO | D42: POR SUMAS DE DINERO | E42: MINIMA | F42: REMITIDA POR OTRO DESPACHO | G42: 45568 | H42: ALBERTO NARANJO S.A | I42: 1 | J42: 0 | K42: OSWALDO DE JESUS GOMEZ RAMIREZ | L42: 1 | M42: 1 | N42: 45568 | O42: =IF(G42="","",(IF(N42="","Pendiente primera actuación",IF(N42="N.A.","N.A.",IF(NETWORKDAYS((G42+1),N42,'Días No Laborales'!$A$2:$U$145)<=20,"SI","NO"))))) -> SI | Q42: NO | W42: 45735 | Y42: N/A | Z42: =IF(B42="","",IF(W42="","Pendiente de sentencia",IF(W42="N.A.","N.A.",DAYS360(G42,W42)))) -> 166 | AA42: N/A | AB42: DESISTIMIENTO TACITO | AC42: 2025-1 | AD42: TERMINA POR DESISTIMIENTO TACITO | AE42: 45735 | AF42: CAMILA | AG42: 01 CIVIL MCPAL | AH42: ELECTRONICO | AI42: 45743 | AM42: TERMINA DESISTIMIENTO TACITO
A43: 36 | B43: 001-2024-00319 | C43: EJECUTIVO | D43: POR SUMAS DE DINERO | E43: MINIMA | F43: REMITIDA POR OTRO DESPACHO | G43: 45568 | H43: BANCO DE OCCIDENTE | I43: 1 | J43: 0 | K43: LUIS ALFREDO ALTAMAR ROJAS | L43: 1 | M43: 0 | N43: 45568 | O43: =IF(G43="","",(IF(N43="","Pendiente primera actuación",IF(N43="N.A.","N.A.",IF(NETWORKDAYS((G43+1),N43,'Días No Laborales'!$A$2:$U$145)<=20,"SI","NO"))))) -> SI | Q43: NO | W43: 45713 | Y43: N/A | Z43: =IF(B43="","",IF(W43="","Pendiente de sentencia",IF(W43="N.A.","N.A.",DAYS360(G43,W43)))) -> 142 | AA43: N/A | AB43: ORDENA SEGUIR ADELANTE CON LA EJECUCIÓN | AC43: 2025-1 | AD43: ORDENA CORRER TRASLADO | AE43: 45798 | AF43: CAROLINA | AG43: 01 CIVIL MCPAL | AH43: ELECTRONICO
A44: 37 | B44: 001-2024-00370 | C44: EJECUTIVO | D44: POR SUMAS DE DINERO | E44: MENOR | F44: REMITIDA POR OTRO DESPACHO | G44: 45568 | H44: INMOBILIARIA BODEGAS Y BODEGAS | I44: 1 | J44: 0 | K44: JHOAN SEBASTIAN PRIETO SANCHEZ Y OTRO | L44: 1 | M44: 0 | N44: 45568 | O44: =IF(G44="","",(IF(N44="","Pendiente primera actuación",IF(N44="N.A.","N.A.",IF(NETWORKDAYS((G44+1),N44,'Días No Laborales'!$A$2:$U$145)<=20,"SI","NO"))))) -> SI | Q44: NO | W44: 45692 | Y44: N/A | Z44: =IF(B44="","",IF(W44="","Pendiente de sentencia",IF(W44="N.A.","N.A.",DAYS360(G44,W44)))) -> 121 | AA44: N/A | AB44: ORDENA SEGUIR ADELANTE CON LA EJECUCIÓN | AC44: 2025-1 | AD44: TERMINA POR PAGO | AE44: 45692 | AF44: LUISA | AG44: 01 CIVIL MCPAL | AH44: ELECTRONICO | AI44: 45699 | AJ44: X | AM44: 2025-1
A45: 38 | B45: 001-2024-00385 | C45: EJECUTIVO | D45: POR SUMAS DE DINERO | E45: MENOR | F45: REMITIDA POR OTRO DESPACHO | G45: 45568 | H45: SCOTIABANK | I45: 1 | J45: 0 | K45: DIEGO ALBERTO HENAO CAMARGO | L45: 1 | M45: 0 | N45: 45568 | O45: =IF(G45="","",(IF(N45="","Pendiente primera actuación",IF(N45="N.A.","N.A.",IF(NETWORKDAYS((G45+1),N45,'Días No Laborales'!$A$2:$U$145)<=20,"SI","NO"))))) -> SI | Q45: NO | W45: 45749 | Y45: N/A | Z45: =IF(B45="","",IF(W45="","Pendiente de sentencia",IF(W45="N.A.","N.A.",DAYS360(G45,W45)))) -> 179 | AA45: N/A | AB45: ORDENA SEGUIR ADELANTE CON LA EJECUCIÓN | AC45: 2025-1 | AD45: APRUEBA LIQUIDACION CREDITO | AE45: 45819 | AF45: CAMILA | AG45: 01 CIVIL MCPAL | AH45: ELECTRONICO
A46: 39 | B46: 001-2024-00392 | C46: PERTENENCIA | D46: VERBAL | E46: MENOR | F46: REMITIDA POR OTRO DESPACHO | G46: 45568 | H46: BLANCA NYDIA URIBE DE CHACON | I46: 1 | J46: 0 | K46: ALVARO AUGUSTO URIBE RODRIGUEZ | L46: 1 | M46: 0 | N46: 45568 | O46: =IF(G46="","",(IF(N46="","Pendiente primera actuación",IF(N46="N.A.","N.A.",IF(NETWORKDAYS((G46+1),N46,'Días No Laborales'!$A$2:$U$145)<=20,"SI","NO"))))) -> SI | Q46: NO | Y46: N/A | Z46: =IF(B46="","",IF(W46="","Pendiente de sentencia",IF(W46="N.A.","N.A.",DAYS360(G46,W46)))) -> Pendiente de sentencia | AA46: N/A | AD46: REITERA REQUERIMIENTO | AE46: 45842 | AF46: LACIDES | AG46: 01 CIVIL MCPAL | AH46: ELECTRONICO
A47: 40 | B47: 001-2024-00394 | C47: EJECUTIVO | D47: POR SUMAS DE DINERO | E47: MINIMA | F47: REMITIDA POR OTRO DESPACHO | G47: 45568 | H47: SERVICIOS Y ACESORIAS INTEGRALES S.A.S | I47: 1 | J47: 0 | K47: ALMAVID SALUD S.A.S | L47: 1 | M47: 0 | N47: 45568 | O47: =IF(G47="","",(IF(N47="","Pendiente primera actuación",IF(N47="N.A.","N.A.",IF(NETWORKDAYS((G47+1),N47,'Días No Laborales'!$A$2:$U$145)<=20,"SI","NO"))))) -> SI | Q47: NO | W47: 45820 | Y47: N/A | Z47: =IF(B47="","",IF(W47="","Pendiente de sentencia",IF(W47="N.A.","N.A.",DAYS360(G47,W47)))) -> 249 | AA47: N/A | AB47: TERMINA DESISTIMIENTO TACITO | AC47: 2025-2 | AD47: TERMINA POR DESISTIMIENTO TACITO | AE47: 45820 | AF47: CAMILA | AG47: 01 CIVIL MCPAL | AH47: ELECTRONICO | AI47: 45827
A48: 41 | B48: 001-2024-00432 | C48: EJECUTIVO | D48: POR SUMAS DE DINERO | E48: MINIMA | F48: REMITIDA POR OTRO DESPACHO | G48: 45568 | H48: BANCO DAVIVIENDA | I48: 1 | J48: 2 | K48: ANDRES CARDONA GALLEGO | L48: 1 | M48: 2 | N48: 45568 | O48: =IF(G48="","",(IF(N48="","Pendiente primera actuación",IF(N48="N.A.","N.A.",IF(NETWORKDAYS((G48+1),N48,'Días No Laborales'!$A$2:$U$145)<=20,"SI","NO"))))) -> SI | Q48: NO | W48: 45573 | Y48: N/A | Z48: =IF(B48="","",IF(W48="","Pendiente de sentencia",IF(W48="N.A.","N.A.",DAYS360(G48,W48)))) -> 5 | AA48: N/A | AB48: ORDENA SEGUIR ADELANTE CON LA EJECUCIÓN | AC48: 2024-4 | AD48: SUPENDIDO | AE48: 45573 | AF48: LACIDES | AG48: 01 CIVIL MCPAL | AH48: ELECTRONICO | AJ48: X
A49: 42 | B49: 001-2024-00448 | C49: EJECUTIVO | D49: POR SUMAS DE DINERO | E49: MINIMA | F49: REMITIDA POR OTRO DESPACHO | G49: 45568 | H49: SISTICREDITO | I49: 1 | J49: 0 | K49: ALICIA MARIA RUIZ ECHEVERRI | L49: 0 | M49: 0 | N49: 45568 | O49: =IF(G49="","",(IF(N49="","Pendiente primera actuación",IF(N49="N.A.","N.A.",IF(NETWORKDAYS((G49+1),N49,'Días No Laborales'!$A$2:$U$145)<=20,"SI","NO"))))) -> SI | Q49: NO | Y49: N/A | Z49: =IF(B49="","",IF(W49="","Pendiente de sentencia",IF(W49="N.A.","N.A.",DAYS360(G49,W49)))) -> Pendiente de sentencia | AA49: N/A | AD49: ACEPTA SUSTITUCION | AE49: 45828 | AF49: CAROLINA | AG49: 01 CIVIL MCPAL | AH49: ELECTRONICO
A50: 43 | B50: 001-2024-00449 | C50: EJECUTIVO | D50: POR SUMAS DE DINERO | E50: MINIMA | F50: REMITIDA POR OTRO DESPACHO | G50: 45568 | H50: RCI COLOMBIA COMPAÑIA DE FINANCIAMIENTO | I50: 0 | J50: 1 | K50: JULIAN ALBERTO ARIAS ESCOBAR | L50: 0 | M50: 1 | N50: 45568 | O50: =IF(G50="","",(IF(N50="","Pendiente primera actuación",IF(N50="N.A.","N.A.",IF(NETWORKDAYS((G50+1),N50,'Días No Laborales'!$A$2:$U$145)<=20,"SI","NO"))))) -> SI | Q50: NO | Y50: N/A | Z50: =IF(B50="","",IF(W50="","Pendiente de sentencia",IF(W50="N.A.","N.A.",DAYS360(G50,W50)))) -> Pendiente de sentencia | AA50: N/A | AD50: PONE EN CONOCIMIENTO RTA TRANSUNION | AE50: 45793 | AF50: LINA | AG50: 01 CIVIL MCPAL | AH50: ELECTRONICO
A51: 44 | B51: 001-2024-00455 | C51: EJECUTIVO | D51: POR SUMAS DE DINERO | E51: MINIMA | F51: REMITIDA POR OTRO DESPACHO | G51: 45568 | H51: BANCO UNION | I51: 0 | J51: 0 | K51: MONICA BIBIANA ESCOBAR MARTINEZ | L51: 0 | M51: 0 | N51: 45568 | O51: =IF(G51="","",(IF(N51="","Pendiente primera actuación",IF(N51="N.A.","N.A.",IF(NETWORKDAYS((G51+1),N51,'Días No Laborales'!$A$2:$U$145)<=20,"SI","NO"))))) -> SI | Q51: NO | W51: 45628 | Y51: N/A | Z51: =IF(B51="","",IF(W51="","Pendiente de sentencia",IF(W51="N.A.","N.A.",DAYS360(G51,W51)))) -> 59 | AA51: N/A | AB51: DESISTIMIENTO TACITO | AC51: 2024-4 | AD51: TERMINA POR DESISTIMIENTO TACITO | AE51: 45628 | AF51: CAMILA | AG51: 01 CIVIL MCPAL | AH51: ELECTRONICO
A52: 45 | B52: 001-2024-00468 | C52: EJECUTIVO | D52: POR SUMAS DE DINERO | E52: MINIMA | F52: REMITIDA POR OTRO DESPACHO | G52: 45568 | H52: FONDO DE EMPLEADOS ALAMECENES EXITO | I52: 0 | J52: 1 | K52: ANDRES ESTEBAN SANCHEZ HERNANDEZ | L52: 1 | M52: 1 | N52: 45568 | O52: =IF(G52="","",(IF(N52="","Pendiente primera actuación",IF(N52="N.A.","N.A.",IF(NETWORKDAYS((G52+1),N52,'Días No Laborales'!$A$2:$U$145)<=20,"SI","NO"))))) -> SI | Q52: NO | W52: 45719 | Y52: N/A | Z52: =IF(B52="","",IF(W52="","Pendiente de sentencia",IF(W52="N.A.","N.A.",DAYS360(G52,W52)))) -> 150 | AA52: N/A | AB52: ORDENA SEGUIR ADELANTE CON LA EJECUCIÓN | AC52: 2025-1 | AD52: APRUEBA LIQUIDACION CREDITO | AE52: 45842 | AF52: LACIDES | AG52: 01 CIVIL MCPAL | AH52: ELECTRONICO
A53: 46 | B53: 001-2024-00482 | C53: EJECUTIVO | D53: POR SUMAS DE DINERO | E53: MINIMA | F53: REMITIDA POR OTRO DESPACHO | G53: 45568 | H53: EDIFICIO SAN BARTOLOMÉ | I53: 1 | J53: 0 | K53: ALICIA DE JESUS PEREZ PEREIRA | L53: 1 | M53: 0 | N53: 45568 | O53: =IF(G53="","",(IF(N53="","Pendiente primera actuación",IF(N53="N.A.","N.A.",IF(NETWORKDAYS((G53+1),N53,'Días No Laborales'!$A$2:$U$145)<=20,"SI","NO"))))) -> SI | Q53: NO | Y53: N/A | Z53: =IF(B53="","",IF(W53="","Pendiente de sentencia",IF(W53="N.A.","N.A.",DAYS360(G53,W53)))) -> Pendiente de sentencia | AA53: N/A | AD53: REQUIERE ART. 317 | AE53: 45811 | AF53: CAROLINA | AG53: 01 CIVIL MCPAL | AH53: ELECTRONICO
A54: 47 | B54: 001-2024-00484 | C54: RESOLUCION DE CONTRATO | D54: DECLARATIVO VERBAL OTROS PROCESO | E54: MENOR | F54: REMITIDA POR OTRO DESPACHO | G54: 45568 | H54: MONICA DEL SOCORRO CANO RAMIREZ | I54: 1 | J54: 1 | K54: BIBIAN ASTRID PEREZ MIRA | L54: 1 | M54: 1 | N54: 45568 | O54: =IF(G54="","",(IF(N54="","Pendiente primera actuación",IF(N54="N.A.","N.A.",IF(NETWORKDAYS((G54+1),N54,'Días No Laborales'!$A$2:$U$145)<=20,"SI","NO"))))) -> SI | Q54: NO | Y54: N/A | Z54: =IF(B54="","",IF(W54="","Pendiente de sentencia",IF(W54="N.A.","N.A.",DAYS360(G54,W54)))) -> Pendiente de sentencia | AA54: N/A | AD54: REQUIERE ART. 317 | AE54: 45954 | AF54: LINA | AG54: 01 CIVIL MCPAL | AH54: ELECTRONICO
A55: 48 | B55: 001-2024-00518 | C55: EJECUTIVO | D55: POR SUMAS DE DINERO | E55: MINIMA | F55: REMITIDA POR OTRO DESPACHO | G55: 45568 | H55: FRANCISCO JAVIER MUÑOZ CARDONA | I55: 1 | J55: 0 | K55: MARTHA EDILDA LOPEZ RIOS | L55: 1 | M55: 0 | N55: 45568 | O55: =IF(G55="","",(IF(N55="","Pendiente primera actuación",IF(N55="N.A.","N.A.",IF(NETWORKDAYS((G55+1),N55,'Días No Laborales'!$A$2:$U$145)<=20,"SI","NO"))))) -> SI | Q55: NO | W55: 45632 | Y55: N/A | Z55: =IF(B55="","",IF(W55="","Pendiente de sentencia",IF(W55="N.A.","N.A.",DAYS360(G55,W55)))) -> 63 | AA55: N/A | AB55: ORDENA SEGUIR ADELANTE CON LA EJECUCIÓN | AC55: 2024-4 | AD55: OSAE - COSTAS | AE55: 45632 | AF55: LUISA | AG55: 01 CIVIL MCPAL | AH55: ELECTRONICO | AJ55: X
A56: 49 | B56: 001-2024-00525 | C56: EJECUTIVO | D56: POR SUMAS DE DINERO | E56: MINIMA | F56: REMITIDA POR OTRO DESPACHO | G56: 45568 | H56: ARRENDAMIENTO ENVIGADO | I56: 1 | J56: 1 | K56: FRANCY ALEJANDRA MARIN ALVAREZ | L56: 0 | M56: 1 | N56: 45568 | O56: =IF(G56="","",(IF(N56="","Pendiente primera actuación",IF(N56="N.A.","N.A.",IF(NETWORKDAYS((G56+1),N56,'Días No Laborales'!$A$2:$U$145)<=20,"SI","NO"))))) -> SI | Q56: NO | W56: 45603 | Y56: N/A | Z56: =IF(B56="","",IF(W56="","Pendiente de sentencia",IF(W56="N.A.","N.A.",DAYS360(G56,W56)))) -> 34 | AA56: N/A | AB56: ORDENA SEGUIR ADELANTE CON LA EJECUCIÓN | AC56: 2024-4 | AD56: TERMINA PROCEO POR PAGO - CON OSAE | AE56: 45751 | AF56: LACIDES | AG56: 01 CIVIL MCPAL | AH56: ELECTRONICO | AI56: 45971 | AJ56: X
A57: 50 | B57: 001-2024-00544 | C57: EJECUTIVO | D57: POR SUMAS DE DINERO | E57: MINIMA | F57: REMITIDA POR OTRO DESPACHO | G57: 45568 | H57: BANCO DE BOGOTA | I57: 0 | J57: 0 | K57: FURTA SECA DE VERONA Y OTRO | L57: 0 | M57: 0 | N57: 45568 | O57: =IF(G57="","",(IF(N57="","Pendiente primera actuación",IF(N57="N.A.","N.A.",IF(NETWORKDAYS((G57+1),N57,'Días No Laborales'!$A$2:$U$145)<=20,"SI","NO"))))) -> SI | Q57: NO | Y57: N/A | Z57: =IF(B57="","",IF(W57="","Pendiente de sentencia",IF(W57="N.A.","N.A.",DAYS360(G57,W57)))) -> Pendiente de sentencia | AA57: N/A | AD57: ENTREGA EL EXPEDIENTE | AE57: 45733 | AF57: CAROLINA | AG57: 01 CIVIL MCPAL | AH57: ELECTRONICO
A58: 51 | B58: 001-2024-00545 | C58: EJECUTIVO | D58: POR SUMAS DE DINERO | E58: MENOR | F58: REMITIDA POR OTRO DESPACHO | G58: 45568 | H58: BANCOLOMBIA S.A | I58: 0 | J58: 1 | K58: ISABEL CRISTINA CARDOZO GARCIA | L58: 1 | M58: 1 | N58: 45568 | O58: =IF(G58="","",(IF(N58="","Pendiente primera actuación",IF(N58="N.A.","N.A.",IF(NETWORKDAYS((G58+1),N58,'Días No Laborales'!$A$2:$U$145)<=20,"SI","NO"))))) -> SI | Q58: NO | Y58: N/A | Z58: =IF(B58="","",IF(W58="","Pendiente de sentencia",IF(W58="N.A.","N.A.",DAYS360(G58,W58)))) -> Pendiente de sentencia | AA58: N/A | AD58: EXIGE REQUISITO | AE58: 45635 | AF58: LUISA | AG58: 01 CIVIL MCPAL | AH58: ELECTRONICO
A59: 52 | B59: 001-2024-00559 | C59: EJECUTIVO | D59: POR SUMAS DE DINERO | E59: MINIMA | F59: REMITIDA POR OTRO DESPACHO | G59: 45568 | H59: CORPORACION OTRA PARTE Y CIA | I59: 1 | J59: 1 | K59: VERTELAB SAS Y OTRS - DIEGO FERNANDO LAVID ECHEVERRI | L59: 0 | M59: 1 | N59: 45568 | O59: =IF(G59="","",(IF(N59="","Pendiente primera actuación",IF(N59="N.A.","N.A.",IF(NETWORKDAYS((G59+1),N59,'Días No Laborales'!$A$2:$U$145)<=20,"SI","NO"))))) -> SI | Q59: NO | Y59: N/A | Z59: =IF(B59="","",IF(W59="","Pendiente de sentencia",IF(W59="N.A.","N.A.",DAYS360(G59,W59)))) -> Pendiente de sentencia | AA59: N/A | AD59: PONE EN CONOCIMIENTO Y REQUIERE 5 DIAS | AE59: 45713 | AF59: CAROLINA | AG59: 01 CIVIL MCPAL | AH59: ELECTRONICO | AM59: VENCEN 04/03/2025
A60: 53 | B60: 001-2024-00565 | C60: EJECUTIVO | D60: POR SUMAS DE DINERO | E60: MINIMA | F60: REMITIDA POR OTRO DESPACHO | G60: 45568 | H60: BANCO SCOTIABANK | I60: 0 | J60: 0 | K60: JHON FREDY DE JESUS VELASQUEZ RIOS | L60: 1 | M60: 0 | N60: 45568 | O60: =IF(G60="","",(IF(N60="","Pendiente primera actuación",IF(N60="N.A.","N.A.",IF(NETWORKDAYS((G60+1),N60,'Días No Laborales'!$A$2:$U$145)<=20,"SI","NO"))))) -> SI | Q60: NO | W60: 45580 | Y60: N/A | Z60: =IF(B60="","",IF(W60="","Pendiente de sentencia",IF(W60="N.A.","N.A.",DAYS360(G60,W60)))) -> 12 | AA60: N/A | AB60: ORDENA SEGUIR ADELANTE CON LA EJECUCIÓN | AC60: 2024-4 | AD60: OSAE - COSTAS | AE60: 45580 | AF60: LUISA | AG60: 01 CIVIL MCPAL | AH60: ELECTRONICO
A61: 54 | B61: 001-2024-00155 | C61: SUCESION | D61: LIQUIDATORIO | E61: MINIMA | F61: REMITIDA POR OTRO DESPACHO | G61: 45568 | H61: MARIA MELBA FRANCO ZULUAGA | I61: 1 | J61: 2 | K61: LUZ YANET JANETH PATIÑO FRANCO Y OTROS | L61: 0 | M61: 2 | N61: 45568 | O61: =IF(G61="","",(IF(N61="","Pendiente primera actuación",IF(N61="N.A.","N.A.",IF(NETWORKDAYS((G61+1),N61,'Días No Laborales'!$A$2:$U$145)<=20,"SI","NO"))))) -> SI | Q61: NO | Y61: N/A | Z61: =IF(B61="","",IF(W61="","Pendiente de sentencia",IF(W61="N.A.","N.A.",DAYS360(G61,W61)))) -> Pendiente de sentencia | AA61: N/A | AD61: AUTO EXIGE REQUISITO | AE61: 45825 | AF61: LACIDES | AG61: 01 CIVIL MCPAL | AH61: ELECTRONICO
A62: 55 | B62: 001-2024-00571 | C62: EJECUTIVO | D62: POR SUMAS DE DINERO | E62: MINIMA | F62: REMITIDA POR OTRO DESPACHO | G62: 45568 | H62: SEGUROS COMERCIALES BOLIVAR | I62: 0 | J62: 1 | K62: SANTIAGO ZAPATA DIAZ Y OTRO | L62: 2 | M62: 1 | N62: 45568 | O62: =IF(G62="","",(IF(N62="","Pendiente primera actuación",IF(N62="N.A.","N.A.",IF(NETWORKDAYS((G62+1),N62,'Días No Laborales'!$A$2:$U$145)<=20,"SI","NO"))))) -> SI | Q62: NO | Y62: N/A | Z62: =IF(B62="","",IF(W62="","Pendiente de sentencia",IF(W62="N.A.","N.A.",DAYS360(G62,W62)))) -> Pendiente de sentencia | AA62: N/A | AD62: DECRETA SECUESTRO Y ORDENA COMISIONAR | AE62: 45734 | AF62: CAROLINA | AG62: 01 CIVIL MCPAL | AH62: ELECTRONICO | AM62: REMISION COMISION OK - 21/03/2025
A63: 56 | B63: 001-2024-00572 | C63: SUCESION | D63: LIQUIDATORIO | E63: MINIMA | F63: REMITIDA POR OTRO DESPACHO | G63: 45568 | H63: JAIME DE JESUS MARIN CASTAÑEDA | I63: 2 | J63: 0 | K63: LUIS FERNANDO MONTOYA GOMEZ Y OTROS | L63: 1 | M63: 0 | N63: 45568 | O63: =IF(G63="","",(IF(N63="","Pendiente primera actuación",IF(N63="N.A.","N.A.",IF(NETWORKDAYS((G63+1),N63,'Días No Laborales'!$A$2:$U$145)<=20,"SI","NO"))))) -> SI | Q63: NO | Y63: N/A | Z63: =IF(B63="","",IF(W63="","Pendiente de sentencia",IF(W63="N.A.","N.A.",DAYS360(G63,W63)))) -> Pendiente de sentencia | AA63: N/A | AD63: INCORPORA Y RESUELVE | AE63: 45846 | AF63: CAMILA | AG63: 01 CIVIL MCPAL | AH63: ELECTRONICO
A64: 57 | B64: 001-2024-00577 | C64: EJECUTIVO | D64: POR SUMAS DE DINERO | E64: MENOR | F64: REMITIDA POR OTRO DESPACHO | G64: 45568 | H64: BANCO DE BOGOTA S.A | I64: 1 | J64: 1 | K64: RIGOBERTO ESPINOSA OLIVA | L64: 2 | M64: 1 | N64: 45568 | O64: =IF(G64="","",(IF(N64="","Pendiente primera actuación",IF(N64="N.A.","N.A.",IF(NETWORKDAYS((G64+1),N64,'Días No Laborales'!$A$2:$U$145)<=20,"SI","NO"))))) -> SI | Q64: NO | Y64: N/A | Z64: =IF(B64="","",IF(W64="","Pendiente de sentencia",IF(W64="N.A.","N.A.",DAYS360(G64,W64)))) -> Pendiente de sentencia | AA64: N/A | AB64: ORDENA SEGUIR ADELANTE CON LA EJECUCIÓN | AC64: 2025-2 | AD64: OSAE - COSTAS | AE64: 45792 | AF64: LACIDES | AG64: 01 CIVIL MCPAL | AH64: ELECTRONICO
A65: 58 | B65: 001-2024-00596 | C65: RESTITUCION BIEN INMUEBLE | D65: VERBAL SUMARIO | E65: MINIMA | F65: REMITIDA POR OTRO DESPACHO | G65: 45568 | H65: JHON JAIRO PIEDRAHITA ARROYAVE | I65: 2 | J65: 2 | K65: JULIAN ZULUAGA ARROYAVE Y OTROS | L65: 1 | M65: 2 | N65: 45568 | O65: =IF(G65="","",(IF(N65="","Pendiente primera actuación",IF(N65="N.A.","N.A.",IF(NETWORKDAYS((G65+1),N65,'Días No Laborales'!$A$2:$U$145)<=20,"SI","NO"))))) -> SI | Q65: NO | W65: 45581 | Y65: N/A | Z65: =IF(B65="","",IF(W65="","Pendiente de sentencia",IF(W65="N.A.","N.A.",DAYS360(G65,W65)))) -> 13 | AA65: N/A | AB65: RECHAZADOS O RETIRADOS | AC65: 2024-4 | AD65: RECHAZA NO SUBSANA | AE65: 45581 | AF65: CAROLINA | AG65: 01 CIVIL MCPAL | AH65: ELECTRONICO | AM65: SE REMITE A CENTRO DE SERVICIOS POR ALFRSCO PARA QUE REMITA AL SUPERIOR 02/7/25
A66: 59 | B66: 001-2024-00599 | C66: EJECUTIVO | D66: POR SUMAS DE DINERO | E66: MINIMA | F66: REMITIDA POR OTRO DESPACHO | G66: 45568 | H66: JFK COOPERATIVAFINANCIERA | I66: 1 | J66: 1 | K66: LORENO HIGUITA GIRON | L66: 0 | M66: 1 | N66: 45568 | O66: =IF(G66="","",(IF(N66="","Pendiente primera actuación",IF(N66="N.A.","N.A.",IF(NETWORKDAYS((G66+1),N66,'Días No Laborales'!$A$2:$U$145)<=20,"SI","NO"))))) -> SI | Q66: NO | Y66: N/A | Z66: =IF(B66="","",IF(W66="","Pendiente de sentencia",IF(W66="N.A.","N.A.",DAYS360(G66,W66)))) -> Pendiente de sentencia | AA66: N/A | AD66: ORDENA OFICIAR | AE66: 45840 | AF66: CAMILA | AG66: 01 CIVIL MCPAL | AH66: ELECTRONICO
A67: 60 | B67: 001-2024-00603 | C67: EJECUTIVO | D67: POR SUMAS DE DINERO | E67: MENOR | F67: REMITIDA POR OTRO DESPACHO | G67: 45568 | H67: BANCO DAVIVIENDA | I67: 0 | J67: 2 | K67: ALEXANDER OTERO BARRETO | L67: 2 | M67: 2 | N67: 45568 | O67: =IF(G67="","",(IF(N67="","Pendiente primera actuación",IF(N67="N.A.","N.A.",IF(NETWORKDAYS((G67+1),N67,'Días No Laborales'!$A$2:$U$145)<=20,"SI","NO"))))) -> SI | Q67: NO | W67: 45832 | Y67: N/A | Z67: =IF(B67="","",IF(W67="","Pendiente de sentencia",IF(W67="N.A.","N.A.",DAYS360(G67,W67)))) -> 261 | AA67: N/A | AB67: ORDENA SEGUIR ADELANTE CON LA EJECUCION | AC67: 2025-2 | AD67: OSAE - COSTAS | AE67: 45832 | AF67: CAROLINA | AG67: 01 CIVIL MCPAL | AH67: ELECTRONICO | AM67: VENCEN 04/03/2025
A68: 61 | B68: 001-2024-00605 | C68: EJECUTIVO | D68: POR SUMAS DE DINERO | E68: MENOR | F68: REMITIDA POR OTRO DESPACHO | G68: 45568 | H68: BANCO DAVIVIENDA | I68: 2 | J68: 1 | K68: ANDERSON ZAPATA PAVAS | L68: 1 | M68: 1 | N68: 45568 | O68: =IF(G68="","",(IF(N68="","Pendiente primera actuación",IF(N68="N.A.","N.A.",IF(NETWORKDAYS((G68+1),N68,'Días No Laborales'!$A$2:$U$145)<=20,"SI","NO"))))) -> SI | Q68: NO | W68: 45679 | Y68: N/A | Z68: =IF(B68="","",IF(W68="","Pendiente de sentencia",IF(W68="N.A.","N.A.",DAYS360(G68,W68)))) -> 109 | AA68: N/A | AB68: ORDENA SEGUIR ADELANTE CON LA EJECUCIÓN | AC68: 2025-1 | AD68: REQUIERE 5 DIAS | AE68: 45734 | AF68: CAMILA | AG68: 01 CIVIL MCPAL | AH68: ELECTRONICO
A69: 62 | B69: 001-2024-00608 | C69: EJECUTIVO | D69: POR SUMAS DE DINERO | E69: MINIMA | F69: REMITIDA POR OTRO DESPACHO | G69: 45568 | H69: ARRENDAMIENTOS ROGELIO ACOSTA | I69: 1 | J69: 2 | K69: JOSE VASQUEZ MURILLO | L69: 0 | M69: 2 | N69: 45568 | O69: =IF(G69="","",(IF(N69="","Pendiente primera actuación",IF(N69="N.A.","N.A.",IF(NETWORKDAYS((G69+1),N69,'Días No Laborales'!$A$2:$U$145)<=20,"SI","NO"))))) -> SI | Q69: NO | W69: 45825 | Y69: N/A | Z69: =IF(B69="","",IF(W69="","Pendiente de sentencia",IF(W69="N.A.","N.A.",DAYS360(G69,W69)))) -> 254 | AA69: N/A | AB69: DESISTIMIENTO TACITO | AC69: 2025-2 | AD69: DESISTIMIENTO TACITO | AE69: 45825 | AF69: LACIDES | AG69: 01 CIVIL MCPAL | AH69: ELECTRONICO
A70: 63 | B70: 001-2024-00616 | C70: EJECUTIVO | D70: POR SUMAS DE DINERO | E70: MINIMA | F70: REMITIDA POR OTRO DESPACHO | G70: 45568 | H70: BANCO DE OCCIDENTE | I70: 0 | J70: 1 | K70: MARIA NORELIA CORREA RAMRIEZ | L70: 2 | M70: 1 | N70: 45568 | O70: =IF(G70="","",(IF(N70="","Pendiente primera actuación",IF(N70="N.A.","N.A.",IF(NETWORKDAYS((G70+1),N70,'Días No Laborales'!$A$2:$U$145)<=20,"SI","NO"))))) -> SI | Q70: NO | W70: 45811 | Y70: N/A | Z70: =IF(B70="","",IF(W70="","Pendiente de sentencia",IF(W70="N.A.","N.A.",DAYS360(G70,W70)))) -> 240 | AA70: N/A | AB70: ORDENA SEGUIR ADELANTE CON LA EJECUCION | AC70: 2025-2 | AD70: OSAE - COSTAS | AE70: 45811 | AF70: CAROLINA | AG70: 01 CIVIL MCPAL | AH70: ELECTRONICO
A71: 64 | B71: 001-2024-00626 | C71: EJECUTIVO | D71: POR SUMAS DE DINERO | E71: MINIMA | F71: REMITIDA POR OTRO DESPACHO | G71: 45568 | H71: BANCO POPULAR | I71: 2 | J71: 2 | K71: OSCAR DE JESUS VILLADA CARDONA | L71: 2 | M71: 2 | N71: 45568 | O71: =IF(G71="","",(IF(N71="","Pendiente primera actuación",IF(N71="N.A.","N.A.",IF(NETWORKDAYS((G71+1),N71,'Días No Laborales'!$A$2:$U$145)<=20,"SI","NO"))))) -> SI | Q71: NO | W71: 45574 | Y71: N/A | Z71: =IF(B71="","",IF(W71="","Pendiente de sentencia",IF(W71="N.A.","N.A.",DAYS360(G71,W71)))) -> 6 | AA71: N/A | AB71: ORDENA SEGUIR ADELANTE CON LA EJECUCIÓN | AC71: 2024-4 | AD71: OSAE - COSTAS | AE71: 45574 | AF71: LACIDES | AG71: 01 CIVIL MCPAL | AH71: ELECTRONICO | AJ71: X
A72: 65 | B72: 001-2024-00629 | C72: EJECUTIVO | D72: POR SUMAS DE DINERO | E72: MENOR | F72: REMITIDA POR OTRO DESPACHO | G72: 45568 | H72: BANCO DE OCCIDENTE S.A. | I72: 2 | J72: 1 | K72: CLAUDIA FONNEGRA TOBON | L72: 1 | M72: 1 | N72: 45568 | O72: =IF(G72="","",(IF(N72="","Pendiente primera actuación",IF(N72="N.A.","N.A.",IF(NETWORKDAYS((G72+1),N72,'Días No Laborales'!$A$2:$U$145)<=20,"SI","NO"))))) -> SI | Q72: NO | W72: 45735 | Y72: N/A | Z72: =IF(B72="","",IF(W72="","Pendiente de sentencia",IF(W72="N.A.","N.A.",DAYS360(G72,W72)))) -> 166 | AA72: N/A | AB72: ORDENA SEGUIR ADELANTE CON LA EJECUCIÓN | AC72: 2025-1 | AD72: REQUIERE | AE72: 45776 | AF72: CAMILA | AG72: 01 CIVIL MCPAL | AH72: ELECTRONICO
A73: 66 | B73: 001-2024-00642 | C73: EJECUTIVO | D73: POR SUMAS DE DINERO | E73: MINIMA | F73: REMITIDA POR OTRO DESPACHO | G73: 45568 | H73: SEGUROS COMERCIALES BOLIVAR S.A. | I73: 1 | J73: 0 | K73: FABIAN DE JESUS PINO JARAMILLO | L73: 1 | M73: 0 | N73: 45568 | O73: =IF(G73="","",(IF(N73="","Pendiente primera actuación",IF(N73="N.A.","N.A.",IF(NETWORKDAYS((G73+1),N73,'Días No Laborales'!$A$2:$U$145)<=20,"SI","NO"))))) -> SI | Q73: NO | W73: 45715 | Y73: N/A | Z73: =IF(B73="","",IF(W73="","Pendiente de sentencia",IF(W73="N.A.","N.A.",DAYS360(G73,W73)))) -> 144 | AA73: N/A | AB73: ORDENA SEGUIR ADELANTE CON LA EJECUCION | AC73: 2025-1 | AD73: ORDENA TRALADO DE LIQUIDACION DE CREDITO | AE73: 45805 | AF73: CAROLINA | AG73: 01 CIVIL MCPAL | AH73: ELECTRONICO | AM73: ORDENA SEGUIR ADELANTE LA EJECUCION
A74: 67 | B74: 001-2024-00646 | C74: RESTITUCION BIEN INMUEBLE | D74: VERBAL SUMARIO | E74: MINIMA | F74: REMITIDA POR OTRO DESPACHO | G74: 45568 | H74: ARRENDAMIENTOS ABURRA SUR S.A.S | I74: 1 | J74: 2 | K74: JOSE GUILLERMO RUIZ JARAMILLO | L74: 1 | M74: 2 | N74: 45568 | O74: =IF(G74="","",(IF(N74="","Pendiente primera actuación",IF(N74="N.A.","N.A.",IF(NETWORKDAYS((G74+1),N74,'Días No Laborales'!$A$2:$U$145)<=20,"SI","NO"))))) -> SI | Q74: NO | W74: 45719 | Y74: N/A | Z74: =IF(B74="","",IF(W74="","Pendiente de sentencia",IF(W74="N.A.","N.A.",DAYS360(G74,W74)))) -> 150 | AA74: N/A | AB74: DESISTIMIENTO TACITO | AC74: 2025-1 | AD74: DESISTIMIENTO TACITO | AE74: 45719 | AF74: LACIDES | AG74: 01 CIVIL MCPAL | AH74: ELECTRONICO | AI74: 45731 | AM74: DESISTIMIENTO TACITO
A75: 68 | B75: 001-2024-00647 | C75: EJECUTIVO | D75: POR SUMAS DE DINERO | E75: MINIMA | F75: REMITIDA POR OTRO DESPACHO | G75: 45568 | H75: BANCO FINANDINA S.A. | I75: 1 | J75: 1 | K75: CARLOS ANDRES PEREZ PEREZ | L75: 1 | M75: 1 | N75: 45568 | O75: =IF(G75="","",(IF(N75="","Pendiente primera actuación",IF(N75="N.A.","N.A.",IF(NETWORKDAYS((G75+1),N75,'Días No Laborales'!$A$2:$U$145)<=20,"SI","NO"))))) -> SI | Q75: NO | W75: 45700 | Y75: N/A | Z75: =IF(B75="","",IF(W75="","Pendiente de sentencia",IF(W75="N.A.","N.A.",DAYS360(G75,W75)))) -> 129 | AA75: N/A | AB75: ORDENA SEGUIR ADELANTE CON LA EJECUCIÓN | AC75: 2025-2 | AD75: REQUIERE ART. 317 | AE75: 45818 | AF75: CAMILA | AG75: 01 CIVIL MCPAL | AH75: ELECTRONICO | AM75: VENCE 30 DIAS: 25/07/2025
A76: 69 | B76: 001-2024-00693 | C76: EJECUTIVO | D76: POR SUMAS DE DINERO | E76: MENOR | F76: REMITIDA POR OTRO DESPACHO | G76: 45568 | H76: BANCO DAVIVIENDA S.A. | I76: 1 | J76: 0 | K76: JUAN FELIPE TABARES DIAZ | L76: 1 | M76: 0 | N76: 45568 | O76: =IF(G76="","",(IF(N76="","Pendiente primera actuación",IF(N76="N.A.","N.A.",IF(NETWORKDAYS((G76+1),N76,'Días No Laborales'!$A$2:$U$145)<=20,"SI","NO"))))) -> SI | Q76: NO | W76: 45714 | Y76: N/A | Z76: =IF(B76="","",IF(W76="","Pendiente de sentencia",IF(W76="N.A.","N.A.",DAYS360(G76,W76)))) -> 143 | AA76: N/A | AB76: ORDENA SEGUIR ADELANTE CON LA EJECUCIÓN | AC76: 2025-1 | AD76: APRUEBA LIQUIDACION | AE76: 45785 | AF76: CAROLINA | AG76: 01 CIVIL MCPAL | AH76: ELECTRONICO
A77: 70 | B77: 001-2024-00661 | C77: EJECUTIVO | D77: POR SUMAS DE DINERO | E77: MINIMA | F77: REMITIDA POR OTRO DESPACHO | G77: 45568 | H77: EUGENIO ALONSO MARIN VALLEJO | I77: 1 | J77: 2 | K77: GISELA TAMAYO LONDOÑO | L77: 0 | M77: 2 | N77: 45568 | O77: =IF(G77="","",(IF(N77="","Pendiente primera actuación",IF(N77="N.A.","N.A.",IF(NETWORKDAYS((G77+1),N77,'Días No Laborales'!$A$2:$U$145)<=20,"SI","NO"))))) -> SI | Q77: NO | W77: 45574 | Y77: N/A | Z77: =IF(B77="","",IF(W77="","Pendiente de sentencia",IF(W77="N.A.","N.A.",DAYS360(G77,W77)))) -> 6 | AA77: N/A | AB77: ORDENA SEGUIR ADELANTE CON LA EJECUCIÓN | AC77: 2024-4 | AD77: REQUIERE 5 DIAS | AE77: 45846 | AF77: LACIDES | AG77: 01 CIVIL MCPAL | AH77: ELECTRONICO | AJ77: X
A78: 71 | B78: 001-2024-00662 | C78: EJECUTIVO | D78: POR SUMAS DE DINERO | E78: MINIMA | F78: REMITIDA POR OTRO DESPACHO | G78: 45568 | H78: CMT ELECTRODOMESTICOS S.A. | I78: 0 | J78: 1 | K78: INDIRA QUINTANA ARANGO | L78: 0 | M78: 1 | N78: 45568 | O78: =IF(G78="","",(IF(N78="","Pendiente primera actuación",IF(N78="N.A.","N.A.",IF(NETWORKDAYS((G78+1),N78,'Días No Laborales'!$A$2:$U$145)<=20,"SI","NO"))))) -> SI | Q78: NO | W78: 45868 | Y78: N/A | Z78: =IF(B78="","",IF(W78="","Pendiente de sentencia",IF(W78="N.A.","N.A.",DAYS360(G78,W78)))) -> 297 | AA78: N/A | AB78: TERMINA POR DESISTIMIENTO TACITO | AC78: 2025-3 | AD78: TERMINA POR DESISTIMIENTO TACITO | AE78: 45868 | AF78: CAMILA | AG78: 01 CIVIL MCPAL | AH78: ELECTRONICO | AM78: 9 MAYO VENCE
A79: 72 | B79: 001-2024-00664 | C79: EJECUTIVO | D79: POR SUMAS DE DINERO | E79: MINIMA | F79: REMITIDA POR OTRO DESPACHO | G79: 45568 | H79: CMT ELECTRODOMESTICOS S.A. | I79: 0 | J79: 2 | K79: ANDRES FELIPE ISAZA LONDOÑO | L79: 0 | M79: 2 | N79: 45568 | O79: =IF(G79="","",(IF(N79="","Pendiente primera actuación",IF(N79="N.A.","N.A.",IF(NETWORKDAYS((G79+1),N79,'Días No Laborales'!$A$2:$U$145)<=20,"SI","NO"))))) -> SI | Q79: NO | Y79: N/A | Z79: =IF(B79="","",IF(W79="","Pendiente de sentencia",IF(W79="N.A.","N.A.",DAYS360(G79,W79)))) -> Pendiente de sentencia | AA79: N/A | AD79: REQUIERE 5 DIAS | AE79: 45714 | AF79: CAROLINA | AG79: 01 CIVIL MCPAL | AH79: ELECTRONICO
A80: 73 | B80: 001-2024-00665 | C80: EJECUTIVO | D80: POR SUMAS DE DINERO | E80: MENOR | F80: REMITIDA POR OTRO DESPACHO | G80: 45568 | H80: BANCO BBVA COLOMBIA | I80: 0 | J80: 1 | K80: FABIO FRANCO JIMENEZ | L80: 0 | M80: 1 | N80: 45568 | O80: =IF(G80="","",(IF(N80="","Pendiente primera actuación",IF(N80="N.A.","N.A.",IF(NETWORKDAYS((G80+1),N80,'Días No Laborales'!$A$2:$U$145)<=20,"SI","NO"))))) -> SI | Q80: NO | Y80: N/A | Z80: =IF(B80="","",IF(W80="","Pendiente de sentencia",IF(W80="N.A.","N.A.",DAYS360(G80,W80)))) -> Pendiente de sentencia | AA80: N/A | AD80: ADMIITE REFORMA DEMANDA | AE80: 45672 | AF80: LACIDES | AG80: 01 CIVIL MCPAL | AH80: ELECTRONICO
A81: 74 | B81: 001-2024-00669 | C81: EJECUTIVO | D81: POR SUMAS DE DINERO | E81: MINIMA | F81: REMITIDA POR OTRO DESPACHO | G81: 45568 | H81: IMDUCOP S.A.S. | I81: 0 | J81: 2 | K81: COVINILTEX S.A.S | L81: 1 | M81: 2 | N81: 45568 | O81: =IF(G81="","",(IF(N81="","Pendiente primera actuación",IF(N81="N.A.","N.A.",IF(NETWORKDAYS((G81+1),N81,'Días No Laborales'!$A$2:$U$145)<=20,"SI","NO"))))) -> SI | Q81: NO | W81: 45575 | Y81: N/A | Z81: =IF(B81="","",IF(W81="","Pendiente de sentencia",IF(W81="N.A.","N.A.",DAYS360(G81,W81)))) -> 7 | AA81: N/A | AB81: ORDENA SEGUIR ADELANTE CON LA EJECUCIÓN | AC81: 2024-4 | AD81: DECRETA EMBARGO | AE81: 45776 | AF81: CAMILA | AG81: 01 CIVIL MCPAL | AH81: ELECTRONICO | AJ81: X
A82: 75 | B82: 001-2024-00683 | C82: RESOLUCION DE CONTRATO | D82: DECLARATIVO VERBAL SUMARIO OTROS PROCESO | E82: MINIMA | F82: REMITIDA POR OTRO DESPACHO | G82: 45568 | H82: SEGUROS DE VIDA SURA | I82: 1 | J82: 0 | K82: ALCIRA ESTRADA MORALES | L82: 2 | M82: 0 | N82: 45568 | O82: =IF(G82="","",(IF(N82="","Pendiente primera actuación",IF(N82="N.A.","N.A.",IF(NETWORKDAYS((G82+1),N82,'Días No Laborales'!$A$2:$U$145)<=20,"SI","NO"))))) -> SI | Q82: NO | Y82: N/A | Z82: =IF(B82="","",IF(W82="","Pendiente de sentencia",IF(W82="N.A.","N.A.",DAYS360(G82,W82)))) -> Pendiente de sentencia | AA82: N/A | AD82: INCORPORA DOCUMENTACION | AE82: 45846 | AF82: LACIDES | AG82: 01 CIVIL MCPAL | AH82: ELECTRONICO
A83: 76 | B83: 001-2024-00685 | C83: EJECUTIVO | D83: POR SUMAS DE DINERO | E83: MINIMA | F83: REMITIDA POR OTRO DESPACHO | G83: 45568 | H83: COOPERATIVA JHON F. KENNEDY | I83: 2 | J83: 1 | K83: MELISSA GARCIA VASQUEZ | L83: 1 | M83: 1 | N83: 45568 | O83: =IF(G83="","",(IF(N83="","Pendiente primera actuación",IF(N83="N.A.","N.A.",IF(NETWORKDAYS((G83+1),N83,'Días No Laborales'!$A$2:$U$145)<=20,"SI","NO"))))) -> SI | Q83: NO | W83: 45803 | Y83: N/A | Z83: =IF(B83="","",IF(W83="","Pendiente de sentencia",IF(W83="N.A.","N.A.",DAYS360(G83,W83)))) -> 233 | AA83: N/A | AB83: ORDENA SEGUIR ADELANTE CON LA EJECUCIÓN | AC83: 2025-2 | AD83: ORDENA CORRER TRASLADO LIQUIDACION DE CREDITO | AE83: 45803 | AF83: CAROLINA | AG83: 01 CIVIL MCPAL | AH83: ELECTRONICO
A84: 77 | B84: 001-2024-00701 | C84: EJECUTIVO | D84: POR SUMAS DE DINERO | E84: MINIMA | F84: REMITIDA POR OTRO DESPACHO | G84: 45568 | H84: COTRAFA COOPERATIVA FINANCIERA | I84: 1 | J84: 0 | K84: ANA MILENA NAVARRO MAZO | L84: 0 | M84: 0 | N84: 45568 | O84: =IF(G84="","",(IF(N84="","Pendiente primera actuación",IF(N84="N.A.","N.A.",IF(NETWORKDAYS((G84+1),N84,'Días No Laborales'!$A$2:$U$145)<=20,"SI","NO"))))) -> SI | Q84: NO | W84: 45632 | Y84: N/A | Z84: =IF(B84="","",IF(W84="","Pendiente de sentencia",IF(W84="N.A.","N.A.",DAYS360(G84,W84)))) -> 63 | AA84: N/A | AB84: ORDENA SEGUIR ADELANTE CON LA EJECUCIÓN | AC84: 2024-4 | AD84: APRUEBA LIQUIDACION CREDITO | AE84: 45743 | AF84: CAMILA | AG84: 01 CIVIL MCPAL | AH84: ELECTRONICO | AJ84: X | AM84: TRASLADO LIQUIDACION DE CREDITO FIJADA EL 19 Y TERMINA EL 25/03/2025
A85: 78 | B85: 001-2024-00711 | C85: EJECUTIVO CON GARANTIA REAL | D85: EJECUTIVO CON GARANTIA REAL | E85: MENOR | F85: REMITIDA POR OTRO DESPACHO | G85: 45568 | H85: BANCOLOMBIA S.A. | I85: 0 | J85: 1 | K85: JAIME NELSON LOAIZA RODRIGUEZ | L85: 1 | M85: 1 | N85: 45568 | O85: =IF(G85="","",(IF(N85="","Pendiente primera actuación",IF(N85="N.A.","N.A.",IF(NETWORKDAYS((G85+1),N85,'Días No Laborales'!$A$2:$U$145)<=20,"SI","NO"))))) -> SI | Q85: NO | W85: 45733 | Y85: N/A | Z85: =IF(B85="","",IF(W85="","Pendiente de sentencia",IF(W85="N.A.","N.A.",DAYS360(G85,W85)))) -> 164 | AA85: N/A | AB85: TERMINA POR PAGO TOTAL | AC85: 2025-1 | AD85: TERMINA POR PAGO | AE85: 45733 | AF85: LACIDES | AG85: 01 CIVIL MCPAL | AH85: ELECTRONICO | AI85: 45743
A86: 79 | B86: 001-2024-00719 | C86: EJECUTIVO | D86: POR SUMAS DE DINERO | E86: MINIMA | F86: REMITIDA POR OTRO DESPACHO | G86: 45568 | H86: COOPERATIVA JHON F. KENNEDY | I86: 1 | J86: 0 | K86: ADRIANA YANETH ARIAS CIFUENTES | L86: 2 | M86: 0 | N86: 45568 | O86: =IF(G86="","",(IF(N86="","Pendiente primera actuación",IF(N86="N.A.","N.A.",IF(NETWORKDAYS((G86+1),N86,'Días No Laborales'!$A$2:$U$145)<=20,"SI","NO"))))) -> SI | Q86: NO | Y86: N/A | Z86: =IF(B86="","",IF(W86="","Pendiente de sentencia",IF(W86="N.A.","N.A.",DAYS360(G86,W86)))) -> Pendiente de sentencia | AA86: N/A | AD86: REITERA REQUERIMIENTO | AE86: 45715 | AF86: CAROLINA | AG86: 01 CIVIL MCPAL | AH86: ELECTRONICO
A87: 80 | B87: 001-2024-00723 | C87: EJECUTIVO | D87: POR SUMAS DE DINERO | E87: MINIMA | F87: REMITIDA POR OTRO DESPACHO | G87: 45568 | H87: CONJUNTO RESIDENCIAL PORTAL DEL VALLE P.H. | I87: 2 | J87: 1 | K87: DARIO MANRIQUE BARAJAS | L87: 0 | M87: 1 | N87: 45568 | O87: =IF(G87="","",(IF(N87="","Pendiente primera actuación",IF(N87="N.A.","N.A.",IF(NETWORKDAYS((G87+1),N87,'Días No Laborales'!$A$2:$U$145)<=20,"SI","NO"))))) -> SI | Q87: NO | W87: 45797 | Y87: N/A | Z87: =IF(B87="","",IF(W87="","Pendiente de sentencia",IF(W87="N.A.","N.A.",DAYS360(G87,W87)))) -> 227 | AA87: N/A | AB87: TERMINA POR PAGO | AC87: 2025-2 | AD87: TERMINA POR PAGO TOTAL | AE87: 45797 | AF87: LINA | AG87: 01 CIVIL MCPAL | AH87: ELECTRONICO | AI87: 45814
A88: 81 | B88: 001-2024-00724 | C88: EJECUTIVO | D88: POR SUMAS DE DINERO | E88: MINIMA | F88: REMITIDA POR OTRO DESPACHO | G88: 45568 | H88: COTRAFA COOPERATIVA FINANCIERA | I88: 0 | J88: 0 | K88: MONICA LILIANA TABARES PATIÑO | L88: 1 | M88: 0 | N88: 45568 | O88: =IF(G88="","",(IF(N88="","Pendiente primera actuación",IF(N88="N.A.","N.A.",IF(NETWORKDAYS((G88+1),N88,'Días No Laborales'!$A$2:$U$145)<=20,"SI","NO"))))) -> SI | Q88: NO | W88: 45581 | Y88: N/A | Z88: =IF(B88="","",IF(W88="","Pendiente de sentencia",IF(W88="N.A.","N.A.",DAYS360(G88,W88)))) -> 13 | AA88: N/A | AB88: ORDENA SEGUIR ADELANTE CON LA EJECUCIÓN | AC88: 2024-4 | AD88: APRUEBA LIQUIDACION CREDITO | AE88: 45743 | AF88: CAMILA | AG88: 01 CIVIL MCPAL | AH88: ELECTRONICO | AJ88: X
A89: 82 | B89: 001-2024-00727 | C89: EJECUTIVO | D89: POR SUMAS DE DINERO | E89: MINIMA | F89: REMITIDA POR OTRO DESPACHO | G89: 45568 | H89: COOPERATIVA JHON F. KENNEDY | I89: 1 | J89: 1 | K89: JUAN FERNANDO BERNAL FLOREZ | L89: 2 | M89: 1 | N89: 45568 | O89: =IF(G89="","",(IF(N89="","Pendiente primera actuación",IF(N89="N.A.","N.A.",IF(NETWORKDAYS((G89+1),N89,'Días No Laborales'!$A$2:$U$145)<=20,"SI","NO"))))) -> SI | Q89: NO | W89: 45604 | Y89: N/A | Z89: =IF(B89="","",IF(W89="","Pendiente de sentencia",IF(W89="N.A.","N.A.",DAYS360(G89,W89)))) -> 35 | AA89: N/A | AB89: ORDENA SEGUIR ADELANTE CON LA EJECUCIÓN | AC89: 2024-4 | AD89: INCORPORA Y RESPONDE | AE89: 45846 | AF89: LACIDES | AG89: 01 CIVIL MCPAL | AH89: ELECTRONICO | AI89: 21/03/20025 | AJ89: X
A90: 83 | B90: 001-2024-00729 | C90: EJECUTIVO | D90: POR SUMAS DE DINERO | E90: MINIMA | F90: REMITIDA POR OTRO DESPACHO | G90: 45568 | H90: CONFIAR COOPERATIVA FINANCIERA | I90: 2 | J90: 0 | K90: KATERINE AGUDELO MARIN | L90: 0 | M90: 0 | N90: 45568 | O90: =IF(G90="","",(IF(N90="","Pendiente primera actuación",IF(N90="N.A.","N.A.",IF(NETWORKDAYS((G90+1),N90,'Días No Laborales'!$A$2:$U$145)<=20,"SI","NO"))))) -> SI | Q90: NO | W90: 45628 | Y90: N/A | Z90: =IF(B90="","",IF(W90="","Pendiente de sentencia",IF(W90="N.A.","N.A.",DAYS360(G90,W90)))) -> 59 | AA90: N/A | AB90: TERMINA POR PAGO TOTAL | AC90: 2024-4 | AD90: TERMINA POR PAGO TOTAL | AE90: 45628 | AF90: CAROLINA | AG90: 01 CIVIL MCPAL | AH90: ELECTRONICO
A91: 84 | B91: 001-2024-00735 | C91: EJECUTIVO | D91: POR SUMAS DE DINERO | E91: MINIMA | F91: REMITIDA POR OTRO DESPACHO | G91: 45568 | H91: BANCO AV VILLAS | I91: 0 | J91: 1 | K91: GIOVANNY GERONIMO SERRANO GONZALEZ | L91: 1 | M91: 1 | N91: 45568 | O91: =IF(G91="","",(IF(N91="","Pendiente primera actuación",IF(N91="N.A.","N.A.",IF(NETWORKDAYS((G91+1),N91,'Días No Laborales'!$A$2:$U$145)<=20,"SI","NO"))))) -> SI | Q91: NO | W91: 45685 | Y91: N/A | Z91: =IF(B91="","",IF(W91="","Pendiente de sentencia",IF(W91="N.A.","N.A.",DAYS360(G91,W91)))) -> 115 | AA91: N/A | AB91: ORDENA SEGUIR ADELANTE CON LA EJECUCIÓN | AC91: 2025-1 | AD91: REQUIERE ART. 317 | AE91: 45861 | AF91: LACIDES | AG91: 01 CIVIL MCPAL | AH91: ELECTRONICO | AJ91: X
A92: 85 | B92: 001-2024-00736 | C92: EJECUTIVO | D92: POR SUMAS DE DINERO | E92: MENOR | F92: REMITIDA POR OTRO DESPACHO | G92: 45568 | H92: BANCOOMEVA | I92: 1 | J92: 0 | K92: ANA MARIA MEDINA DUQUE | L92: 2 | M92: 0 | N92: 45568 | O92: =IF(G92="","",(IF(N92="","Pendiente primera actuación",IF(N92="N.A.","N.A.",IF(NETWORKDAYS((G92+1),N92,'Días No Laborales'!$A$2:$U$145)<=20,"SI","NO"))))) -> SI | Q92: NO | W92: 45576 | Y92: N/A | Z92: =IF(B92="","",IF(W92="","Pendiente de sentencia",IF(W92="N.A.","N.A.",DAYS360(G92,W92)))) -> 8 | AA92: N/A | AB92: ORDENA SEGUIR ADELANTE CON LA EJECUCIÓN | AC92: 2024-4 | AD92: APRUEBA LIQUIDACION CREDITO | AE92: 45743 | AF92: CAMILA | AG92: 01 CIVIL MCPAL | AH92: ELECTRONICO | AJ92: X
A93: 86 | B93: 001-2024-00742 | C93: EJECUTIVO | D93: POR SUMAS DE DINERO | E93: MINIMA | F93: REMITIDA POR OTRO DESPACHO | G93: 45568 | H93: CONJUNTO RESIDENCIA ORINOCO P.H. | I93: 2 | J93: 1 | K93: MATEO MAYA MEJIA | L93: 0 | M93: 1 | N93: 45568 | O93: =IF(G93="","",(IF(N93="","Pendiente primera actuación",IF(N93="N.A.","N.A.",IF(NETWORKDAYS((G93+1),N93,'Días No Laborales'!$A$2:$U$145)<=20,"SI","NO"))))) -> SI | Q93: NO | W93: 45601 | Y93: N/A | Z93: =IF(B93="","",IF(W93="","Pendiente de sentencia",IF(W93="N.A.","N.A.",DAYS360(G93,W93)))) -> 32 | AA93: N/A | AB93: ORDENA SEGUIR ADELANTE CON LA EJECUCIÓN | AC93: 2024-4 | AD93: TERMINA POR PACO CON OSAE | AE93: 45742 | AF93: LACIDES | AG93: 01 CIVIL MCPAL | AH93: ELECTRONICO | AJ93: X
A94: 87 | B94: 001-2024-00744 | C94: EJECUTIVO | D94: POR SUMAS DE DINERO | E94: MINIMA | F94: REMITIDA POR OTRO DESPACHO | G94: 45568 | H94: COTRAFA COOPERATIVA FINANCIERA | I94: 0 | J94: 0 | K94: STIVEN SALAZAR AGUDELO | L94: 1 | M94: 0 | N94: 45568 | O94: =IF(G94="","",(IF(N94="","Pendiente primera actuación",IF(N94="N.A.","N.A.",IF(NETWORKDAYS((G94+1),N94,'Días No Laborales'!$A$2:$U$145)<=20,"SI","NO"))))) -> SI | Q94: NO | W94: 45672 | Y94: N/A | Z94: =IF(B94="","",IF(W94="","Pendiente de sentencia",IF(W94="N.A.","N.A.",DAYS360(G94,W94)))) -> 102 | AA94: N/A | AB94: ORDENA SEGUIR ADELANTE CON LA EJECUCIÓN | AC94: 2025-1 | AD94: ACEPTA RENUNCIA PODER | AE94: 45891 | AF94: CAROLINA | AG94: 01 CIVIL MCPAL | AH94: ELECTRONICO
A95: 88 | B95: 001-2024-00746 | C95: EJECUTIVO | D95: POR SUMAS DE DINERO | E95: MINIMA | F95: REMITIDA POR OTRO DESPACHO | G95: 45568 | H95: CONFIAR COOPERATIVA FINANCIERA | I95: 1 | J95: 1 | K95: ALVARO DE JESUS CASTAÑO MOLINA | L95: 2 | M95: 1 | N95: 45568 | O95: =IF(G95="","",(IF(N95="","Pendiente primera actuación",IF(N95="N.A.","N.A.",IF(NETWORKDAYS((G95+1),N95,'Días No Laborales'!$A$2:$U$145)<=20,"SI","NO"))))) -> SI | Q95: NO | W95: 45635 | Y95: N/A | Z95: =IF(B95="","",IF(W95="","Pendiente de sentencia",IF(W95="N.A.","N.A.",DAYS360(G95,W95)))) -> 66 | AA95: N/A | AB95: ORDENA SEGUIR ADELANTE CON LA EJECUCIÓN | AC95: 2024-4 | AD95: OSAE - COSTAS | AE95: 45804 | AF95: CAMILA | AG95: 01 CIVIL MCPAL | AH95: ELECTRONICO | AJ95: X
A96: 89 | B96: 001-2024-00752 | C96: EJECUTIVO CON GARANTIA REAL | D96: EJECUTIVO CON GARANTIA REAL | E96: MENOR | F96: REMITIDA POR OTRO DESPACHO | G96: 45568 | H96: BANCOLOMBIA S.A. | I96: 2 | J96: 0 | K96: WILLIAM DE JESUS ACEVEDO CAMPUZANO | L96: 0 | M96: 0 | N96: 45568 | O96: =IF(G96="","",(IF(N96="","Pendiente primera actuación",IF(N96="N.A.","N.A.",IF(NETWORKDAYS((G96+1),N96,'Días No Laborales'!$A$2:$U$145)<=20,"SI","NO"))))) -> SI | Q96: NO | W96: 45729 | Y96: N/A | Z96: =IF(B96="","",IF(W96="","Pendiente de sentencia",IF(W96="N.A.","N.A.",DAYS360(G96,W96)))) -> 160 | AA96: N/A | AB96: ORDENA SEGUIR ADELANTE CON LA EJECUCIÓN | AC96: 2025-1 | AD96: REQUIERE 5 DIAS | AE96: 45861 | AF96: LACIDES | AG96: 01 CIVIL MCPAL | AH96: ELECTRONICO | AI96: 45743
A97: 90 | B97: 001-2024-00748 | C97: EJECUTIVO | D97: POR SUMAS DE DINERO | E97: MINIMA | F97: REMITIDA POR OTRO DESPACHO | G97: 45568 | H97: BANCO DE BOGOTA S.A. | I97: 0 | J97: 1 | K97: LUIS FERNANDO MURILLO QUICENO | L97: 1 | M97: 1 | N97: 45568 | O97: =IF(G97="","",(IF(N97="","Pendiente primera actuación",IF(N97="N.A.","N.A.",IF(NETWORKDAYS((G97+1),N97,'Días No Laborales'!$A$2:$U$145)<=20,"SI","NO"))))) -> SI | Q97: NO | W97: 45715 | Y97: N/A | Z97: =IF(B97="","",IF(W97="","Pendiente de sentencia",IF(W97="N.A.","N.A.",DAYS360(G97,W97)))) -> 144 | AA97: N/A | AB97: ORDENA SEGUIR ADELANTE CON LA EJECUCIÓN | AC97: 2025-1 | AD97: OSAE - COSTAS | AE97: 45618 | AF97: CAROLINA | AG97: 01 CIVIL MCPAL | AH97: ELECTRONICO
A98: 91 | B98: 001-2024-00755 | C98: EJECUTIVO | D98: POR SUMAS DE DINERO | E98: MENOR | F98: REMITIDA POR OTRO DESPACHO | G98: 45568 | H98: BANCO DE BOGOTA S.A. | I98: 1 | J98: 0 | K98: PABLO MARIO VANEGAS VELASQUEZ | L98: 2 | M98: 1 | N98: 45568 | O98: =IF(G98="","",(IF(N98="","Pendiente primera actuación",IF(N98="N.A.","N.A.",IF(NETWORKDAYS((G98+1),N98,'Días No Laborales'!$A$2:$U$145)<=20,"SI","NO"))))) -> SI | Q98: NO | W98: 45853 | Y98: N/A | Z98: =IF(B98="","",IF(W98="","Pendiente de sentencia",IF(W98="N.A.","N.A.",DAYS360(G98,W98)))) -> 282 | AA98: N/A | AB98: ORDENA SEGUIR ADELANTE CON LA EJECUCION | AC98: 2025-3 | AD98: INCORPORA Y ORDENA TRASLADO LIQUIDACION | AE98: 45891 | AF98: CAMILA | AG98: 01 CIVIL MCPAL | AH98: ELECTRONICO
A99: 92 | B99: 001-2024-00758 | C99: EJECUTIVO | D99: POR SUMAS DE DINERO | E99: MINIMA | F99: REMITIDA POR OTRO DESPACHO | G99: 45568 | H99: EDIFICIO PALMAS DE ZUÑIGA P.H. | I99: 2 | J99: 0 | K99: THOMAS ANTONIO FAJARDO DELGADO | L99: 0 | M99: 1 | N99: 45568 | O99: =IF(G99="","",(IF(N99="","Pendiente primera actuación",IF(N99="N.A.","N.A.",IF(NETWORKDAYS((G99+1),N99,'Días No Laborales'!$A$2:$U$145)<=20,"SI","NO"))))) -> SI | Q99: NO | W99: 45736 | Y99: N/A | Z99: =IF(B99="","",IF(W99="","Pendiente de sentencia",IF(W99="N.A.","N.A.",DAYS360(G99,W99)))) -> 167 | AA99: N/A | AB99: ORDENA SEGUIR ADELANTE CON LA EJECUCIÓN | AC99: 2025-1 | AD99: DECRETA SECUESTRO Y COMISIONA | AE99: 45868 | AF99: CAMILA | AG99: 01 CIVIL MCPAL | AH99: ELECTRONICO | AM99: VENCE 22/11/2024
A100: 93 | B100: 001-2024-00761 | C100: EJECUTIVO | D100: POR SUMAS DE DINERO | E100: MENOR | F100: REMITIDA POR OTRO DESPACHO | G100: 45568 | H100: BANCOOMEVA | I100: 0 | J100: 1 | K100: ISAIAS GARCERANT CAMPO | L100: 1 | M100: 1 | N100: 45568 | O100: =IF(G100="","",(IF(N100="","Pendiente primera actuación",IF(N100="N.A.","N.A.",IF(NETWORKDAYS((G100+1),N100,'Días No Laborales'!$A$2:$U$145)<=20,"SI","NO"))))) -> SI | Q100: NO | W100: 45583 | Y100: N/A | Z100: =IF(B100="","",IF(W100="","Pendiente de sentencia",IF(W100="N.A.","N.A.",DAYS360(G100,W100)))) -> 15 | AA100: N/A | AB100: ORDENA SEGUIR ADELANTE CON LA EJECUCIÓN | AC100: 2024-4 | AD100: TERMINA PROCESO POR PAGO - CON OSAE | AE100: 45771 | AF100: LACIDES | AG100: 01 CIVIL MCPAL | AH100: ELECTRONICO | AJ100: X
A101: 94 | B101: 001-2024-00768 | C101: EJECUTIVO | D101: POR SUMAS DE DINERO | E101: MENOR | F101: REMITIDA POR OTRO DESPACHO | G101: 45568 | H101: SCOTIABANK COLPATRIA S.A. | I101: 1 | J101: 0 | K101: LUIS CARLOS CARDENAS ZAPATA | L101: 0 | M101: 1 | N101: 45568 | O101: =IF(G101="","",(IF(N101="","Pendiente primera actuación",IF(N101="N.A.","N.A.",IF(NETWORKDAYS((G101+1),N101,'Días No Laborales'!$A$2:$U$145)<=20,"SI","NO"))))) -> SI | Q101: NO | W101: 45618 | Y101: N/A | Z101: =IF(B101="","",IF(W101="","Pendiente de sentencia",IF(W101="N.A.","N.A.",DAYS360(G101,W101)))) -> 49 | AA101: N/A | AB101: ORDENA SEGUIR ADELANTE CON LA EJECUCIÓN | AC101: 2024-4 | AD101: MODIFICA LIQUIDACION | AE101: 45797 | AF101: CAROLINA | AG101: 01 CIVIL MCPAL | AH101: ELECTRONICO | AJ101: X
A102: 95 | B102: 001-2023-01140 | C102: SUCESION | D102: LIQUIDATORIO | E102: MENOR | F102: REMITIDA POR OTRO DESPACHO | G102: 45568 | H102: GIOVANNY - VELEZ BOLIVAR | I102: 0 | J102: 1 | K102: GUSTAVO HERNAN VELEZ GOMEZ | L102: 2 | M102: 1 | N102: 45568 | O102: =IF(G102="","",(IF(N102="","Pendiente primera actuación",IF(N102="N.A.","N.A.",IF(NETWORKDAYS((G102+1),N102,'Días No Laborales'!$A$2:$U$145)<=20,"SI","NO"))))) -> SI | Q102: NO | W102: 45638 | Y102: N/A | Z102: =IF(B102="","",IF(W102="","Pendiente de sentencia",IF(W102="N.A.","N.A.",DAYS360(G102,W102)))) -> 69 | AA102: N/A | AB102: RECHAZADOS O RETIRADOS | AC102: 2024-4 | AD102: AUTORIZA RETIRO | AE102: 45638 | AF102: CAMILA | AG102: 01 CIVIL MCPAL | AH102: ELECTRONICO
A103: 96 | B103: 001-2020-00747 | C103: PERTENENCIA | D103: VERBAL | E103: MENOR | F103: REMITIDA POR OTRO DESPACHO | G103: 45568 | H103: JOSE ALEJANDRO BOTERO VELASQUEZ | I103: 1 | J103: 0 | K103: CARLOS MARIO NOREÑA CORRALES | L103: 0 | M103: 1 | N103: 45568 | O103: =IF(G103="","",(IF(N103="","Pendiente primera actuación",IF(N103="N.A.","N.A.",IF(NETWORKDAYS((G103+1),N103,'Días No Laborales'!$A$2:$U$145)<=20,"SI","NO"))))) -> SI | Q103: NO | W103: 45720 | Y103: N/A | Z103: =IF(B103="","",IF(W103="","Pendiente de sentencia",IF(W103="N.A.","N.A.",DAYS360(G103,W103)))) -> 151 | AA103: N/A | AB103: DESISTIMIENTO TACITO | AC103: 2025-1 | AD103: DESISTIMIENTO TACITO | AE103: 45720 | AF103: LACIDES | AG103: 01 CIVIL MCPAL | AH103: ELECTRONICO | AI103: 45734
...

Sheet Tutelas
C1: SEGUIMIENTO A TÉRMINOS PROCESALES - TUTELAS
C2: PROCESO MEJORAMIENTO DE LA GESTIÓN
A4: Juzgado | C4: Juzgado 004 Civil Municipal de Envigado
A6: N° | B6: N° RADICADO | C6: ACCIONANTE | D6: ACCIONADO | E6: FECHA DE INGRESO dd-mm-aaaa | F6: OTRAS ENTRADAS | G6: ASIGNADO | H6: ALERTA | I6: NO. DIAS | J6: DIA SIETE | K6: DIA DIEZ | L6: PERSPECTIVA DE GÉNERO (SI/NO) | M6: CON MEDIDA PROVISIONAL | N6: LUGAR DE ORIGEN | P6: INSTANCIA | Q6: CUADERNOS | R6: FOLIOS | S6: FECHA DE LA SENTENCIA dd-mm-aaaa | T6: ¿DICTÓ SENTENCIA DENTRO DEL TÉRMINO? (si/no) | U6: OBSERVACIONES (EN CASO DE NO CUMPLIR LOS TÉRMINOS) | V6: No. DE DÍAS | W6: Fecha de archivo o de salida sin decisión definitiva | X6: DERECHO FUNDAMENTAL INVOCADO | Y6: DERECHO FUNDAMENTAL TUTELADO | Z6: DECISIÓN | AA6: ¿SE IMPUGNÓ? | AB6: FECHA LIMITE IMPUGNACION | AC6: FECHA REMISIÓN CORTE/CIRCUITO | AD6: DECISIÓN SEGUNDA INSTANCIA | AE6: FECHA REGRESO | AF6: ARCHIVO DEFINITIVO | AG6: OBSERVACIONES
A7: 1 | B7: 2024-00001 | C7: RENATA SOTO PEREZ | D7: FLOSILDA SAS | E7: 45564 | F7: REPARTO | G7: DANIELA | H7: =IF(E7="","",IF(S7<>"","",IF(NETWORKDAYS(E7+1,TODAY(),'Días No Laborales'!$E$1:$U$146)>=7,"ALERTA",""))) | I7: 6 | J7: =WORKDAY(E7,7,'Días No Laborales'!$A$1:$U$141) -> 45573 | K7: =IF(E7="","",WORKDAY(E7,10,'Días No Laborales'!$B$1:$U$142)) -> 45576 | L7: NO | M7: NO | N7: CENTRO DE SERVICIOS ADMINISTRATIVOS | S7: 45566 | T7: =IF(S7="","",IF(E7="RECHAZA ","RECHAZA ",IF(E7="","",(IF(E7="Pendiente sentencia","Pendiente sentencia",IF(E7=" "," ",IF(NETWORKDAYS((E7+1),S7,'Días No Laborales'!$A$2:$U$160)<=10,"SI","NO"))))))) -> SI | U7: =IF(T7="","",IF(T7="NO","OBSERVACIÓN","N.A")) -> N.A | V7: =IF(S7="","",IF(E7="","",NETWORKDAYS(E7+1,S7,'Días No Laborales'!$A$1:$U$141))) -> 2 | X7: SALUD | Y7: N/A | Z7: IMPROCEDENTE | AA7: NO | AB7: 45573 | AC7: 45610
A8: 2 | B8: 2024-00007 | C8: OMAIRA MARIA CAIDEO GARCIA | D8: SECRETARIA EDUCACION/MUNICIPIO ENVIGADO | E8: 45560 | F8: REPARTO | G8: CAMILA | H8: =IF(E8="","",IF(S8<>"","",IF(NETWORKDAYS(E8+1,TODAY(),'Días No Laborales'!$E$1:$U$146)>=7,"ALERTA",""))) | I8: 6 | J8: =WORKDAY(E8,7,'Días No Laborales'!$A$1:$U$141) -> 45569 | K8: =IF(E8="","",WORKDAY(E8,10,'Días No Laborales'!$B$1:$U$142)) -> 45574 | L8: NO | M8: NO | N8: CENTRO DE SERVICIOS ADMINISTRATIVOS | S8: 45569 | T8: =IF(S8="","",IF(E8="RECHAZA ","RECHAZA ",IF(E8="","",(IF(E8="Pendiente sentencia","Pendiente sentencia",IF(E8=" "," ",IF(NETWORKDAYS((E8+1),S8,'Días No Laborales'!$A$2:$U$160)<=10,"SI","NO"))))))) -> SI | U8: =IF(T8="","",IF(T8="NO","OBSERVACIÓN","N.A")) -> N.A | V8: =IF(S8="","",IF(E8="","",NETWORKDAYS(E8+1,S8,'Días No Laborales'!$A$1:$U$141))) -> 7 | X8: PETICION | Y8: PETICION | Z8: CONCEDE | AA8: SI | AB8: 45576 | AC8: 45582 | AD8: CONFIRMA | AE8: 45587
A9: 3 | B9: 2024-00010 | C9: LINA PATRICIA PEREZ MARTINEZ | D9: EPS SURAMERICANA S.A.S | E9: 45562 | F9: REPARTO | G9: LACIDES | H9: =IF(E9="","",IF(S9<>"","",IF(NETWORKDAYS(E9+1,TODAY(),'Días No Laborales'!$E$1:$U$146)>=7,"ALERTA",""))) | J9: =WORKDAY(E9,7,'Días No Laborales'!$A$1:$U$141) -> 45573 | K9: =IF(E9="","",WORKDAY(E9,10,'Días No Laborales'!$B$1:$U$142)) -> 45576 | L9: NO | M9: NO | N9: CENTRO DE SERVICIOS ADMINISTRATIVOS | S9: 45562 | T9: =IF(S9="","",IF(E9="RECHAZA ","RECHAZA ",IF(E9="","",(IF(E9="Pendiente sentencia","Pendiente sentencia",IF(E9=" "," ",IF(NETWORKDAYS((E9+1),S9,'Días No Laborales'!$A$2:$U$160)<=10,"SI","NO"))))))) -> SI | U9: =IF(T9="","",IF(T9="NO","OBSERVACIÓN","N.A")) -> N.A | V9: =IF(S9="","",IF(E9="","",NETWORKDAYS(E9+1,S9,'Días No Laborales'!$A$1:$U$141))) -> -1 | W9: PROPONE CONFLICTO | X9: SEGURIDAD SOCIAL | Y9: N/A | Z9: PROPONE CONFLICTO | AA9: NO | AB9: N/A | AE9: 45616 | AG9: TRIBUNAL ASIGNO COMPTENCIA A ESTE DESPACHO

Sheet Tutelas - Corte
D1: CONTROL ENVIO TUTELAS A CORTE
D2: RADICADO | F2: FECHA ENVIO | G2: OK
D3: 2024-00001 | F3: 45610
D4: 2024-00013 | F4: 45610
D5: 2024-00015 | F5: 45610
D6: 2024-00019 | F6: 45610
D7: 2024-00021 | F7: 45610
D8: 2024-00023 | F8: 45610
D9: 2024-00027 | F9: 45610
D10: 2024-00033 | F10: 45610
D11: 2024-00039 | F11: 45610
D12: 2024-00042 | F12: 45610
D13: 2024-00047 | F13: 45610
D14: 2024-00048 | F14: 45610
G15: OK
D16: 2024-00056 | F16: 45631
D17: 2024-00058 | F17: 45625
D18: 2024-00060 | F18: 45625
D19: 2024-00066 | F19: 45625
D20: 2024-00069 | F20: 45625
D21: 2024-00071 | F21: 45625
D22: 2024-00078 | F22: 45625
D23: 2024-00081 | F23: 45625
D24: 2024-00084 | F24: 45625
D25: 2024-00085 | F25: 45625
D26: 2024-00095 | F26: 45625
D27: 2024-00101 | F27: 45625
D28: 2024-00103 | F28: 45625
G29: OK
D30: 2024-00107 | F30: 45645
D31: 2024-00118 | F31: 45645
D32: 2024-00124 | F32: 45645
D33: 2024-00128 | F33: 45645
D34: 2024-00131 | F34: 45645
D35: 2024-00137 | F35: 45645
D36: 2024-00149 | F36: 45645
D37: 2024-00157 | F37: 45304
D38: 2024-00162 | F38: 45645
D39: 2024-00167 | F39: 45645
D40: 2024-00169 | F40: 45645
D41: 2024-00171 | F41: 45645
... D51: 2024-00197 | F51: 45645
G52: OK
D53: 2024-00208 | F53: 45692
D54: 2024-00214 | F54: 45692
D55: 2024-00219 | F55: 45692
D56: 2024-00224 | F56: 45692
D57: 2024-00225 | F57: 45692
D58: 2024-00228 | F58: 45692
D59: 2024-00229 | F59: 45692
D60: 2024-00246 | F60: 45692
D61: 2024-00259 | F61: 45692
G62: OK
D63: 2024-00255 | F63: 45702
D64: 2024-00264 | F64: 45702
D65: 2024-00275 | F65: 45702
D66: 2025-00007 | F66: 45702
D67: 2025-00011 | F67: 45702
D68: 2025-00016 | F68: 45702
D69: 2025-00020 | F69: 45702
D70: 2025-00025 | F70: 45702
D71: 2025-00026 | F71: 45702
D72: 2025-00027 | F72: 45702
D73: 2025-00029 | F73: 45702
D74: 2025-00030 | F74: 45702
... D77: 2025-000048 | F77: 45702
G78: OK
D79: 2025-00049 | F79: 45716
D80: 2025-00059 | F80: 45716
D81: 2025-00045 | F81: 45716
D82: 2025-00063 | F82: 45716
D83: 2025-00047 | F83: 45716
D84: 2025-00055 | F84: 45716
D85: 2025-00064 | F85: 45716
D86: 2025-00068 | F86: 45716
D87: 2025-00058 | F87: 45716
D88: 2025-00080 | F88: 45716
D89: 2025-00082 | F89: 45716
D90: 2025-00090 | F90: 45716
... D95: 2025-00108 | F95: 45716
G96: PASA A JHOHHAN EL 17/3/2025
D97: 2025-00117 | F97: 45737
D98: 2025-00076 | F98: 45737
D99: 2025-00097 | F99: 45737
D100: 2025-00103 | F100: 45737
D101: 2025-00109 | F101: 45737
D102: 2025-00123 | F102: 45737
D103: 2025-000129 | F103: 45737
D104: 2025-00137 | F104: 45737
D105: 2025-00138 | F105: 45737
D106: 2025-00140 | F106: 45737
D107: 2025-00142 | F107: 45737
D108: 2025-00149 | F108: 45737
... D112: 2025-00162 | F112: 45737
G113: PASA A 8/4/2025
D114: 2025-00156 | E114: 45735 | F114: 45782
D115: 2025-00160 | E115: 45730
D116: 2025-00166 | E116: 45733 | F116: 45755
D117: 2025-00167 | E117: 45735 | F117: 45782
D118: 2025-00170 | E118: 45736 | F118: 45755
...

Sheet Incidentes de Desacato
A1: JUZGADO CUARTO CIVIL MUNICIPAL DE ENVIGADO
A2: INCIDENTES DE DESACATO - TUTELAS
A3: RADICADO | B3: FECHA INGRESO | C3: REINGRESO NULIDAD | D3: DEMANDANTE | E3: DEMANDADO | F3: CUADERNOS | G3: DERECHO | H3: REQUERIMIENTO | I3: APERTURA | J3: P SANCION (DIA 7) | K3: ÚLTIMA ACTUACIÓN | L3: FECHA ÚLTIMA ACTUACIÓN | M3: REMITIDO A CONSULTA | N3: FECHA TERMINACION | O3: FECHA REGRESO | P3: DECISIÓN CONSULTA | Q3: UBICACIÓN EXPEDIENTE | R3: FECHA ARCHIVO DEFINITIVO | S3: CAJA | T3: INAP. SANCIÓN | U3: FECHA INAP. SANCIÓN | V3: OBSERVACIONES
A4: 2024-00023 | B4: 45587 | D4: MELISSA LAVERDE GOMEZ | E4: EMPRESAS PUBLICAS DE MEDELLIN Y OTROS | G4: PETICION | H4: 0 | I4: 0 | J4: 0 | K4: RECHAZO | L4: 45587 | N4: 45587 | Q4: ELECTRONICO | R4: 45587 | W4: LAURA
A5: 2024-00007 | B5: 45603 | D5: OMAIRA MARIA CAIDEO GARCIA | E5: SECRETARIA EDUCACION/MUNICIPIO ENVIGADO | G5: PETICION | H5: 45604 | I5: 45614 | J5: 0 | K5: SANCIONA | L5: 45624 | N5: 45624 | O5: 45628 | P5: NULIDAD | Q5: ELECTRONICO | V5: Enviado Consulta 29/11/2024 | W5: CAMILA
A6: 2024-00162 | B6: 45625 | D6: YUSMARY COROMOTO FIGUEREDO | E6: SECRETARIA SECCIONAL SALUD | G6: SALUD | H6: 0 | I6: 0 | J6: 0 | K6: RECHAZO | L6: 45628 | N6: 45628 | Q6: ELECTRONICO | R6: 45628 | W6: JHOHHAN
A7: 2024-00007 | B7: 45628 | C7: REINGRESO NULIDAD | D7: OMAIRA MARIA CAIDEO GARCIA | E7: SECRETARIA EDUCACION/MUNICIPIO ENVIGADO | G7: PETICION | H7: 45629 | I7: 0 | J7: 0 | K7: ABSTIENE APERTURAR | L7: 45638 | N7: 45638 | Q7: ELECTRONICO | R7: 45638 | V7: Reingreso | W7: CAMILA
A8: 2024-00171 | B8: 45635 | D8: JOSE MARIO USME RAMRIEZ | E8: SAVIA SALUD EPS | G8: SALUD | H8: 45636 | I8: 45639 | K8: SANCIONA | L8: 45673 | O8: 45311 | P8: CONFIRMA | Q8: ELECTRONICO | V8: ENVIADO A CONSULTA 16/01/2024 | W8: LACIDES | X8: Solo se comienza estadistica Primer t 2025
A9: 2 0 2 5 2 0 2 5 2 0 2 5
A10: 2025-00025 | B10: 45684 | C10: REINGRESO NULIDAD | D10: WILSON WBEIMAR ALVAREZ MENDEZ | E10: MARIA WENCESLAA TORRES | G10: SALUD | K10: ABSTIENE APERTURAR | L10: 45715 | N10: 45349 | W10: CAMILA
A11: 2025-00049 | B11: 45704 | C11: N/A | D11: ENRIQUE ACUÑA ALZATE | E11: SECRETARIA BELLO | G11: PETICION | H11: 45701 | I11: 45708 | J11: 1 | K11: REQUIERE PREVIO A APERTURAR | L11: 45719 | N11: 45719 | W11: CAMILA
A12: 2025-00093 | B12: 45715 | C12: N/A | D12: NEVARDO DE JESUS GALLEGO | E12: VIAJES EXITO | F12: VIAJES EXITO | G12: PETICION | H12: 45716 | I12: 45721 | J12: 45728 | K12: CIERRA INCIDENTE | L12: 45728 | N12: 45728 | W12: LACIDES
A13: 2025-00108 | B13: 45712 | C13: N/A | D13: CESAR AUGUSTO FERDINAND ACEVEDO | E13: BANCO CAJA SOCIAL | G13: PETICION | H13: 45715 | I13: 45720 | J13: 45728 | K13: CIERRA INCIDENTE | L13: 45728 | N13: 45728 | W13: LINA
A14: 2025-000112 | B14: 45722 | C14: N/A | D14: DIANA PATRICIA RODRÍGUEZ MOJICA | E14: EPS SURA - COLFONDOS | G14: SEGURIDAD SOCIAL | H14: 45723 | I14: 45730 | J14: 45750 | K14: CIERRA INCIDENTE | L14: 45750 | N14: 45750 | W14: JHOHHAN
A15: 2025-00137 | B15: 45723 | C15: N/A | D15: THE KINDER DOG S.A.S. | E15: SANITAS EPS | G15: PETICION | H15: 45726 | I15: 45730 | J15: 45737 | K15: SANCIONA | L15: 45737 | M15: 45741 | N15: 45741 | O15: 45742 | P15: CONFIRMA | Q15: ACCIONES CONSTITUCIONALES | R15: 45755 | T15: SI | U15: 45750 | V15: INAPLICA SANCION - 28/3/2025 | W15: LACIDES
A16: 2025-00175 | B16: 45727 | C16: N/A | D16: JORGE TORRES RAMIREZ | E16: ALEXANDER GOMEZ HERNANDEZ | G16: PETICION | K16: RECHAZO | L16: 45730 | N16: 45730 | W16: CAMILA
A17: 2025-00138 | B17: 45733 | C17: N/A | D17: SELSO ANTONIO CONTRERAS VIDES | E17: EPS SURAMERICANA S.A. | G17: PETICION | H17: 45733 | I17: 45733 | J17: 45736 | K17: CIERRA INCIDENTE | L17: 45736 | W17: LINA
A18: 2025-00150 | B18: 45729 | C18: N/A | D18: HOSPITAL MANUEL URIBE ÁNGEL | E18: EMPRESA SOCIAL DEL ESTADO HOSPITAL LA MARÍA | G18: PETICION | H18: 45733 | I18: 45736 | J18: 45747 | K18: SANCIONA | L18: 45747 | W18: LACIDES
A19: 2025-00097 | B19: 45734 | C19: N/A | D19: FLANKLIN RAFAEL BARIOS CELEDÓN | E19: IMPERMEABILIZADOS Y REVESTIMIENTOS CONSOLIDADOS SAS - SIC SOLUCIONES INTELIGENTES PARA LA CONSTRUCCION S.A.S. | G19: PETICION | H19: 45735 | I19: 45750 | J19: 45757 | K19: SANCIONA | L19: 45757 | N19: 45757 | O19: 45812 | P19: REVOCA | Q19: ACCIONES CONSTITUCIONALES | R19: 45771 | S19: N/A | T19: N/A | U19: N/A | V19: SANCIONA Y CONFIRMA SANCION EL SUPERIOR | W19: LINA
A20: 2025-00180 | B20: 45741 | C20: N/A | D20: NUBIA ESPERANZA MAHECHA SALAMANCA | E20: NOVEDADES PLASTICAS | G20: PETICION | H20: 45742 | I20: 45748 | J20: 45776 | K20: SANCIONA | L20: 45776 | N20: 45776 | O20: 45785 | P20: CONFIRMA | Q20: ACCIONES CONSTITUCIONALES | R20: 45785 | S20: N/A | T20: N/A | U20: N/A | V20: AUTO SANCIONA | W20: LINA
A21: 2025-00212 | B21: 45751 | C21: N/A | D21: LEIDYS ADRIANA ESPAÑA BURGOS | E21: Clínica de las Américas y Departamento de Gestión del SOAT. LA PREVISORA SA | G21: SALUD | H21: 45756 | I21: 45768 | J21: 45772 | K21: ABSTIENE DE SANCIONAR | L21: 45772 | N21: 45772 | O21: N/A | P21: N/A | Q21: ACCIONES CONSTITUCIONALES | R21: 45772 | S21: N/A | T21: N/A | U21: N/A | V21: SE ABSTIENE DE SANCIONAR | W21: LACIDES
A22: 2025-00176 | B22: 45758 | C22: N/A | D22: OCTAVIO DE JESUS CASTRILLON | E22: EPS SURAMERICANA S.A. | G22: SALUD | H22: 45772 | I22: 45784 | J22: 45791 | K22: ABSTIENE DE SANCIONAR | L22: 45791 | N22: 45791 | O22: N/A | P22: N/A | Q22: ACCIONES CONSTITUCIONALES | R22: 45797 | S22: N/A | T22: N/A | U22: N/A | V22: SE ABSTIENE DE SANCIONAR | W22: JHOHHAN
A23: 2025-00199 | B23: 45751 | C23: N/A | D23: FRANCISCO JAVIER PINZÓN SOTELO | E23: SECRETARIA DE TRÁNSITO Y MOVILIDAD DE POPAYAN | G23: PETICION | H23: 45755 | I23: 45772 | J23: 45784 | K23: ABSTIENE DE SANCIONAR | V23: SE ABSTIENE DE SANCIONAR | W23: JHOHHAN
A24: 2025-00112 | B24: 45769 | C24: N/A | D24: DIANA PATRICIA RODRÍGUEZ MOJICA | E24: COLFONDOS Y EPS SURA | G24: SALUD | H24: 45772 | I24: 45785 | J24: 45791 | K24: ABSTIENE DE SANCIONAR | L24: 45791 | M24: NO | N24: 45791 | O24: N/A | P24: N | Q24: ACCIONES CONSTITUCIONALES | R24: 45797 | S24: N/A | T24: N/A | U24: N/A | V24: SE ABSTIENE DE SANCIONAR | W24: JHOHHAN
A25: 2025-00150 | B25: 45772 | C25: N/A | D25: HOSPITAL MANUEL URIBE ÁNGEL | E25: EMPRESA SOCIAL DEL ESTADO HOSPITAL LA MARÍA | G25: PETICION | H25: 45775 | I25: tiene hasta el 30/04/2025 | K25: CIERRA INCIDENTE | L25: 45783 | N25: 45783 | O25: N/A | P25: N/A | Q25: ACCIONES CONSTITUCIONALES | R25: 45783 | S25: N/A | T25: N/A | U25: N/A | V25: CIERRA INCIDENTE | W25: LACIDES
A26: 2025-00303 | B26: 45792 | C26: N/A | D26: AURELIO ANCIZAR ARANGO MONTOYA | E26: A.F.P. PORVENIR S.A. SEGUROS DE VIDA ALFA S.A. E.P.S. SURAMERICANA S.A. | G26: SEGURIDAD SOCIAL | H26: 45793 | I26: 45799 | J26: 45806 | K26: SANCIONA | L26: 45806 | M26: 45807 | N26: 45812 | O26: 45812 | P26: REVOCA | Q26: ACCIONES CONSTITUCIONALES | V26: REVOCA SANCION | W26: LACIDES
A27: 2025-00176 | B27: 45803 | C27: N/A | D27: OCTAVIO DE JESUS CASTRILLON | E27: EPS SURAMERICANA S.A. | G27: SALUD | K27: ACEPTA DESISTIMIENTO INCIDENTE | L27: 45811 | M27: N/A | N27: 45812 | O27: N/A | P27: N/A | Q27: ACCIONES CONSTITUCIONALES | S27: N/A | T27: N/A | U27: N/A | V27: CIERRA INCIDENTE | W27: JHOHHAN
A28: 2025-00323 | B28: 45817 | C28: N/A | D28: IDEAR SOLUCIONES FINANCIERAS | E28: SERVIEXPRESS LIBA SAS | G28: PETICION | H28: 45818 | I28: 45825 | J28: 45835 | K28: SANCIONA | L28: 45835 | M28: 45839 | O28: 45842 | P28: CONFIRMA | Q28: ACCIONES CONSTITUCIONALES | S28: N/A | T28: N/A | U28: N/A | V28: CONFIRMA AUTO IMPONE SANCION - JUZGADO 001 CIVIL CIRCUITO ENVIGADO | W28: LINA
A29: 2025-00396 | B29: 45821 | C29: N/A | D29: JORGE ALBERTO ROBLEDO GIRALDO | E29: EPS SURAMERICANA S.A. | G29: SALUD | H29: 45821 | I29: 45826 | J29: 45839 | K29: SANCIONA | L29: 45839 | M29: 45839 | V29: ASIGNADA A JUZGDAO 003 CIVIL CIRCUITO | W29: LINA
A30: 2025-00321 | B30: 45821 | C30: N/A | D30: JUAN SEBASTIAN CASTAÑEDA agente oficioso de la señora JULIANA MARULANDA RESTREPO | E30: EPS SURAMERICANA S.A. | G30: SALUD | H30: 45821 | I30: 45826 | J30: 45832 | K30: SANCIONA | L30: 45832 | M30: 45834 | N30: 45839 | O30: N/A | P30: N/A | Q30: ACCIONES CONSTITUCIONALES | R30: 45842 | S30: N/A | T30: N/A | U30: N/A | V30: CONFIRMA AUTO IMPONE SANCION - JUZGADO 002 CIVIL CIRCUITO ENVIGADO | W30: CAROLINA
A31: 2025-00418 | B31: 45821 | C31: N/A | D31: ANGELA ALICIA ZAPATA SANCHEZ | E31: SUMIMEDICAL EPS | G31: SALUD | H31: 45821 | I31: 45826 | J31: 45839 | K31: ABSTIENE DE SANCIONAR | L31: 45840 | M31: N/A | N31: 45840 | O31: N/A | P31: N/A | Q31: ACCIONES CONSTITUCIONALES | R31: 45840 | S31: N/A | T31: N/A | U31: N/A | V31: SE ABSTIENE DE SANCIONAR | W31: LINA
A32: 2025-00401 | B32: 45828 | C32: N/A | D32: JOSE ALONSO LOTERO SANDOVAL actuando como agente oficioso de JIMENA AYLIN LOTERO SUAREZ | E32: EPS SURAMERICANA S.A. | G32: SALUD | H32: 45832 | I32: 45840 | J32: 45847 | K32: ABSTIENE DE SANCIONAR | L32: 45847 | M32: N/A | N32: 45847 | O32: N/A | P32: N/A | Q32: ACCIONES CONSTITUCIONALES | R32: 45853 | S32: N/A | T32: N/A | U32: N/A | V32: SE ABSTIENE DE SANCIONAR | W32: LACIDES
A33: 2025-00414 | B33: 45839 | C33: N/A | D33: ANDRES FELIPE GONZALEZ ARIAS | E33: TELEPERFORMANCE COLOMBIA EPS SURAMERICANA S.A. PROTECCIÓN S.A. | G33: SALUD | H33: 45841 | I33: PRESCINDE DE PRUEBA - 21/7/2025 | J33: 45869 | K33: SANCIONA | L33: 45869 | M33: 45873 | N33: 45877 | O33: N/A | P33: N/A | Q33: ACCIONES CONSTITUCIONALES | R33: 45883 | S33: N/A | T33: N/A | U33: N/A | V33: REVOCA SANCION - CUMPLIO EN SEDE DE CONSULTA | W33: JHOHHAN
A34: 2025-00321 | B34: 45839 | C34: N/A | D34: JUAN SEBASTIAN CASTAÑEDA agente oficioso de la señora JULIANA MARULANDA RESTREPO | E34: EPS SURAMERICANA S.A. | G34: SALUD | H34: 45842 | J34: 45847 | K34: ABSTIENE DE SANCIONAR | L34: 45847 | M34: N/A | N34: 45847 | O34: N/A | P34: N/A | Q34: ACCIONES CONSTITUCIONALES | R34: 45847 | S34: N/A | T34: N/A | U34: N/A | V34: SE ABSTIENE DE SANCIONAR | W34: CAROLINA
A35: 2025-00475 | B35: 45845 | C35: N/A | D35: NOVEDADES PLÁSTICAS S.A.S. | E35: BANCO DAVIVIENDA VINCULADO: FISCALIA 10 LOCAL DE MEDELLIN | G35: PETICION | H35: 45853 | I35: 45859 | J35: 45869 | K35: SANCIONA | L35: 45869 | M35: 45873 | N35: 45874 | O35: N/A | P35: N/A | Q35: ACCIONES CONSTITUCIONALES | R35: 45880 | S35: N/A | T35: N/A | U35: N/A | V35: REVOCA SANCION - CUMPLIO EN SEDE DE CONSULTA | W35: JHOHHAN
A36: 2025-00524 | B36: 45852 | C36: N/A | D36: Gessica Paola Ruiz Gómez | E36: IQOR Colombia S.A.S. | G36: DEBIDO PROCESO | H36: 45853 | J36: 45854 | K36: RECHAZO | L36: 45854 | M36: N/A | Q36: ACCIONES CONSTITUCIONALES | V36: RECHAZA POR NO ESTR EJECUTORIADO | W36: LACIDES
A37: 2025-00524 | B37: 45856 | C37: N/A | D37: Gessica Paola Ruiz Gómez | E37: IQOR Colombia S.A.S. | G37: DEBIDO PROCESO | H37: 45859 | I37: 45866 | J37: 45877 | K37: SANCIONA | L37: 45877 | M37: 45880 | Q37: ACCIONES CONSTITUCIONALES | V37: NO ACCEDE A INAPLICACION SE SANCION - 20/8/2025 - NO HAN CUMPLIDO COMPLET | W37: LACIDES
A38: 2025-00395 | B38: 45859 | C38: N/A | D38: IDEAR NEGOCIOS S.A.S – PRESENTE Financiero | E38: HAASS EXPRESS S.A. | G38: PETICION | H38: 45873 | J38: 45877 | K38: ABSTIENE DE SANCIONAR | L38: 45877 | M38: N/A | Q38: ACCIONES CONSTITUCIONALES | W38: CAROLINA
A39: 2025-00496 | B39: 45860 | C39: N/A | D39: IDEAR NEGOCIOS S.A.S – PRESENTE Financiero | E39: DIEGO FERNANDO RIOS SALAZAR | G39: PETICION | H39: 45862 | I39: 45870 | J39: 45877 | K39: ABSTIENE DE SANCIONAR | L39: 45877 | M39: N/A | N39: 45877 | O39: N/A | P39: N/A | Q39: ACCIONES CONSTITUCIONALES | R39: 45883 | S39: N/A | T39: N/A | U39: N/A | V39: SE ABSTIENE DE SANCIONAR | W39: CAMILA
A40: 2025-00510 | B40: 45860 | C40: N/A | D40: IDEAR NEGOCIOS S.A.S – PRESENTE Financiero | E40: DISTRIBUCIONES YEIMI S.A.S | G40: PETICION | H40: 45861 | I40: 45870 | J40: 45882 | K40: SANCIONA | L40: 45883 | Q40: ACCIONES CONSTITUCIONALES | W40: LACIDES
A41: 2025-00492 | B41: 45862 | C41: N/A | D41: DIANA PATRICIA RODRIGUEZ MOJICA | E41: KALONI COLOMBIA S.A.S. | G41: PETICION | H41: 45863 | I41: 45869 | J41: 45875 | K41: ABSTIENE DE SANCIONAR | L41: 45877 | M41: N/A | N41: 45877 | O41: N/A | P41: N/A | Q41: ACCIONES CONSTITUCIONALES | R41: 12/8/205 | S41: N/A | T41: N/A | U41: N/A | V41: SE ABSTIENE DE SANCIONAR | W41: LINA
A42: 2025-00189 | B42: 45863 | C42: N/A | D42: PAMELA BERMUDEZ DURAN | E42: EPS SURAMERICANA S.A.S | G42: SALUD | H42: 45863 | I42: 45869 | J42: 45877 | K42: SANCIONA | L42: 45877 | M42: 45880 | O42: 45883 | P42: NULIDAD | Q42: ACCIONES CONSTITUCIONALES | S42: N/A | T42: N/A | U42: N/A | V42: REVOCA JUZGADO 1 CIVCIL CIRCUITO: DECLARA NULIDAD Y ORDENA REHACER | W42: CAROLINA
A43: 2025-00549 | B43: 45856 | C43: N/A | D43: GIOVANNY HERNAN CARDONA RINCON Agente Oficioso de LEON HERNAN CARDONA CARDONA | E43: CLINICA VIDA S.A.S. EPS SURAMERICANA S.A. | G43: SALUD | H43: 45859 | I43: 45873 | J43: 45888 | K43: ABSTIENE DE SANCIONAR | L43: 45888 | M43: N/A | N43: 45888 | O43: N/A | P43: N/A | Q43: ACCIONES CONSTITUCIONALES | R43: 45894 | S43: N/A | T43: N/A | U43: N/A | V43: SE ABSTIENE DE SANCIONAR | W43: CAMILA
A44: 2025-00517 | B44: 45873 | C44: N/A | D44: IDEAR NEGOCIOS S.A.S – PRESENTE Financiero | E44: VVC ASOCIADOS S.A.S. | G44: PETICION | H44: 45874 | I44: 45880 | J44: 45889 | K44: ABSTIENE DE SANCIONAR | L44: 45889 | M44: N/A | N44: 45889 | O44: N/A | P44: N/A | Q44: ACCIONES CONSTITUCIONALES | R44: 45894 | S44: N/A | T44: N/A | U44: N/A | V44: SE ABSTIENE DE SANCIONAR | W44: CAROLINA
A45: 2025-00575 | B45: 45875 | C45: N/A | D45: IDEAR NEGOCIOS S.A.S – PRESENTE Financiero | E45: MERCAVICOLA PEZPOLLO S.A. | G45: PETICION | H45: 45875 | I45: 45889 | J45: 45889 | K45: ABSTIENE DE SANCIONAR | L45: 45889 | M45: N/A | N45: 45890 | O45: N/A | P45: N/A | Q45: ACCIONES CONSTITUCIONALES | R45: 45894 | S45: N/A | T45: N/A | U45: N/A | V45: SE ABSTIENE DE SANCIONAR | W45: LINA
A46: 2025-00597 | B46: 45881 | C46: N/A | D46: ALVARO GUILLERMO LONDOÑO RAMIREZ | E46: EPS SURAMERICANA S.A. | G46: SALUD | H46: 45882 | J46: VENCE: 28 AGOSTO DE 2025 | W46: LACIDES
A47: 2025-00530 | B47: 45881 | C47: N/A | D47: SANDRA MILENA RUDAS DE LA HOZ_x000D_ | E47: ELECTROSERVICIOS DEL VALLE S.A.S. GLADYS MARIN GALLO | G47: MINIMO VITAL | H47: 45882 | I47: 45888 | J47: VENCE: 28 AGOSTO DE 2025 | W47: CAROLINA
A48: 2025-00439 | B48: 14/78/2025 | C48: N/A | D48: JHON JAIRO SERNA CANO | E48: MEFIA | G48: HABEAS DATA | H48: 45889 | J48: VENCE: 04 DE SEPTIEMBRE 2025 | W48: LINA
A49: 2025-00189 | B49: 45863 | C49: N/A | D49: PAMELA BERMUDEZ DURAN | E49: EPS SURAMERICANA S.A.S | G49: SALUD | H49: 45888 | I49: 45891
A50: 2025-00029 | B50: 45891 | C50: N/A | D50: ALBA LUZ LOPERA VELASQUEZ | E50: EPS SAVIA SALUD S.A.
T110: X | U110: 44025
V280: Cierra incidente por imposibilidad de cumplimiento
V282: Se inaplicó la sanción el 07/06/2019.
V283: Se inaplicó la sanción el 04/07/2019.
V284: Inaplica sanción el 10/02/2020.
V286: Se inaplicó la sanción el 17/03/2019.
V287: Inaplica sanción el 21/10/2019. Resuelve solicitud el 28/10/2019.
V288: El Superior decretò nulidad el 28/05/2019.
V292: El Superior decretó nulidad el 30/05/2019.
V294: Inaplica sanción el 13/02/2020.
V295: Desvicnula funcionario 27/05/2019.
V296: Niega solictud 05/08/2019.
T299: X | U299: 44127
T300: X | U300: 44428 | V300: Inaplica sanción por imposibilidad de cumplimiento.
V302: Se inaplicó la sanción por cumplimiento el 21/06/2019.
T306: X | U306: 44132
V308: No accede a solicitud de suspensión 29/08/2019.
V309: Inaplica sanción el 18/10/2019.
V311: Se inaplicò de sancion por cumplimiento el 27/07/2019.
V315: Inaplica sanción por cumplimiento 20/08/2019.
V317: Niega solicitud de inaplicacion de sancion el 08/07/2019.
V318: Cúmplase lo resuelto por el Superior 22/07/2019.
V319: Se decretó nulidad. Se inaplicó la sanción por cumplimiento el 11/07/2019.
V320: Se decretó nulidad. Cúmplase lo resuelto por el Superior el 08/08/2019. Inaplica sanción el 17/09/2019.
V321: Niega solicitud de inaplicacion el 10/07/2019.
T323: X | U323: 43990 | V323: Niega solicitud de desvinculacion 26/06/2019 y 08/07/2019. Inaplica sanción el 08/06/2020.
V324: Cúmplase lo resuelo por el Superior y requiere previo apertura de desacato 26/07/2019.
T325: X | U325: 44025 | V325: Cumplase lo resuelo por el Superior 26/07/2019.
V326: Cúmplase lo resuelto por el Superior el 14/08/2019.
V327: Se inaplicó la sanción por imposiblidad de cumplimiento el 11/07/2019.
V330: Niega solicitud de suspension de sancion 24/07/2019. Inaplica sanción el 22/11/2019.
V331: Cúmplase lo resuelto por el superior 05/08/2019. Inaplica sanción el 18/10/2019.
V334: Cúmplase lo resuelo por el superior 22/07/2019. Incaplica sanción el 20/09/2019.
V335: Cúmplase lo resuelto por el superior 06/08/2019.
V336: Inaplica todas las sanciones anteriores el 11/03/2020.
T337: X | U337: 44231 | V337: Cúmplase lo resuelto por el superior 06/08/2019. Inaplica sanción 28/08/2019.
V338: Cúmplase lo resuelto por el Superior 14/08/2019.
V339: Cúmplase lo resuelto por el Superior 20/08/2019. Inaplica sanción 29/08/2019.
V340: Cúmplase lo resuelto por el Superior 20/08/2019. Inaplica sanción 28/08/2019.
V341: Cúmplase lo resuelto por el Superior el 19/09/2019.
V342: Cúmplase lo resuelto por el Superior el 06/08/2019. Se inaplica sanción el 10/09/2019.
V343: Cúmplase lo resuelto por el Superior 23/08/2019.
V346: Se volvió a tramitar el incidente (3) luego de que se decretara la nulidad. Cúmplase lo resuelto por el superior 08/08/2019.
V347: Cúmplase lo resuelto por el Superior 29/08/2019. Inaplica sanción el 09/03/2020.
V350: Cúmplase lo resuelto por el Superior 02/09/2019
V351: Cúmplase lo resuelto por el Superior 20/08/2019.
V352: Niega solicitud de inaplicacion de sanción 01/08/2019. Cúmplase lo resuelto por el Superior el 11/09/2019.
V353: Cúmplase lo resuelto por el Superior 11/09/2019.
... V360: Requiere en trámite de cumplimiento 09/09/2019. Ordena compulsar copias a la Fiscalía el 18/09/2019.
T362: X | U362: 44428 | V362: Inaplica sanción por imposibilidad de cumplimiento.
...

Sheet Inaplicación Inc.
A2: Radicado | B2: Fecha Ingreso | C2: Fecha Resulve Solicitud | D2: Resuelve
A3: 2024-00171 | B3: 45693 | C3: 45695 | D3: NIEGA INAPLICACION
A4: 2025-00137 | B4: 45744 | C4: 45750 | D4: INAPLICA
A5: 2025-00321 | B5: 45842 | E5: CAROLINA
A6: 2025-00323 | B6: 45848 | C6: 45848 | D6: INAPLICA | E6: LINA
A7: 2025-00414 | B7: 45870 | D7: REVOCA SANCION CIRCUITO | E7: ALEXANDER
A8: 2025-00524 | B8: 45884 | C8: 45889 | D8: NIEGA INAPLICACION | E8: LACIDES

Sheet Tutelas - Vigilancia
A3: TIPO | B3: RADICADO | C3: DEPENDENCIA | D3: FECHA LLEGADA | E3: FECHA RESPUESTA | F3: DECISIÓN
A4: 2024
A5: TUTELA | B5: 2024-00308 | C5: JUZGADO 03 CIVIL CIRCUITO | D5: 45568 | E5: 45572 | F5: NIEGA - HECHO SUPERADO
A6: VIGILANCIA | B6: 03-2024-00572 | C6: CONSEJO SECCIONAL | D6: 45573 | E6: 45575 | F6: ABSTIENE
A7: VIGILANCIA | B7: 02-2024-00429 | C7: CONSEJO SECCIONAL | D7: 45587 | E7: 45590 | F7: ABSTIENE
A8: VIGILANCIA | B8: 02-2024-00557 | C8: CONSEJO SECCIONAL | D8: 45642 | E8: 45305 | F8: ABSTIENE
A10: 2025
A11: TIPO | B11: RADICADO | C11: DEPENDENCIA | D11: FECHA LLEGADA | E11: FECHA RESPUESTA | F11: DECISIÓN | G11: IMPUGNARON/ | H11: VENCE IMPUGNACION | I11: DECISION
A12: VIGILANCIA | B12: 02-2024-00530 | C12: CONSEJO SECCIONAL | D12: 45671 | E12: 45674 | F12: ABSTIENE
A13: TUTELA | B13: 02-2024-00288 | C13: JUZGADO 02 CIVIL CIRCUITO | D13: 45672 | E13: 45673 | F13: NIEGA - INEXISTENCIA VULNERACION
A14: TUTELA | B14: 04-2024-00161 | C14: JUZGADO 01 CIVIL CTO | D14: 45673 | E14: 45677 | F14: HECHO SUPERADO
A15: TUTELA | B15: 031-2025-00090 | C15: J. 31 PENAL MPAL CONTROL GARANTIAS | D15: 45728
A16: TUTELA | B16: 002-2025-00134-00 | C16: JUZGADO 02 CIVIL CIRCUITO | D16: 45757 | E16: 45757 | F16: REQUIERE AUTO NOTIFICANDO VINCULADOS - 22/04/2025
A17: PETICION | B17: SIN RADICADO | C17: DAVID MATEO LEIVA SILVA | E17: 45758 | F17: RESUELTO Y OCULTAMIENTO REALIZADO POR JAIBER
A18: VIGILANCIA | B18: 2024-00273 | C18: EDWARD PINZON COGOLLO | D18: 45769 | E18: 45770 | F18: ORDENA ARCHIVAR VIGILANCIA
A19: VIGILANCIA | B19: 2025-00009 | C19: CONSEJO SECCIONAL | D19: 45770 | E19: 45775 | F19: ORDENA ARCHIVAR VIGILANCIA
A20: TUTELA | B20: 2025-00325 | D20: 45792 | E20: 45797 | F20: ORDENA ARCHIVAR VIGILANCIA
A21: VIGILANCIA | B21: 2024-00174 | C21: CONSEJO SECCIONAL | D21: 45797 | E21: 45798 | F21: ORDENA ARCHIVAR VIGILANCIA
A22: VIGILANCIA | B22: 2025-00009 | C22: CONSEJO SECCIONAL | D22: 45798 | E22: 45805 | F22: ORDENA ARCHIVAR VIGILANCIA
A23: TUTELA | B23: 014-2025-00281 | C23: JUZGADO 14 PENAL CON FCG MEDELLIN | D23: 45841 | E23: 45845 | F23: DECLARA IMPROCEDENTE POR INEXISTENCIA DE C VULNERADORA | G23: SI | H23: HASTA EL 31/07/2025
A24: TUTELA | B24: 002-2025-00293 | C24: JUZGADO 002 CIVIL CIRCUITO DE ENVIGADO | D24: 45853 | E24: 45862 | F24: NIEGA TUTELA - Y DEJA SIN EFECTOS LA MEDIDA PROVISIONAL CONCEDIDA | G24: SI | H24: HASTA EL 30/08/2025
A25: TUTELA | B25: 001-2025-00315-00 | C25: JUZGADO 001 CVIL DEL CIRCUITO DE ENVIGADO | D25: 45855 | E25: 45855 | F25: NIEGA - INEXISTENCIA VULNERACION | G25: N/A
A26: TUTELA | B26: 015-2025-01278-00 | C26: JUZGADO 15 CIVIL MUNICIPAL DE ENVIGADO | D26: 45870 | E26: 45873 | F26: NIEGA - INEXISTENCIA VULNERACION | G26: N/A

Sheet Acciones Populares
E1: SEGUIMIENTO A TÉRMINOS PROCESALES - ACCIONES POPULARES
E2: PROCESO MEJORAMIENTO DE LA GESTIÓN
A4: Juzgado | E4: Juzgado Primero Civil Circuito
A6: NO. | B6: N° RADICADO | C6: Demandante | D6: Demandado | E6: FECHA DE INGRESO (dd-mm-aaaa) | F6: FECHA DEL AUTO DE ADMISIÓN O NO (dd-mm-aaaa) | G6: ¿CUMPLIÓ CON EL TÉRMINO DE ADMISIÓN/INADMISIÓN? (si/no) | H6: PERSPECTIVA DE GÉNERO (SI/NO) | I6: FECHA DE LA SENTENCIA (dd-mm-aaaa) | J6: ¿DICTÓ SENTENCIA DENTRO DEL TÉRMINO? (si/no) | K6: OBSERVACIONES (EN CASO DE NO CUMPLIR LOS TÉRMINOS) | L6: No. DE DÍAS
A7: 1 | H7: NO
A8: 2 | H8: NO
A9: 3 | H9: NO
A10: 4 | H10: NO
A11: 5 | H11: NO
A12: 6 | H12: NO
A13: 7 | H13: NO
A14: 8 | H14: NO
A15: 9 | H15: NO
A16: 10 | H16: NO
A17: 11 | H17: NO
A18: 12 | H18: NO
... A61: 55 | H61: NO
A62: 56 | G62: #NAME? | H62: NO
A63: 57 | G63: #NAME? | H63: NO
A64: 58 | G64: #NAME? | H64: NO
A65: 59 | G65: #NAME? | H65: NO
A66: 60 | G66: #NAME? | H66: NO
A67: 61 | G67: #NAME? | H67: NO
A68: 62 | G68: #NAME? | H68: NO
A69: 63 | G69: #NAME? | H69: NO
A70: 64 | G70: #NAME? | H70: NO
A71: 65 | G71: #NAME? | H71: NO
A72: 66 | G72: #NAME? | H72: NO
A73: 67 | G73: #NAME? | H73: NO
... A1150: 1140 | G1150: #NAME? | H1150: NO
A1151: CONTAR SI | G1151: =COUNTIF(G7:G1150,"SI") -> 0 | H1151: =COUNTIF(H7:H1150,"SI") -> 0 | J1151: =COUNTIF(J7:J1150,"SI") -> 0
A1152: CONTAR NO | G1152: =COUNTIF(G7:G1150,"NO") -> 0 | H1152: =COUNTIF(H7:H1150,"NO") -> 1143 | J1152: =COUNTIF(J7:J1150,"NO") -> 0
A1153: TOTAL | G1153: =SUM(G1151:G1152) -> 0 | H1153: =SUM(H1151:H1152) -> 1143 | J1153: =SUM(J1151:J1152) -> 0
A1154: % DE CUMPLIMIENTO | G1154: =G1151/G1153 -> #DIV/0! | H1154: =H1151/H1153 -> 0 | J1154: =J1151/J1153 -> #DIV/0!

Sheet Habeas Corpus
E1: SEGUIMIENTO A TÉRMINOS PROCESALES - HABEAS CORPUS
E2: PROCESO MEJORAMIENTO DE LA GESTIÓN
A4: Juzgado | E4: Juzgado Primero Civil Circuito
A6: NO. | B6: N° RADICADO | C6: Accionante | D6: Accionado | E6: FECHA DE INGRESO (dd-mm-aaaa) | F6: FECHA DE RESUELVE (dd-mm-aaaa) | G6: PERSPECTIVA DE GÉNERO (SI/NO) | H6: ¿CUMPLIÓ CON EL TÉRMINO DE RESUELVE? (si/no) | I6: No. DE DÍAS
A7: 1 | G7: NO | H7: #NAME? | I7: #NAME?
A8: 2 | G8: NO | H8: =IF(NETWORKDAYS(E8,F8)<=2,"SI","NO") -> SI | I8: =NETWORKDAYS(E8,F8) -> 0
A9: 3 | G9: NO | H9: =IF(NETWORKDAYS(E9,F9)<=2,"SI","NO") -> SI | I9: =NETWORKDAYS(E9,F9) -> 0
A10: 4 | G10: NO | H10: =IF(NETWORKDAYS(E10,F10)<=2,"SI","NO") -> SI | I10: =NETWORKDAYS(E10,F10) -> 0
A11: 5 | G11: NO | H11: =IF(NETWORKDAYS(E11,F11)<=2,"SI","NO") -> SI | I11: =NETWORKDAYS(E11,F11) -> 0
A12: 6 | G12: NO | H12: =IF(NETWORKDAYS(E12,F12)<=2,"SI","NO") -> SI | I12: =NETWORKDAYS(E12,F12) -> 0
A13: 7 | G13: NO | H13: =IF(NETWORKDAYS(E13,F13)<=2,"SI","NO") -> SI | I13: =NETWORKDAYS(E13,F13) -> 0
A14: 8 | G14: NO | H14: =IF(NETWORKDAYS(E14,F14)<=2,"SI","NO") -> SI | I14: =NETWORKDAYS(E14,F14) -> 0
A15: 9 | G15: NO | H15: =IF(NETWORKDAYS(E15,F15)<=2,"SI","NO") -> SI | I15: =NETWORKDAYS(E15,F15) -> 0
A16: 10 | G16: NO | H16: =IF(NETWORKDAYS(E16,F16)<=2,"SI","NO") -> SI | I16: =NETWORKDAYS(E16,F16) -> 0
A17: 11 | G17: NO | H17: =IF(NETWORKDAYS(E17,F17)<=2,"SI","NO") -> SI | I17: =NETWORKDAYS(E17,F17) -> 0
A18: 12 | G18: NO | H18: =IF(NETWORKDAYS(E18,F18)<=2,"SI","NO") -> SI | I18: =NETWORKDAYS(E18,F18) -> 0
A19: 13 | G19: NO | H19: =IF(NETWORKDAYS(E19,F19)<=2,"SI","NO") -> SI | I19: =NETWORKDAYS(E19,F19) -> 0
... A1150: 1144 | G1150: NO | H1150: =IF(NETWORKDAYS(E1150,F1150)<=2,"SI","NO") -> SI | I1150: =NETWORKDAYS(E1150,F1150) -> 0
A1151: CONTAR SI | G1151: =COUNTIF(G7:G1150,"SI") -> 0 | H1151: =COUNTIF(H7:H1150,"SI") -> 1143
A1152: CONTAR NO | G1152: =COUNTIF(G7:G1150,"NO") -> 1144 | H1152: =COUNTIF(H7:H1150,"NO") -> 0
A1153: TOTAL | G1153: =SUM(G1151:G1152) -> 1144 | H1153: =SUM(H1151:H1152) -> 1143
A1154: % DE CUMPLIMIENTO | G1154: =G1151/G1153 -> 0 | H1154: =H1151/H1153 -> 1

Sheet Días No Laborales
A1: 2010 | B1: 2011 | C1: 2012 | D1: 2013 | E1: 2014 | F1: 2015 | G1: 2016 | H1: 2017 | I1: 2018 | J1: 2019 | K1: 2020 | L1: 2021 | M1: 2022 | N1: 2023 | O1: 2024 | P1: 2025 | Q1: 2026 | R1: 2027 | S1: 2028 | T1: 2029 | U1: 2030
A2: 40179 | B2: 40544 | C2: 40909 | D2: 41275 | E2: 41640 | F2: 42005 | G2: 42370 | H2: 42736 | I2: 43101 | J2: 43466 | K2: 43831 | L2: 44197 | M2: 44562 | N2: 44927 | O2: 45292 | P2: 45658 | Q2: 46023 | R2: 46388 | S2: 46753 | T2: 47119 | U2: 47484
A3: 40180 | B3: 40545 | C3: 40910 | D3: 41276 | E3: 41641 | F3: 42006 | G3: 42371 | H3: 42737 | I3: 43102 | J3: 43467 | K3: 43832 | L3: 44198 | M3: 44563 | N3: 44928 | O3: 45293 | P3: 45659 | Q3: 46024 | R3: 46389 | S3: 46754 | T3: 47120 | U3: 47485
A4: 40181 | B4: 40546 | C4: 40911 | D4: 41277 | E4: 41642 | F4: 42007 | G4: 42372 | H4: 42738 | I4: 43103 | J4: 43468 | K4: 43833 | L4: 44199 | M4: 44564 | N4: 44929 | O4: 45294 | P4: 45660 | Q4: 46025 | R4: 46390 | S4: 46755 | T4: 47121 | U4: 47486
A5: 40182 | B5: 40547 | C5: 40912 | D5: 41278 | E5: 41643 | F5: 42008 | G5: 42373 | H5: 42739 | I5: 43104 | J5: 43469 | K5: 43834 | L5: 44200 | M5: 44565 | N5: 44930 | O5: 45295 | P5: 45661 | Q5: 46026 | R5: 46391 | S5: 46756 | T5: 47122 | U5: 47487
A6: 40183 | B6: 40548 | C6: 40913 | D6: 41279 | E6: 41644 | F6: 42009 | G6: 42374 | H6: 42740 | I6: 43105 | J6: 43470 | K6: 43835 | L6: 44201 | M6: 44566 | N6: 44931 | O6: 45296 | P6: 45662 | Q6: 46027 | R6: 46392 | S6: 46757 | T6: 47123 | U6: 47488
A7: 40184 | B7: 40549 | C7: 40914 | D7: 41280 | E7: 41645 | F7: 42010 | G7: 42375 | H7: 42741 | I7: 43106 | J7: 43471 | K7: 43836 | L7: 44202 | M7: 44567 | N7: 44932 | O7: 45297 | P7: 45663 | Q7: 46028 | R7: 46393 | S7: 46758 | T7: 47124 | U7: 47489
A8: 40185 | B8: 40550 | C8: 40915 | D8: 41281 | E8: 41646 | F8: 42011 | G8: 42376 | H8: 42742 | I8: 43107 | J8: 43472 | K8: 43837 | L8: 44203 | M8: 44568 | N8: 44933 | O8: 45298 | P8: 45664 | Q8: 46029 | R8: 46394 | S8: 46759 | T8: 47125 | U8: 47490
A9: 40186 | B9: 40551 | C9: 40916 | D9: 41282 | E9: 41647 | F9: 42012 | G9: 42377 | H9: 42743 | I9: 43108 | J9: 43473 | K9: 43838 | L9: 44204 | M9: 44569 | N9: 44934 | O9: 45299 | P9: 45665 | Q9: 46030 | R9: 46395 | S9: 46760 | T9: 47126 | U9: 47491
A10: 40187 | B10: 40552 | C10: 40917 | D10: 41283 | E10: 41648 | F10: 42013 | G10: 42378 | H10: 42744 | I10: 43109 | J10: 43474 | K10: 43839 | L10: 44205 | M10: 44570 | N10: 44935 | O10: 45300 | P10: 45666 | Q10: 46031 | R10: 46396 | S10: 46761 | T10: 47127 | U10: 47492
A11: 40188 | B11: 40553 | C11: 40918 | D11: 41284 | E11: 41649 | F11: 42014 | G11: 42379 | H11: 42745 | I11: 43110 | J11: 43475 | K11: 43840 | L11: 44206 | M11: 44571 | N11: 44936 | O11: 45301 | P11: 45667 | Q11: 46032 | R11: 46397 | S11: 46762 | T11: 47131 | U11: 47493
A12: 40189 | B12: 40558 | C12: 40919 | D12: 41286 | E12: 41650 | F12: 42015 | G12: 42380 | H12: 42749 | I12: 43113 | J12: 43477 | K12: 43841 | L12: 44207 | M12: 44576 | N12: 44940 | O12: 45304 | P12: 45668 | Q12: 46033 | R12: 46398 | S12: 46767 | T12: 47132 | U12: 47495
... A19: 40215 | B19: 40580 | C19: 40943 | D19: 41308 | E19: 41672 | F19: 42036 | G19: 42406 | H19: 42771 | I19: 43128 | J19: 43499 | K19: 43863 | L19: 44233 | M19: 44598 | N19: 44962 | O19: 45326 | P19: 45690 | Q19: 46054 | R19: 46424 | S19: 46789 | T19: 47159 | U19: 47517
A20: 40216 | B20: 40586 | C20: 40944 | D20: 41315 | E20: 41679 | F20: 42042 | G20: 42407 | H20: =H18+7 -> 42777 | I20: 43134 | J20: 43505 | K20: 43869 | L20: 44234 | M20: 44604 | N20: 44968 | O20: 45332 | P20: 45696 | Q20: 46060 | R20: 46425 | S20: 46795 | T20: 47160 | U20: 47523
A21: 40222 | B21: 40587 | C21: 40950 | D21: 41316 | E21: 41685 | F21: 42043 | G21: 42413 | H21: 42778 | I21: 43135 | J21: 43506 | K21: 43870 | L21: 44240 | M21: 44605 | N21: 44969 | O21: 45333 | P21: 45697 | Q21: 46061 | R21: 46431 | S21: 46796 | T21: 47166 | U21: 47524
A22: 40223 | B22: 40593 | C22: 40951 | D22: 41322 | E22: 41686 | F22: 42049 | G22: 42414 | H22: 42784 | I22: 43141 | J22: 43512 | K22: 43876 | L22: 44241 | M22: 44611 | N22: 44975 | O22: 45339 | P22: 45703 | Q22: 46067 | R22: 46432 | S22: 46802 | T22: 47167 | U22: 47530
A23: 40229 | B23: 40594 | C23: 40957 | D23: 41323 | E23: 41692 | F23: 42050 | G23: 42420 | H23: 42785 | I23: 43142 | J23: 43513 | K23: 43877 | L23: 44247 | M23: 44612 | N23: 44976 | O23: 45340 | P23: 45704 | Q23: 46068 | R23: 46438 | S23: 46803 | T23: 47173 | U23: 47531
A24: 40230 | B24: 40600 | C24: 40958 | D24: 41329 | E24: 41693 | F24: 42056 | G24: 42421 | H24: 42791 | I24: 43148 | J24: 43519 | K24: 43883 | L24: 44248 | M24: 44618 | N24: 44982 | O24: 45346 | P24: 45710 | Q24: 46074 | R24: 46439 | S24: 46809 | T24: 47174 | U24: 47537
A25: 40236 | B25: 40601 | C25: 40964 | D25: 41330 | E25: 41699 | F25: 42057 | G25: 42427 | H25: 42792 | I25: 43149 | J25: 43520 | K25: 43884 | L25: 44254 | M25: 44619 | N25: 44983 | O25: 45347 | P25: 45711 | Q25: 46075 | R25: 46445 | S25: 46810 | T25: 47180 | U25: 47538
A26: 40237 | B26: 40607 | C26: 40965 | D26: 41335 | E26: 41700 | F26: 42063 | G26: 42428 | H26: 42798 | I26: 43155 | J26: 43526 | K26: 43890 | L26: 44255 | M26: 44625 | N26: 44989 | O26: 45353 | P26: 45717 | Q26: 46081 | R26: 46446 | S26: 46816 | T26: 47181 | U26: 47544
A27: 40243 | B27: 40608 | C27: 40971 | D27: 41336 | E27: 41706 | F27: 42064 | G27: 42434 | H27: 42799 | I27: 43156 | J27: 43527 | K27: 43891 | L27: 44261 | M27: 44626 | N27: 44990 | O27: 45354 | P27: 45718 | Q27: 46082 | R27: 46452 | S27: 46817 | T27: 47187 | U27: 47545
A28: 40244 | B28: 40614 | C28: 40972 | D28: 41342 | E28: 41707 | F28: 42070 | G28: 42435 | H28: 42805 | I28: 43162 | J28: 43533 | K28: 43897 | L28: 44262 | M28: 44632 | N28: 44996 | O28: 45360 | P28: 45724 | Q28: 46088 | R28: 46453 | S28: 46823 | T28: 47188 | U28: 47551
A29: 40250 | B29: 40615 | C29: 40985 | D29: 41343 | E29: 41713 | F29: 42071 | G29: 42441 | H29: 42806 | I29: 43163 | J29: 43534 | K29: 43898 | L29: 44268 | M29: 44633 | N29: 44997 | O29: 45361 | P29: 45725 | Q29: 46089 | R29: 46459 | S29: 46824 | T29: 47194 | U29: 47552
A30: 40251 | B30: 40621 | C30: 40986 | D30: 41349 | E30: 41714 | F30: 42077 | G30: 42442 | H30: 42812 | I30: 43169 | J30: 43540 | K30: 43904 | L30: 44269 | M30: 44639 | N30: 45003 | O30: 45367 | P30: 45731 | Q30: 46095 | R30: 46460 | S30: 46830 | T30: 47195 | U30: 47558
A31: 40257 | B31: 40622 | C31: 40987 | D31: 41350 | E31: 41722 | F31: 42078 | G31: 42448 | H31: 42813 | I31: 43170 | J31: 43541 | K31: 43905 | L31: 44275 | M31: 44640 | N31: 45004 | O31: 45368 | P31: 45732 | Q31: 46096 | R31: 46466 | S31: 46831 | T31: 47196 | U31: 47559
A32: 40258 | B32: 40623 | C32: 40992 | D32: 41356 | E32: 41727 | F32: 42084 | G32: 42449 | H32: 42814 | I32: 43176 | J32: 43547 | K32: 43911 | L32: 44276 | M32: 45006 | N32: 45005 | O32: 45374 | P32: 45738 | Q32: 46102 | R32: 46467 | S32: 46832 | T32: 47201 | U32: 47537
... A135: 40539 | B135: 40906 | C135: 41273 | D135: 41637 | E135: 42004 | F135: 42363 | G135: 42733 | H135: 43096 | I135: 43459 | J135: 43830 | K135: 44190 | L135: 44557 | M135: 44924 | N135: 45287 | O135: 45657 | P135: 46020 | Q135: 46383 | R135: 46750 | S135: 47114 | T135: 47481 | U135: 47848
A136: 40540 | B136: 40907 | C136: 41274 | D136: 41638 | F136: 42364 | G136: 42734 | H136: 43097 | I136: 43460 | K136: 44191 | L136: 44558 | M136: 44925 | N136: 45288 | P136: 46021 | Q136: 46384 | R136: 46751 | S136: 47115 | T136: 47482
A137: 40541 | B137: 40908 | D137: 41639 | F137: 42365 | G137: 42735 | H137: 43098 | I137: 43461 | K137: 44192 | L137: 44559 | M137: 44926 | N137: 45289 | P137: 46022 | Q137: 46385 | R137: 46752 | S137: 47116 | T137: 47483
A138: 40542 | F138: 42366 | H138: 43099 | I138: 43462 | K138: 44193 | L138: 44560 | N138: 45290 | Q138: 46386 | S138: 47117
A139: 40543 | F139: 42367 | H139: 43100 | I139: 43463 | K139: 44194 | L139: 44561 | N139: 45291 | Q139: 46387 | S139: 47118
F140: 43464 | I140: 43464 | K140: 44195
F141: 43465 | I141: 43465 | K141: 44196

Sheet SIERJU

Sheet Notas de Cambio
A1: PROCESOS
A2: VERSIÓN INICIAL | B2: BREVE DESCRIPCIÓN DEL CAMBIO | C2: VERSIÓN FINAL | D2: FECHA
A3: 1 | B3: No aplica para la primera versión. | C3: 1 | D3: 40571
A4: 2 | B4: Se incluyó la columna "Perspectiva de Género" y se actualizó el logo del CSJ.. | C4: 1 | D4: 40898
A6: TUTELAS
A7: VERSIÓN INICIAL | B7: BREVE DESCRIPCIÓN DEL CAMBIO | C7: VERSIÓN FINAL | D7: FECHA
A8: 1 | B8: No aplica para la primera versión. | C8: 1 | D8: 40571
A9: 2 | B9: Se eliminaron las columnas "Fecha del Auto" y "Cumplimiento de la Primera Actuación". | C9: 1 | D9: 40898
A10: 2 | B10: Se incluyó la columna "Perspectiva de Género" y se actualizó el logo del CSJ.. | C10: 1 | D10: 40898
A12: TUTELAS SEGUNDA INSTANCIA
A13: VERSIÓN INICIAL | B13: BREVE DESCRIPCIÓN DEL CAMBIO | C13: VERSIÓN FINAL | D13: FECHA
A14: 1 | B14: No aplica para la primera versión. | C14: 1 | D14: 40571
A15: 2 | B15: Se eliminaron las columnas "Fecha del Auto" y "Cumplimiento de la Primera Actuación". | C15: 1 | D15: 40898
A16: 2 | B16: Se incluyó la columna "Perspectiva de Género" y se actualizó el logo del CSJ.. | C16: 1 | D16: 40898
A18: ACCIONES DE GRUPO
A19: VERSIÓN INICIAL | B19: BREVE DESCRIPCIÓN DEL CAMBIO | C19: VERSIÓN FINAL | D19: FECHA
A20: 1 | B20: No aplica para la primera versión. | C20: 1 | D20: 40571
A21: 2 | B21: Se incluyó la columna "Perspectiva de Género" y se actualizó el logo del CSJ.. | C21: 1 | D21: 40898
A23: ACCIONES POPULARES
A24: VERSIÓN INICIAL | B24: BREVE DESCRIPCIÓN DEL CAMBIO | C24: VERSIÓN FINAL | D24: FECHA
A25: 1 | B25: No aplica para la primera versión. | C25: 1 | D25: 40571
A26: 2 | B26: Se incluyó la columna "Perspectiva de Género" y se actualizó el logo del CSJ.. | C26: 1 | D26: 40898
A28: HABEAS CORPUS
A29: VERSIÓN INICIAL | B29: BREVE DESCRIPCIÓN DEL CAMBIO | C29: VERSIÓN FINAL | D29: FECHA
A30: 1 | B30: No aplica para la primera versión. | C30: 1 | D30: 40571
A31: 2 | B31: Se incluyó la columna "Perspectiva de Género" y se actualizó el logo del CSJ.. | C31: 1 | D31: 40898

Sheet Acciones de Grupo
E1: SEGUIMIENTO A TÉRMINOS PROCESALES - ACCIONES DE GRUPO
E2: PROCESO MEJORAMIENTO DE LA GESTIÓN
A4: Juzgado | E4: Juzgado Primero Civil Circuito
A6: NO. | B6: N° RADICADO | C6: Demandante | D6: Demandado | E6: FECHA DE INGRESO (dd-mm-aaaa) | F6: FECHA DEL AUTO DE ADMISIÓN O NO (dd-mm-aaaa) | G6: ¿CUMPLIÓ CON EL TÉRMINO DE ADMISIÓN/INADMISIÓN? (si/no) | H6: PERSPECTIVA DE GÉNERO (SI/NO) | I6: FECHA DE LA SENTENCIA (dd-mm-aaaa) | J6: ¿DICTÓ SENTENCIA DENTRO DEL TÉRMINO? (si/no) | K6: OBSERVACIONES (EN CASO DE NO CUMPLIR LOS TÉRMINOS) | L6: No. DE DÍAS
A7: 1 | G7: Si | H7: NO
A8: 2 | G8: #NAME? | H8: NO
A9: 3 | G9: #NAME? | H9: NO
A10: 4 | G10: #NAME? | H10: NO
A11: 5 | G11: #NAME? | H11: NO
A12: 6 | G12: #NAME? | H12: NO
A13: 7 | G13: #NAME? | H13: NO
A14: 8 | G14: #NAME? | H14: NO
A15: 9 | G15: #NAME? | H15: NO
A16: 10 | G16: #NAME? | H16: NO
A17: 11 | G17: #NAME? | H17: NO
A18: 12 | G18: #NAME? | H18: NO
A19: 13 | G19: #NAME? | H19: NO
... A34: 28 | G34: #NAME? | H34: NO
G35: #NAME? | H35: NO
A36: 29 | G36: #NAME? | H36: NO
A37: 30 | G37: #NAME? | H37: NO
A38: 31 | G38: #NAME? | H38: NO
A39: 29 | G39: #NAME? | H39: NO
A40: 30 | G40: #NAME? | H40: NO
A41: 31 | G41: #NAME? | H41: NO
A42: 32 | G42: #NAME? | H42: NO
A43: 33 | G43: #NAME? | H43: NO
A44: 34 | G44: #NAME? | H44: NO
A45: 35 | G45: #NAME? | H45: NO
A46: 36 | G46: #NAME? | H46: NO
A47: 37 | G47: #NAME? | H47: NO
A48: 39 | G48: #NAME? | H48: NO
G49: #NAME? | H49: NO
A50: 40 | G50: #NAME? | H50: NO
A51: 41 | G51: #NAME? | H51: NO
A52: 42 | G52: #NAME? | H52: NO
A53: 43 | G53: #NAME? | H53: NO
A54: 44 | G54: #NAME? | H54: NO
A55: 45 | G55: #NAME? | H55: NO
A56: 46 | G56: #NAME? | H56: NO
A57: 47 | G57: #NAME? | H57: NO
A58: 48 | G58: #NAME? | H58: NO
A59: 49 | G59: #NAME? | H59: NO
A60: 50 | G60: #NAME? | H60: NO
A61: 51 | G61: #NAME? | H61: NO
... A1150: 1140 | G1150: #NAME? | H1150: NO
A1151: CONTAR SI | G1151: =COUNTIF(G7:G1150,"SI") -> 1 | H1151: =COUNTIF(H7:H1150,"SI") -> 0 | J1151: =COUNTIF(J7:J1150,"SI") -> 0
A1152: CONTAR NO | G1152: =COUNTIF(G7:G1150,"NO") -> 0 | H1152: =COUNTIF(H7:H1150,"NO") -> 1144 | J1152: =COUNTIF(J7:J1150,"NO") -> 0
A1153: TOTAL | G1153: =SUM(G1151:G1152) -> 1 | H1153: =SUM(H1151:H1152) -> 1144 | J1153: =SUM(J1151:J1152) -> 0
A1154: % DE CUMPLIMIENTO | G1154: =G1151/G1153 -> 1 | H1154: =H1151/H1153 -> 0 | J1154: =J1151/J1153 -> #DIV/0!

Sheet PROC. ESTADISTICA
B3: REMITIDOS X OTROS DESPACHOS
B6: (FIL5541) DECLARATIVOS VERBAL PERTENENCIA | D6: (FIL6251) DECLARATIVOS VERBAL RESTITUCIÓN DE INMUEBLE ARRENDADO | F6: (FIL6253) DECLARATIVOS VERBAL OTROS PROCESOS | H6: DECLARATIVOS VERBAL SUMARIO CONTROVERSIAS SOBRE PROPIEDAD HORIZONTAL | J6: (FIL6257) DECLARATIVOS VERBAL SUMARIO OTROS PROCESOS | L6: (FIL5547) DECLARATIVOS ESPECIALES DIVISORIO | N6: (FIL102) EJECUTIVOS | AJ6: (FIL5548) EJECUTIVOS CON GARANTÍA REAL | AL6: (FIL2062) MONITORIO | AN6: (FIL5214) INSOLVENCIA DE LA PERSONA NATURAL NO COMERCIANTE | AP6: (FIL76) PROCESOS DE LIQUIDACIÓN - SUCESIÓN | AR6: (FIL80) PROCESOS DE JURISDICCIÓN VOLUNTARIA | BD6: AMPARROS DE POBREZA
A7: 1 | B7: 001-2022-00378 | C7: 1 | D7: 001-2022-00068 | E7: 1 | F7: 001-2023-00414 | G7: 1 | H7: 003-2024-00572 | I7: 1 | J7: 001-2023-00216 | K7: 1 | L7: 001-2024-00141 | M7: 1 | N7: 001-2023-01613 | P7: 36 | Q7: 001-2024-00518 | R7: 71 | S7: 001-2024-00748 | T7: 106 | U7: 001-2024-00271 | V7: 141 | W7: 001-2024-00590 | Y7: 002-2024-00109 | AA7: 002-2024-00197 | AC7: 002-2024-00277 | AE7: 002-2024-00377 | AG7: 002-2024-00472 | AI7: 1 | AJ7: 001-2024-00711 | AK7: 1 | AL7: 002-2024-00475 | AM7: 1 | AN7: 001-2024-00474 | AO7: 1 | AP7: 001-2024-00155 | AQ7: 1 | AR7: 002-2024-00419 | BC7: 1 | BD7: 2024-00025
A8: 2 | B8: 001-2024-00392 | C8: 2 | D8: 001-2023-00619 | E8: 2 | F8: 001-2024-00100 | I8: 2 | J8: 001-2023-00453 | K8: 2 | L8: 001-2023-00897 | M8: 2 | N8: 001-2023-01614 | P8: 37 | Q8: 001-2024-00525 | R8: 72 | S8: 001-2024-00755 | T8: 107 | U8: 001-2024-00285 | V8: 142 | W8: 001-2024-00611 | Y8: 002-2024-00112 | AA8: 002-2024-00201 | AC8: 002-2024-00279 | AE8: 002-2024-00379 | AG8: 002-2024-00473 | AI8: 2 | AJ8: 001-2024-00752 | AK8: 2 | AL8: 002-2024-00496 | AM8: 2 | AN8: 002-2024-00096 | AO8: 2 | AP8: 001-2024-00572 | BC8: 2 | BD8: 2024-00135
A9: 3 | B9: 001-2020-00747 | C9: 3 | D9: 001-2023-01227 | E9: 3 | F9: 001-2024-00484 | I9: 3 | J9: 001-2023-00960 | K9: 3 | L9: 002-2024-00535 | M9: 3 | N9: 001-2024-00018 | P9: 38 | Q9: 001-2024-00544 | R9: 73 | S9: 001-2024-00758 | T9: 108 | U9: 001-2024-00290 | V9: 143 | W9: 001-2024-00620 | Y9: 002-2024-00113 | AA9: 002-2024-00204 | AC9: 002-2024-00280 | AE9: 002-2024-00384 | AG9: 002-2024-00481 | AI9: 3 | AJ9: 001-2023-01178 | AK9: 3 | AL9: 002-2024-00624 | AM9: 3 | AN9: 003-2024-00815 | AO9: 3 | AP9: 001-2023-01140 | BC9: 3 | BD9: 2024-00152
A10: 4 | B10: 001-2021-01171 | C10: 4 | D10: 001-2024-00289 | E10: 4 | F10: 001-2022-01022 | I10: 4 | J10: 001-2024-00683 | K10: 4 | L10: 003-2023-01474 | M10: 4 | N10: 001-2024-00031 | P10: 39 | Q10: 001-2024-00545 | R10: 74 | S10: 001-2024-00761 | T10: 109 | U10: 001-2024-00299 | V10: 144 | W10: 001-2024-00623 | Y10: 002-2024-00114 | AA10: 002-2024-00206 | AC10: 002-2024-00281 | AE10: 002-2024-00393 | AG10: 002-2024-00483 | AI10: 4 | AJ10: 001-2023-01293 | AM10: 4 | AN10: 003-2024-00362 | AO10: 4 | AP10: 001-2023-00383 | BC10: 4 | BD10: 2024-00164
A11: 5 | B11: 001-2024-00020 | C11: 5 | D11: 001-2024-00596 | E11: 5 | F11: 001-2023-01490 | I11: 5 | J11: 001-2023-00064 | M11: 5 | N11: 001-2024-00032 | P11: 40 | Q11: 001-2024-00559 | R11: 75 | S11: 001-2024-00768 | T11: 110 | U11: 001-2024-00303 | V11: 145 | W11: 001-2024-00630 | Y11: 002-2024-00116 | AA11: 002-2024-00207 | AC11: 002-2024-00282 | AE11: 002-2024-00395 | AG11: 002-2024-00487 | AI11: 5 | AJ11: 002-2024-00081 | AM11: 5 | AN11: 003-2024-00177 | AO11: 5 | AP11: 001-2024-00506
A12: 6 | B12: 002-2024-00434 | C12: 6 | D12: 001-2024-00646 | E12: 6 | F12: 001-2023-01554 | I12: 6 | J12: 001-2023-01653 | M12: 6 | N12: 001-2024-00035 | P12: 41 | Q12: 001-2024-00565 | R12: 76 | S12: 001-2023-01619 | T12: 111 | U12: 001-2024-00305 | W12: 001-2024-00635 | Y12: 002-2024-00122 | AA12: 002-2024-00208 | AC12: 002-2024-00286 | AE12: 002-2024-00397 | AG12: 002-2024-00488 | AI12: 6 | AJ12: 002-2024-00085 | AM12: 6 | AN12: 003-2024-00117 | AO12: 6 | AP12: 002-2024-00381
A13: 7 | B13: 002-2024-00505 | C13: 7 | D13: 001-2021-00750 | E13: 7 | F13: 002-2024-00217 | I13: 7 | J13: 001-2023-00574 | M13: 7 | N13: 001-2024-00053 | P13: 42 | Q13: 001-2024-00571 | R13: 77 | S13: 001-2023-01622 | T13: 112 | U13: 001-2024-00310 | W13: 001-2024-00636 | Y13: 002-2024-00124 | AA13: 002-2024-00209 | AC13: 002-2024-00288 | AE13: 002-2024-00400 | AG13: 002-2024-00445 | AH13: Conexo | AI13: 7 | AJ13: 002-2024-00095 | AM13: 7 | AN13: 003-2023-01429 | AO13: 7 | AP13: 002-2024-00438
A14: 8 | B14: 002-2024-00508 | C14: 8 | D14: 001-2022-00232 | E14: 8 | F14: 002-2024-00248 | I14: 8 | J14: 002-2024-00276 | M14: 8 | N14: 001-2024-00074 | P14: 43 | Q14: 001-2024-00577 | R14: 78 | S14: 001-2023-01635 | T14: 113 | U14: 001-2024-00322 | W14: 001-2024-00670 | Y14: 002-2024-00125 | AA14: 002-2024-00212 | AC14: 002-2024-00289 | AE14: 002-2024-00401 | AG14: 003-2023-01547 | AH14: Conexo | AI14: 8 | AJ14: 002-2024-00247 | AM14: 8 | AN14: 003-2023-01277 | AO14: 8 | AP14: 002-2024-00626
A15: 9 | B15: 002-2024-00644 | C15: 9 | D15: 001-2024-00075 | E15: 9 | F15: 002-2024-00312 | I15: 9 | J15: 002-2024-00294 | M15: 9 | N15: 001-2024-00078 | P15: 44 | Q15: 001-2024-00599 | R15: 79 | S15: 001-2024-01638 | T15: 114 | U15: 001-2024-00325 | W15: 001-2024-00672 | Y15: 002-2024-00126 | AA15: 002-2024-00214 | AC15: 002-2024-00296 | AE15: 002-2024-00403 | AG15: 003-2023-01462 | AH15: Conexo | AI15: 9 | AJ15: 003-2024-00621 | AM15: 9 | AN15: 003-2023-01276 | AO15: 9 | AP15: 003-2024-00724
A16: 10 | B16: 002-2024-00707 | C16: 10 | D16: 001-2024-00254 | E16: 10 | F16: 002-2024-00345 | I16: 10 | J16: 002-2024-00427 | M16: 10 | N16: 001-2024-00083 | P16: 45 | Q16: 001-2024-00603 | R16: 80 | S16: 001-2023-01642 | T16: 115 | U16: 001-2024-00346 | W16: 001-2024-00680 | Y16: 002-2024-00132 | AA16: 002-2024-00216 | AC16: 002-2024-00298 | AE16: 002-2024-00404 | AG16: 003-2023-01461 | AH16: Conexo | AI16: 10 | AJ16: 003-2024-00308 | AO16: 10 | AP16: 003-2024-00623
A17: 11 | B17: 003-2024-00782 | C17: 11 | D17: 001-2024-00430 | E17: 11 | F17: 002-2024-00458 | I17: 11 | J17: 002-2024-00439 | M17: 11 | N17: 001-2024-00097 | P17: 46 | Q17: 001-2024-00605 | R17: 81 | S17: 001-2023-01644 | T17: 116 | U17: 001-2024-00361 | W17: 001-2024-00705 | Y17: 002-2024-00137 | AA17: 002-2024-00219 | AC17: 002-2024-00304 | AE17: 002-2024-00405 | AG17: Sigue en el cuadro | AI17: 11 | AJ17: 003-2024-00030 | AO17: 11 | AP17: 003-2024-00617
A18: 12 | B18: 003-2024-00569 | C18: 12 | D18: 001-2024-00102 | E18: 12 | F18: 002-2024-00578 | I18: 12 | J18: 002-2024-00480 | M18: 12 | N18: 001-2024-00103 | P18: 47 | Q18: 001-2024-00608 | R18: 82 | S18: 001-2023-01646 | T18: 117 | U18: 001-2024-00363 | W18: 001-2024-00738 | Y18: 002-2024-00139 | AA18: 002-2024-00221 | AC18: 002-2024-00306 | AE18: 002-2024-00406 | AG18: Total: 511 | AI18: 12 | AJ18: 003-2023-01498 | AO18: 12 | AP18: 003-2024-00607
A19: 13 | B19: 003-2024-00407 | C19: 13 | D19: 002-2024-00065 | E19: 13 | F19: 002-2024-00594 | I19: 13 | J19: 002-2024-00625 | M19: 13 | N19: 001-2024-00105 | P19: 48 | Q19: 001-2024-00616 | R19: 83 | S19: 001-2023-01656 | T19: 118 | U19: 001-2024-00364 | W19: 001-2024-00741 | Y19: 002-2024-00141 | AA19: 002-2024-00223 | AC19: 002-2024-00307 | AE19: 002-2024-00407 | AO19: 13 | AP19: 003-2024-00309
A20: 14 | B20: 003-2024-00374 | C20: 14 | D20: 002-2024-00104 | E20: 14 | F20: 002-2024-00621 | I20: 14 | J20: 002-2024-00669 | M20: 14 | N20: 001-2024-00107 | P20: 49 | Q20: 001-2024-00626 | R20: 84 | S20: 001-2024-00002 | T20: 119 | U20: 001-2024-00367 | W20: 001-2024-00771 | Y20: 002-2024-00143 | AA20: 002-2024-00224 | AC20: 002-2024-00313 | AE20: 002-2024-00412 | AO20: 14 | AP20: 003-2024-00250
A21: 15 | B21: 003-2024-00174 | C21: 15 | D21: 002-2024-00120 | E21: 15 | F21: 003-2023-01450 | I21: 15 | J21: 002-2024-00331 | M21: 15 | N21: 001-2024-00126 | P21: 50 | Q21: 001-2024-00629 | R21: 85 | S21: 001-2024-00024 | T21: 120 | U21: 001-2024-00377 | W21: 001-2024-00111 | Y21: 002-2024-00147 | AA21: 002-2024-00225 | AC21: 002-2024-00318 | AE21: 002-2024-00417 | AO21: 15 | AP21: 003-2023-01610
A22: 16 | B22: 003-2024-00064 | C22: 16 | D22: 002-2024-00131 | E22: 16 | F22: 003-2023-01347 | M22: 16 | N22: 001-2024-00174 | P22: 51 | Q22: 001-2024-00642 | R22: 86 | S22: 001-2024-00025 | T22: 121 | U22: 001-2024-00383 | W22: 001-2024-00122 | Y22: 002-2024-00148 | AA22: 002-2024-00229 | AC22: 002-2024-00320 | AE22: 002-2024-00420 | AO22: 16 | AP22: 003-2023-01460
A23: 17 | B23: 003-2023-01340 | C23: 17 | D23: 002-2024-00134 | E23: 17 | F23: 003-2023-01327 | M23: 17 | N23: 001-2024-00175 | P23: 52 | Q23: 001-2024-00647 | R23: 87 | S23: 001-2024-00039 | T23: 122 | U23: 001-2024-00388 | W23: 002-2024-00057 | Y23: 002-2024-00150 | AA23: 002-2024-00231 | AC23: 002-2024-00323 | AE23: 002-2024-00422 | AO23: 17 | AP23: 003-2023-01348
A24: 18 | B24: 003-2023-01339 | C24: 18 | D24: 002-2024-00199 | M24: 18 | N24: 001-2024-00213 | P24: 53 | Q24: 001-2024-00693 | R24: 88 | S24: 001-2024-00058 | T24: 123 | U24: 001-2024-00390 | W24: 002-2024-00060 | Y24: 002-2024-00151 | AA24: 002-2024-00234 | AC24: 002-2024-00326 | AE24: 002-2024-00425
A25: 19 | B25: 003-2023-01326 | C25: 19 | D25: 002-2024-00389 | M25: 19 | N25: 001-2024-00240 | P25: 54 | Q25: 001-2024-00661 | R25: 89 | S25: 001-2024-00076 | T25: 124 | U25: 001-2024-00401 | W25: 002-2024-00062 | Y25: 002-2024-00154 | AA25: 002-2024-00236 | AC25: 002-2024-00327 | AE25: 002-2024-00426
C26: 20 | D26: 002-2024-00470 | M26: 20 | N26: 001-2024-00263 | P26: 55 | Q26: 001-2024-00662 | R26: 90 | S26: 001-2024-00090 | T26: 125 | U26: 001-2024-00405 | W26: 002-2024-00066 | Y26: 002-2024-00157 | AA26: 002-2024-00241 | AC26: 002-2024-00332 | AE26: 002-2024-00429
C27: 21 | D27: 002-2024-00530 | M27: 21 | N27: 001-2024-00277 | P27: 56 | Q27: 001-2024-00664 | R27: 91 | S27: 001-2024-00096 | T27: 126 | U27: 001-2024-00415 | W27: 002-2024-00068 | Y27: 002-2024-00159 | AA27: 002-2024-00244 | AC27: 002-2024-00334 | AE27: 002-2024-00430
C28: 22 | D28: 002-2024-00570 | M28: 22 | N28: 001-2024-00279 | P28: 57 | Q28: 001-2024-00665 | R28: 92 | S28: 001-2024-00127 | T28: 127 | U28: 001-2024-00416 | W28: 002-2024-00071 | Y28: 002-2024-00161 | AA28: 002-2024-00250 | AC28: 002-2024-00347 | AE28: 002-2024-00432
C29: 23 | D29: 002-2024-00572 | M29: 23 | N29: 001-2024-00282 | P29: 58 | Q29: 001-2024-00669 | R29: 93 | S29: 001-2024-00138 | T29: 128 | U29: 001-2024-00417 | W29: 002-2024-00072 | Y29: 002-2024-00165 | AA29: 002-2024-00251 | AC29: 002-2024-00348 | AE29: 002-2024-00437
C30: 24 | D30: 002-2024-00679 | M30: 24 | N30: 001-2024-00297 | P30: 59 | Q30: 001-2024-00685 | R30: 94 | S30: 001-2024-00144 | T30: 129 | U30: 001-2024-00428 | W30: 002-2024-00073 | Y30: 002-2024-00167 | AA30: 002-2024-00252 | AC30: 002-2024-00350 | AE30: 002-2024-00442
C31: 25 | D31: 002-2024-00702 | M31: 25 | N31: 001-2024-00312 | P31: 60 | Q31: 001-2024-00701 | R31: 95 | S31: 001-2024-00154 | T31: 130 | U31: 001-2024-00435 | W31: 002-2024-00077 | Y31: 002-2024-00169 | AA31: 002-2024-00253 | AC31: 002-2024-00353 | AE31: 002-2024-00448
M32: 26 | N32: 001-2024-00319 | P32: 61 | Q32: 001-2024-00719 | R32: 96 | S32: 001-2024-00172 | T32: 131 | U32: 001-2024-00440 | W32: 002-2024-00078 | Y32: 002-2024-00171 | AA32: 002-2024-00257 | AC32: 002-2024-00356 | AE32: 002-2024-00449
M33: 27 | N33: 001-2024-00370 | P33: 62 | Q33: 001-2024-00723 | R33: 97 | S33: 001-2024-00176 | T33: 132 | U33: 001-2024-00446 | W33: 002-2024-00080 | Y33: 002-2024-00172 | AA33: 002-2024-00259 | AC33: 002-2024-00360 | AE33: 002-2024-00451
M34: 28 | N34: 001-2024-00385 | P34: 63 | Q34: 001-2024-00724 | R34: 98 | S34: 001-2024-00181 | T34: 133 | U34: 001-2024-00477 | W34: 002-2024-00083 | Y34: 002-2024-00173 | AA34: 002-2024-00260 | AC34: 002-2024-00365 | AE34: 002-2024-00452
M35: 29 | N35: 001-2024-00394 | P35: 64 | Q35: 001-2024-00727 | R35: 99 | S35: 001-2024-00197 | T35: 134 | U35: 001-2024-00483 | W35: 002-2024-00089 | Y35: 002-2024-00175 | AA35: 002-2024-00262 | AC35: 002-2024-00367 | AE35: 002-2024-00455
M36: 30 | N36: 001-2024-00432 | P36: 65 | Q36: 001-2024-00729 | R36: 100 | S36: 001-2024-00211 | T36: 135 | U36: 001-2024-00489 | W36: 002-2024-00092 | Y36: 002-2024-00179 | AA36: 002-2024-00264 | AC36: 002-2024-00369 | AE36: 002-2024-00456
M37: 31 | N37: 001-2024-00448 | P37: 66 | Q37: 001-2024-00735 | R37: 101 | S37: 001-2024-00215 | T37: 136 | U37: 001-2024-00494 | W37: 002-2024-00097 | Y37: 002-2024-00182 | AA37: 002-2024-00265 | AC37: 002-2024-00371 | AE37: 002-2024-00457
M38: 32 | N38: 001-2024-00449 | P38: 67 | Q38: 001-2024-00736 | R38: 102 | S38: 001-2024-00230 | T38: 137 | U38: 001-2024-00504 | W38: 002-2024-00102 | Y38: 002-2024-00188 | AA38: 002-2024-00270 | AC38: 002-2024-00372 | AE38: 002-2024-00460
M39: 33 | N39: 001-2024-00455 | P39: 68 | Q39: 001-2024-00742 | R39: 103 | S39: 001-2024-00242 | T39: 138 | U39: 001-2024-00529 | W39: 002-2024-00103 | Y39: 002-2024-00190 | AA39: 002-2024-00273 | AC39: 002-2024-00373 | AE39: 002-2024-00464
M40: 34 | N40: 001-2024-00468 | P40: 69 | Q40: 001-2024-00744 | R40: 104 | S40: 001-2024-00257 | T40: 139 | U40: 001-2024-00533 | W40: 002-2024-00107 | Y40: 002-2024-00193 | AA40: 002-2024-00274 | AC40: 002-2024-00375 | AE40: 002-2024-00465
M41: 35 | N41: 001-2024-00482 | P41: 70 | Q41: 001-2024-00746 | R41: 105 | S41: 001-2024-00262 | T41: 140 | U41: 001-2024-00569 | W41: 002-2024-00108 | Y41: 002-2024-00195 | AA41: 002-2024-00275 | AC41: 002-2024-00376 | AE41: 002-2024-00471
Y42: 002-2024-00180
B44: X REPARTO
B47: 0 | D47: (FIL6251) DECLARATIVOS VERBAL RESTITUCIÓN DE INMUEBLE ARRENDADO | F47: (FIL6253) DECLARATIVOS VERBAL OTROS PROCESOS | H47: 0 | J47: (FIL6257) DECLARATIVOS VERBAL SUMARIO OTROS PROCESOS | L47: (FIL5547) DECLARATIVOS ESPECIALES DIVISORIO | N47: (FIL102) EJECUTIVOS | R47: (FIL5548) EJECUTIVOS CON GARANTÍA REAL | T47: (FIL2062) MONITORIO | V47: (FIL5214) INSOLVENCIA DE LA PERSONA NATURAL NO COMERCIANTE | X47: (FIL76) PROCESOS DE LIQUIDACIÓN - SUCESIÓN | AC47: (FIL4730) DESPACHOS COMISORIOS | AE47: (FIL144) PRUEBAS ANTICIPADAS | AG47: (FIL680) OTROS ASUNTOS - GARANTIAS | AI47: Otros Asuntos- Solicitud Entrega | AK47: Otros asuntos - Designacion Administrador
C48: 1 | D48: 2024-00002 | E48: 1 | F48: 2024-00119 | I48: 1 | J48: 2024-00031 | K48: 1 | L48: 2024-00065 | Q48: 1 | R48: 2024-00086 | S48: 1 | T48: 2024-00043 | U48: 1 | V48: 2024-00089 | W48: 1 | X48: 2024-00243 | AB48: 1 | AC48: 16-2021-00080 | AD48: 1 | AE48: 2024-00170 | AF48: 1 | AG48: 2024-00016 | AH48: 1 | AI48: 2024-00029 | AJ48: 1 | AK48: 2024-00168
C49: 2 | D49: 2024-00012 | E49: 2 | F49: 2024-00142 | I49: 2 | J49: 2024-00037 | N49: Se inicia el trimestre con 3: 24-6, 24 -9, 24-11 | Q49: 2 | R49: 2024-00104 | U49: 2 | V49: 2024-00165 | X49: El trimestre se inició con 1, 2024-0004 | AB49: 2 | AC49: 021-2024-00205 | AF49: 2 | AG49: 2024-00052 | AH49: 2 | AI49: 2024-00045
C50: 3 | D50: 2024-00127 | E50: 3 | F50: 2024-00159 | I50: 3 | J50: 2024-00073 | Q50: 3 | R50: 2024-00123 | U50: 3 | V50: 2024-00223 | AB50: 3 | AC50: 012-2024-00089 | AF50: 3 | AG50: 2024-00055 | AH50: 3 | AI50: 2024-00094
C51: 4 | D51: 2024-00145 | E51: 4 | F51: 2024-00206 | I51: 4 | J51: 2024-00077 | M51: 1 | N51: 2024-00017 | Q51: 4 | R51: 2024-00138 | U51: 4 | V51: 2024-00232 | AB51: 4 | AC51: 020-2024-00404 | AF51: 4 | AG51: 2024-00063 | AH51: 4 | AI51: 2024-00115
C52: 5 | D52: 2024-00180 | I52: 5 | J52: 2024-00199 | M52: 2 | N52: 2024-00018 | Q52: 5 | R52: 2024-00148 | AB52: 5 | AC52: 020-2024-00316 | AF52: 5 | AG52: 2024-00070 | AH52: 5 | AI52: 2024-00235
C53: 6 | D53: 2024-00221 | I53: 6 | J53: 2024-00217 | M53: 3 | N53: 2024-00020 | Q53: 6 | R53: 2024-00209 | V53: El trimestre se inicio con 2, 2024-3, 2024-8 | AB53: 6 | AC53: 001-2024-00749 | AF53: 6 | AG53: 2024-00074
C54: 7 | D54: 2024-00240 | I54: 7 | J54: 2024-00278 | M54: 4 | N54: 2024-00022 | Q54: 7 | R54: 2024-00213 | AB54: 7 | AC54: 029-2023-00786 | AF54: 7 | AG54: 2024-00076
C55: 8 | D55: 2024-00248 | M55: 5 | N55: 2024-00024 | AB55: 8 | AC55: 001-2024-00590 | AF55: 8 | AG55: 2024-00133
M56: 6 | N56: 2024-00026 | AC56: Se inicia el trimestre con 1, 003-2024-00704 | AF56: 9 | AG56: 2024-00141
M57: 7 | N57: 2024-00028 | AF57: 10 | AG57: 2024-00151
M58: 8 | N58: 2024-00030 | AF58: 11 | AG58: 2024-00174
M59: 9 | N59: 2024-00034 | AF59: 12 | AG59: 2024-00184
M60: 10 | N60: 2024-00035 | AF60: 13 | AG60: 2024-00192
M61: 11 | N61: 2024-00038 | AF61: 14 | AG61: 2024-00195
M62: 12 | N62: 2024-00040 | AF62: 15 | AG62: 2024-00202
M63: 13 | N63: 2024-00041 | AF63: 16 | AG63: 2024-00215
M64: 14 | N64: 2024-00044 | AF64: 17 | AG64: 2024-00238
M65: 15 | N65: 2024-00046 | AF65: 18 | AG65: 2024-00262
M66: 16 | N66: 2024-00049 | AF66: 19 | AG66: 2024-00271
M67: 17 | N67: 2024-00051
M68: 18 | N68: 2024-00053
M69: 19 | N69: 2024-00054
M70: 20 | N70: 2024-00057
M71: 21 | N71: 2024-00059
M72: 22 | N72: 2024-00061
M73: 23 | N73: 2024-00062
M74: 24 | N74: 2024-00064
M75: 25 | N75: 2024-00067
M76: 26 | N76: 2024-00068
M77: 27 | N77: 2024-00072
M78: 28 | N78: 2024-00075
... M186: 136 | N186: 2024-00282
